Workbook

Sheet README
B2: Stripe × Xero Financial Dashboard
B3: FY2025 · Multi-currency · Live formulas · Meta discount add-back
B6: PURPOSE
B7: This workbook consolidates financial data from Stripe, Xero, Bank statements, and Meta (Facebook/WhatsApp) invoices into a single live-formula dashboard. It tracks revenue across WhatsApp, Subscription, and Development streams; monitors receivables for UAE and Singapore entities; and applies a special Meta discount add-back logic so each customer shows a single net Meta cost. Every derived number is a live Excel formula — paste raw rows into the input sheets and every dashboard, KPI, and chart updates automatically.
B13: DATA FLOW
B15: ① PASTE | C15: Raw_Stripe, Raw_Xero, Raw_Bank, Raw_Meta | D15: Drop your exports / CSV rows into these four input sheets.
B17: ② CONFIG | C17: Settings_FX | D17: Edit FX rates monthly, maintain customer master, set company names.
B19: ③ CALCULATE | C19: Revenue_Dashboard, Meta_Expenses, PnL_Statement | D19: Live SUMIFS formulas aggregate raw rows by month, category, customer.
B21: ④ MONITOR | C21: Receivables_Aging | D21: A/R aging by customer across UAE & Singapore entities.
B23: ⑤ REVIEW | C23: Executive_Summary | D23: KPI cards + trend charts for the leadership view.
B25: ⑥ AUDIT | C25: Formula_Audit | D25: Every key formula listed with its description for transparency.
B28: META DISCOUNT ADD-BACK LOGIC
B29: Meta invoices typically show: • Gross Billed (list price) • Discount Given (credit applied by Meta) • Net Paid (amount actually charged to your card = Gross − Discount) Add-Back Formula: Amount_With_AddBack = Net_Paid + Discount_Given This reverses the discount so the dashboard shows the full gross charge per customer — useful for cost-pass-through billing and customer profitability analysis where the discount is yours, not your customer's.
B35: MULTI-CURRENCY HANDLING
B36: Each raw transaction keeps its NATIVE currency (USD, AED, SGD, EUR). A USD-equivalent column on every raw sheet converts via the monthly FX rate table in Settings_FX using: Amount_USD = Amount × FX_Rate(month, currency). Update the FX rate table once per month — every downstream USD total refreshes automatically. Native-currency subtotals are preserved on each dashboard for entity-level reporting (UAE books in AED, Singapore books in SGD).
B42: SHEET DIRECTORY
B44: Settings_FX | C44: FX rates, customer master, company config, category map
B45: Raw_Stripe | C45: Stripe transaction paste-zone (with Void/Draft/Unsent statuses)
B46: Raw_Xero | C46: Xero journal paste-zone (P&L opex)
B47: Raw_Xero_Invoices | C47: Xero customer invoice paste-zone (with Void/Draft/Unsent/AwaitPay)
B48: Raw_Bank | C48: Bank statement paste-zone
B49: Raw_Meta | C49: Meta invoice paste-zone (with discount add-back)
B50: Revenue_Dashboard | C50: Revenue by 4 categories × month + bar + pie charts
B51: Receivables_Aging | C51: A/R aging by customer (UAE & SG) — 0-30/31-60/60+ buckets
B52: Customer_Receivables | C52: ★ Per-customer invoice status breakdown — Xero + Stripe
B53: Meta_Expenses | C53: Meta cost per customer with add-back
B54: PnL_Statement | C54: Monthly P&L — 4 revenue categories − Meta − OpEx
B55: Executive_Summary | C55: KPI cards + trend charts
B56: Formula_Audit | C56: Every key formula documented

Sheet Executive_Summary
B2: Executive Summary · FY2025 YTD
B3: Stripe × Xero consolidated financial snapshot — live from Raw sheets
B5: TOTAL REVENUE YTD | E5: TOTAL EXPENSES YTD | H5: NET PROFIT YTD | K5: GROSS MARGIN YTD
B6: =PnL_Statement!O11 -> 218895.77 | E6: =PnL_Statement!O15+PnL_Statement!O24 -> 359508.91 | H6: =PnL_Statement!O26 -> -140613.14 | K6: =PnL_Statement!P16 -> 0.38966386
B9: NET PROFIT MARGIN | E9: A/R OUTSTANDING (USD) | H9: META COST YTD (ADD-BACK) | K9: META DISCOUNTS CAPTURED
B10: =PnL_Statement!P26 -> -0.64237488 | E10: =SUM(Raw_Stripe!L6:L49) -> 72647.4 | H10: =SUM(Raw_Meta!L6:L28) -> 133600 | K10: =SUMPRODUCT(Raw_Meta!H6:H28,Raw_Meta!G6:G28)/SUMIF(Raw_Meta!G6:G28,">0",Raw_Meta!G6:G28)*SUM(Raw_Meta!H6:H28) -> 6355179.6
B13: MONTHLY SNAPSHOT
B14: Month | C14: Revenue | D14: Meta Cost | E14: OpEx | F14: Net Profit | G14: Margin %
B15: Jan-25 | C15: =PnL_Statement!C11 -> 25737.51 | D15: =PnL_Statement!C15 -> 19700 | E15: =PnL_Statement!C24 -> 39635.515 | F15: =PnL_Statement!C26 -> -33598.005 | G15: =IFERROR(F15/C15,0) -> -1.3054101
B16: Feb-25 | C16: =PnL_Statement!D11 -> 23034.3 | D16: =PnL_Statement!D15 -> 16300 | E16: =PnL_Statement!D24 -> 40616.45 | F16: =PnL_Statement!D26 -> -33882.15 | G16: =IFERROR(F16/C16,0) -> -1.4709433
B17: Mar-25 | C17: =PnL_Statement!E11 -> 26464.44 | D17: =PnL_Statement!E15 -> 30300 | E17: =PnL_Statement!E24 -> 42515.19 | F17: =PnL_Statement!E26 -> -46350.75 | G17: =IFERROR(F17/C17,0) -> -1.7514351
B18: Apr-25 | C18: =PnL_Statement!F11 -> 13088.26 | D18: =PnL_Statement!F15 -> 9300 | E18: =PnL_Statement!F24 -> 42458.97 | F18: =PnL_Statement!F26 -> -38670.71 | G18: =IFERROR(F18/C18,0) -> -2.9546105
B19: May-25 | C19: =PnL_Statement!G11 -> 12589.43 | D19: =PnL_Statement!G15 -> 17300 | E19: =PnL_Statement!G24 -> 18858.3 | F19: =PnL_Statement!G26 -> -23568.87 | G19: =IFERROR(F19/C19,0) -> -1.8721157
B20: Jun-25 | C20: =PnL_Statement!H11 -> 33888.23 | D20: =PnL_Statement!H15 -> 12400 | E20: =PnL_Statement!H24 -> 20190.47 | F20: =PnL_Statement!H26 -> 1297.76 | G20: =IFERROR(F20/C20,0) -> 0.038295302
B21: Jul-25 | C21: =PnL_Statement!I11 -> 12773.75 | D21: =PnL_Statement!I15 -> 14000 | E21: =PnL_Statement!I24 -> 21003.45 | F21: =PnL_Statement!I26 -> -22229.7 | G21: =IFERROR(F21/C21,0) -> -1.7402642
B22: Aug-25 | C22: =PnL_Statement!J11 -> 10331 | D22: =PnL_Statement!J15 -> 4500 | E22: =PnL_Statement!J24 -> 332.6 | F22: =PnL_Statement!J26 -> 5498.4 | G22: =IFERROR(F22/C22,0) -> 0.53222341
B23: Sep-25 | C23: =PnL_Statement!K11 -> 13051.64 | D23: =PnL_Statement!K15 -> 9800 | E23: =PnL_Statement!K24 -> 297.97 | F23: =PnL_Statement!K26 -> 2953.67 | G23: =IFERROR(F23/C23,0) -> 0.22630643
B24: Oct-25 | C24: =PnL_Statement!L11 -> 26314.55 | D24: =PnL_Statement!L15 -> 0 | E24: =PnL_Statement!L24 -> 0 | F24: =PnL_Statement!L26 -> 26314.55 | G24: =IFERROR(F24/C24,0) -> 1
B25: Nov-25 | C25: =PnL_Statement!M11 -> 10979 | D25: =PnL_Statement!M15 -> 0 | E25: =PnL_Statement!M24 -> 0 | F25: =PnL_Statement!M26 -> 10979 | G25: =IFERROR(F25/C25,0) -> 1
B26: Dec-25 | C26: =PnL_Statement!N11 -> 10643.66 | D26: =PnL_Statement!N15 -> 0 | E26: =PnL_Statement!N24 -> 0 | F26: =PnL_Statement!N26 -> 10643.66 | G26: =IFERROR(F26/C26,0) -> 1
B27: YTD TOTAL | C27: =SUM(C15:C26) -> 218895.77 | D27: =SUM(D15:D26) -> 133600 | E27: =SUM(E15:E26) -> 225908.92 | F27: =SUM(F15:F26) -> -140613.14 | G27: =IFERROR(F27/C27,0) -> -0.64237488
B30: REVENUE vs EXPENSES TREND
B54: NET PROFIT BY MONTH

Sheet Revenue_Dashboard
B2: Revenue Dashboard · FY2025
B3: Live SUMIFS by category × month — auto-updates from Raw_Stripe
B5: REVENUE BY CATEGORY × MONTH (USD equivalent)
B6: Category | C6: Jan-25 | D6: Feb-25 | E6: Mar-25 | F6: Apr-25 | G6: May-25 | H6: Jun-25 | I6: Jul-25 | J6: Aug-25 | K6: Sep-25 | L6: Oct-25 | M6: Nov-25 | N6: Dec-25 | O6: YTD Total
B7: WhatsApp | C7: =SUMIFS(Raw_Stripe!$H$6:$H$49,Raw_Stripe!$M$6:$M$49,"Jan-25",Raw_Stripe!$N$6:$N$49,"WhatsApp") -> 4202.01 | D7: =SUMIFS(Raw_Stripe!$H$6:$H$49,Raw_Stripe!$M$6:$M$49,"Feb-25",Raw_Stripe!$N$6:$N$49,"WhatsApp") -> 3825.85 | E7: =SUMIFS(Raw_Stripe!$H$6:$H$49,Raw_Stripe!$M$6:$M$49,"Mar-25",Raw_Stripe!$N$6:$N$49,"WhatsApp") -> 4625.64 | F7: =SUMIFS(Raw_Stripe!$H$6:$H$49,Raw_Stripe!$M$6:$M$49,"Apr-25",Raw_Stripe!$N$6:$N$49,"WhatsApp") -> 1279.81 | G7: =SUMIFS(Raw_Stripe!$H$6:$H$49,Raw_Stripe!$M$6:$M$49,"May-25",Raw_Stripe!$N$6:$N$49,"WhatsApp") -> 1334.27 | H7: =SUMIFS(Raw_Stripe!$H$6:$H$49,Raw_Stripe!$M$6:$M$49,"Jun-25",Raw_Stripe!$N$6:$N$49,"WhatsApp") -> 7061.03 | I7: =SUMIFS(Raw_Stripe!$H$6:$H$49,Raw_Stripe!$M$6:$M$49,"Jul-25",Raw_Stripe!$N$6:$N$49,"WhatsApp") -> 1415.96 | J7: =SUMIFS(Raw_Stripe!$H$6:$H$49,Raw_Stripe!$M$6:$M$49,"Aug-25",Raw_Stripe!$N$6:$N$49,"WhatsApp") -> 2831 | K7: =SUMIFS(Raw_Stripe!$H$6:$H$49,Raw_Stripe!$M$6:$M$49,"Sep-25",Raw_Stripe!$N$6:$N$49,"WhatsApp") -> 1851.64 | L7: =SUMIFS(Raw_Stripe!$H$6:$H$49,Raw_Stripe!$M$6:$M$49,"Oct-25",Raw_Stripe!$N$6:$N$49,"WhatsApp") -> 0 | M7: =SUMIFS(Raw_Stripe!$H$6:$H$49,Raw_Stripe!$M$6:$M$49,"Nov-25",Raw_Stripe!$N$6:$N$49,"WhatsApp") -> 3135.3 | N7: =SUMIFS(Raw_Stripe!$H$6:$H$49,Raw_Stripe!$M$6:$M$49,"Dec-25",Raw_Stripe!$N$6:$N$49,"WhatsApp") -> 0 | O7: =SUM(C7:N7) -> 31562.51
B8: Subscription | C8: =SUMIFS(Raw_Stripe!$H$6:$H$49,Raw_Stripe!$M$6:$M$49,"Jan-25",Raw_Stripe!$N$6:$N$49,"Subscription") -> 13782.45 | D8: =SUMIFS(Raw_Stripe!$H$6:$H$49,Raw_Stripe!$M$6:$M$49,"Feb-25",Raw_Stripe!$N$6:$N$49,"Subscription") -> 408.45 | E8: =SUMIFS(Raw_Stripe!$H$6:$H$49,Raw_Stripe!$M$6:$M$49,"Mar-25",Raw_Stripe!$N$6:$N$49,"Subscription") -> 408.45 | F8: =SUMIFS(Raw_Stripe!$H$6:$H$49,Raw_Stripe!$M$6:$M$49,"Apr-25",Raw_Stripe!$N$6:$N$49,"Subscription") -> 2608.45 | G8: =SUMIFS(Raw_Stripe!$H$6:$H$49,Raw_Stripe!$M$6:$M$49,"May-25",Raw_Stripe!$N$6:$N$49,"Subscription") -> 1339.2 | H8: =SUMIFS(Raw_Stripe!$H$6:$H$49,Raw_Stripe!$M$6:$M$49,"Jun-25",Raw_Stripe!$N$6:$N$49,"Subscription") -> 24000 | I8: =SUMIFS(Raw_Stripe!$H$6:$H$49,Raw_Stripe!$M$6:$M$49,"Jul-25",Raw_Stripe!$N$6:$N$49,"Subscription") -> 0 | J8: =SUMIFS(Raw_Stripe!$H$6:$H$49,Raw_Stripe!$M$6:$M$49,"Aug-25",Raw_Stripe!$N$6:$N$49,"Subscription") -> 0 | K8: =SUMIFS(Raw_Stripe!$H$6:$H$49,Raw_Stripe!$M$6:$M$49,"Sep-25",Raw_Stripe!$N$6:$N$49,"Subscription") -> 0 | L8: =SUMIFS(Raw_Stripe!$H$6:$H$49,Raw_Stripe!$M$6:$M$49,"Oct-25",Raw_Stripe!$N$6:$N$49,"Subscription") -> 24000 | M8: =SUMIFS(Raw_Stripe!$H$6:$H$49,Raw_Stripe!$M$6:$M$49,"Nov-25",Raw_Stripe!$N$6:$N$49,"Subscription") -> 1343.7 | N8: =SUMIFS(Raw_Stripe!$H$6:$H$49,Raw_Stripe!$M$6:$M$49,"Dec-25",Raw_Stripe!$N$6:$N$49,"Subscription") -> 0 | O8: =SUM(C8:N8) -> 67890.7
B9: Development | C9: =SUMIFS(Raw_Stripe!$H$6:$H$49,Raw_Stripe!$M$6:$M$49,"Jan-25",Raw_Stripe!$N$6:$N$49,"Development") -> 6800 | D9: =SUMIFS(Raw_Stripe!$H$6:$H$49,Raw_Stripe!$M$6:$M$49,"Feb-25",Raw_Stripe!$N$6:$N$49,"Development") -> 12000 | E9: =SUMIFS(Raw_Stripe!$H$6:$H$49,Raw_Stripe!$M$6:$M$49,"Mar-25",Raw_Stripe!$N$6:$N$49,"Development") -> 18086.85 | F9: =SUMIFS(Raw_Stripe!$H$6:$H$49,Raw_Stripe!$M$6:$M$49,"Apr-25",Raw_Stripe!$N$6:$N$49,"Development") -> 0 | G9: =SUMIFS(Raw_Stripe!$H$6:$H$49,Raw_Stripe!$M$6:$M$49,"May-25",Raw_Stripe!$N$6:$N$49,"Development") -> 8500 | H9: =SUMIFS(Raw_Stripe!$H$6:$H$49,Raw_Stripe!$M$6:$M$49,"Jun-25",Raw_Stripe!$N$6:$N$49,"Development") -> 0 | I9: =SUMIFS(Raw_Stripe!$H$6:$H$49,Raw_Stripe!$M$6:$M$49,"Jul-25",Raw_Stripe!$N$6:$N$49,"Development") -> 10050.75 | J9: =SUMIFS(Raw_Stripe!$H$6:$H$49,Raw_Stripe!$M$6:$M$49,"Aug-25",Raw_Stripe!$N$6:$N$49,"Development") -> 0 | K9: =SUMIFS(Raw_Stripe!$H$6:$H$49,Raw_Stripe!$M$6:$M$49,"Sep-25",Raw_Stripe!$N$6:$N$49,"Development") -> 11200 | L9: =SUMIFS(Raw_Stripe!$H$6:$H$49,Raw_Stripe!$M$6:$M$49,"Oct-25",Raw_Stripe!$N$6:$N$49,"Development") -> 2314.55 | M9: =SUMIFS(Raw_Stripe!$H$6:$H$49,Raw_Stripe!$M$6:$M$49,"Nov-25",Raw_Stripe!$N$6:$N$49,"Development") -> 0 | N9: =SUMIFS(Raw_Stripe!$H$6:$H$49,Raw_Stripe!$M$6:$M$49,"Dec-25",Raw_Stripe!$N$6:$N$49,"Development") -> 9500 | O9: =SUM(C9:N9) -> 78452.15
B10: Other Services | C10: =SUMIFS(Raw_Stripe!$H$6:$H$49,Raw_Stripe!$M$6:$M$49,"Jan-25",Raw_Stripe!$N$6:$N$49,"Other Services") -> 953.05 | D10: =SUMIFS(Raw_Stripe!$H$6:$H$49,Raw_Stripe!$M$6:$M$49,"Feb-25",Raw_Stripe!$N$6:$N$49,"Other Services") -> 6800 | E10: =SUMIFS(Raw_Stripe!$H$6:$H$49,Raw_Stripe!$M$6:$M$49,"Mar-25",Raw_Stripe!$N$6:$N$49,"Other Services") -> 3343.5 | F10: =SUMIFS(Raw_Stripe!$H$6:$H$49,Raw_Stripe!$M$6:$M$49,"Apr-25",Raw_Stripe!$N$6:$N$49,"Other Services") -> 9200 | G10: =SUMIFS(Raw_Stripe!$H$6:$H$49,Raw_Stripe!$M$6:$M$49,"May-25",Raw_Stripe!$N$6:$N$49,"Other Services") -> 1415.96 | H10: =SUMIFS(Raw_Stripe!$H$6:$H$49,Raw_Stripe!$M$6:$M$49,"Jun-25",Raw_Stripe!$N$6:$N$49,"Other Services") -> 2827.2 | I10: =SUMIFS(Raw_Stripe!$H$6:$H$49,Raw_Stripe!$M$6:$M$49,"Jul-25",Raw_Stripe!$N$6:$N$49,"Other Services") -> 1307.04 | J10: =SUMIFS(Raw_Stripe!$H$6:$H$49,Raw_Stripe!$M$6:$M$49,"Aug-25",Raw_Stripe!$N$6:$N$49,"Other Services") -> 7500 | K10: =SUMIFS(Raw_Stripe!$H$6:$H$49,Raw_Stripe!$M$6:$M$49,"Sep-25",Raw_Stripe!$N$6:$N$49,"Other Services") -> 0 | L10: =SUMIFS(Raw_Stripe!$H$6:$H$49,Raw_Stripe!$M$6:$M$49,"Oct-25",Raw_Stripe!$N$6:$N$49,"Other Services") -> 0 | M10: =SUMIFS(Raw_Stripe!$H$6:$H$49,Raw_Stripe!$M$6:$M$49,"Nov-25",Raw_Stripe!$N$6:$N$49,"Other Services") -> 6500 | N10: =SUMIFS(Raw_Stripe!$H$6:$H$49,Raw_Stripe!$M$6:$M$49,"Dec-25",Raw_Stripe!$N$6:$N$49,"Other Services") -> 1143.66 | O10: =SUM(C10:N10) -> 40990.41
B11: TOTAL REVENUE | C11: =SUM(C7:C10) -> 25737.51 | D11: =SUM(D7:D10) -> 23034.3 | E11: =SUM(E7:E10) -> 26464.44 | F11: =SUM(F7:F10) -> 13088.26 | G11: =SUM(G7:G10) -> 12589.43 | H11: =SUM(H7:H10) -> 33888.23 | I11: =SUM(I7:I10) -> 12773.75 | J11: =SUM(J7:J10) -> 10331 | ... N11: =SUM(N7:N10) -> 10643.66 | O11: =SUM(C11:N11) -> 218895.77
B12: MoM Growth % | C12: — | D12: =IFERROR((D11/C11)-1,"-") -> -0.10502997 | E12: =IFERROR((E11/D11)-1,"-") -> 0.14891444 | F12: =IFERROR((F11/E11)-1,"-") -> -0.50543975 | G12: =IFERROR((G11/F11)-1,"-") -> -0.038112782 | H12: =IFERROR((H11/G11)-1,"-") -> 1.6918002 | I12: =IFERROR((I11/H11)-1,"-") -> -0.62306234 | J12: =IFERROR((J11/I11)-1,"-") -> -0.19123202 | K12: =IFERROR((K11/J11)-1,"-") -> 0.26334721 | ... N12: =IFERROR((N11/M11)-1,"-") -> -0.030543765
B15: REVENUE TREND CHART (clustered bar — categories × months)

Sheet Receivables_Aging
B2: Receivables Aging · UAE & Singapore
B3: Outstanding by customer, bucketed by invoice age — live from Raw_Stripe
B5: UAE Company (UAE)
B6: Customer | C6: Total Outstanding | D6: Current (0-30) | E6: 31-60 days | F6: 60+ days | G6: Currency | H6: USD Equivalent | I6: % of Total | J6: Oldest Inv. | K6: Status
B7: Alphabet Logistics LLC | C7: =SUMIFS(Raw_Stripe!$L$6:$L$49,Raw_Stripe!$D$6:$D$49,B7,Raw_Stripe!$O$6:$O$49,"UAE") -> 10554.5 | D7: =SUMIFS(Raw_Stripe!$L$6:$L$49,Raw_Stripe!$D$6:$D$49,B7,Raw_Stripe!$O$6:$O$49,"UAE",Raw_Stripe!$C$6:$C$49,">="&(TODAY()-30)) -> 0 | E7: =SUMIFS(Raw_Stripe!$L$6:$L$49,Raw_Stripe!$D$6:$D$49,B7,Raw_Stripe!$O$6:$O$49,"UAE",Raw_Stripe!$C$6:$C$49,">="&(TODAY()-60),Raw_Stripe!$C$6:$C$49,"<"&(TODAY()-30)) -> 0 | F7: =SUMIFS(Raw_Stripe!$L$6:$L$49,Raw_Stripe!$D$6:$D$49,B7,Raw_Stripe!$O$6:$O$49,"UAE",Raw_Stripe!$C$6:$C$49,"<"&(TODAY()-60)) -> 10554.5 | G7: AED | H7: =C7*Settings_FX!D$27 -> 2873.9904 | I7: =IFERROR(C7/$C$15,0) -> 0.28104488 | J7: =IFERROR(minifs(Raw_Stripe!$C$6:$C$49,Raw_Stripe!$D$6:$D$49,B7,Raw_Stripe!$L$6:$L$49,">0"),"") | K7: =IF(F7>0,"⚠ 60+ days",IF(E7>0,"⚠ 31-60 days","✓ Current")) -> ⚠ 60+ days
B8: Emirates Retail Group | C8: =SUMIFS(Raw_Stripe!$L$6:$L$49,Raw_Stripe!$D$6:$D$49,B8,Raw_Stripe!$O$6:$O$49,"UAE") -> 4200 | D8: =SUMIFS(Raw_Stripe!$L$6:$L$49,Raw_Stripe!$D$6:$D$49,B8,Raw_Stripe!$O$6:$O$49,"UAE",Raw_Stripe!$C$6:$C$49,">="&(TODAY()-30)) -> 0 | E8: =SUMIFS(Raw_Stripe!$L$6:$L$49,Raw_Stripe!$D$6:$D$49,B8,Raw_Stripe!$O$6:$O$49,"UAE",Raw_Stripe!$C$6:$C$49,">="&(TODAY()-60),Raw_Stripe!$C$6:$C$49,"<"&(TODAY()-30)) -> 0 | F8: =SUMIFS(Raw_Stripe!$L$6:$L$49,Raw_Stripe!$D$6:$D$49,B8,Raw_Stripe!$O$6:$O$49,"UAE",Raw_Stripe!$C$6:$C$49,"<"&(TODAY()-60)) -> 4200 | G8: AED | H8: =C8*Settings_FX!D$27 -> 1143.66 | I8: =IFERROR(C8/$C$15,0) -> 0.11183746 | J8: =IFERROR(minifs(Raw_Stripe!$C$6:$C$49,Raw_Stripe!$D$6:$D$49,B8,Raw_Stripe!$L$6:$L$49,">0"),"") | K8: =IF(F8>0,"⚠ 60+ days",IF(E8>0,"⚠ 31-60 days","✓ Current")) -> ⚠ 60+ days
B9: Gulf Tech Distribution | C9: =SUMIFS(Raw_Stripe!$L$6:$L$49,Raw_Stripe!$D$6:$D$49,B9,Raw_Stripe!$O$6:$O$49,"UAE") -> 9500 | D9: =SUMIFS(Raw_Stripe!$L$6:$L$49,Raw_Stripe!$D$6:$D$49,B9,Raw_Stripe!$O$6:$O$49,"UAE",Raw_Stripe!$C$6:$C$49,">="&(TODAY()-30)) -> 0 | E9: =SUMIFS(Raw_Stripe!$L$6:$L$49,Raw_Stripe!$D$6:$D$49,B9,Raw_Stripe!$O$6:$O$49,"UAE",Raw_Stripe!$C$6:$C$49,">="&(TODAY()-60),Raw_Stripe!$C$6:$C$49,"<"&(TODAY()-30)) -> 0 | F9: =SUMIFS(Raw_Stripe!$L$6:$L$49,Raw_Stripe!$D$6:$D$49,B9,Raw_Stripe!$O$6:$O$49,"UAE",Raw_Stripe!$C$6:$C$49,"<"&(TODAY()-60)) -> 9500 | G9: USD | H9: =C9 -> 9500 | I9: =IFERROR(C9/$C$15,0) -> 0.25296569 | J9: =IFERROR(minifs(Raw_Stripe!$C$6:$C$49,Raw_Stripe!$D$6:$D$49,B9,Raw_Stripe!$L$6:$L$49,">0"),"") | K9: =IF(F9>0,"⚠ 60+ days",IF(E9>0,"⚠ 31-60 days","✓ Current")) -> ⚠ 60+ days
B10: Dubai Properties Co | C10: =SUMIFS(Raw_Stripe!$L$6:$L$49,Raw_Stripe!$D$6:$D$49,B10,Raw_Stripe!$O$6:$O$49,"UAE") -> 0 | D10: =SUMIFS(Raw_Stripe!$L$6:$L$49,Raw_Stripe!$D$6:$D$49,B10,Raw_Stripe!$O$6:$O$49,"UAE",Raw_Stripe!$C$6:$C$49,">="&(TODAY()-30)) -> 0 | E10: =SUMIFS(Raw_Stripe!$L$6:$L$49,Raw_Stripe!$D$6:$D$49,B10,Raw_Stripe!$O$6:$O$49,"UAE",Raw_Stripe!$C$6:$C$49,">="&(TODAY()-60),Raw_Stripe!$C$6:$C$49,"<"&(TODAY()-30)) -> 0 | F10: =SUMIFS(Raw_Stripe!$L$6:$L$49,Raw_Stripe!$D$6:$D$49,B10,Raw_Stripe!$O$6:$O$49,"UAE",Raw_Stripe!$C$6:$C$49,"<"&(TODAY()-60)) -> 0 | G10: AED | H10: =C10*Settings_FX!D$27 -> 0 | I10: =IFERROR(C10/$C$15,0) -> 0 | J10: =IFERROR(minifs(Raw_Stripe!$C$6:$C$49,Raw_Stripe!$D$6:$D$49,B10,Raw_Stripe!$L$6:$L$49,">0"),"") | K10: =IF(F10>0,"⚠ 60+ days",IF(E10>0,"⚠ 31-60 days","✓ Current")) -> ✓ Current
B11: Abu Dhabi Trading | C11: =SUMIFS(Raw_Stripe!$L$6:$L$49,Raw_Stripe!$D$6:$D$49,B11,Raw_Stripe!$O$6:$O$49,"UAE") -> 0 | D11: =SUMIFS(Raw_Stripe!$L$6:$L$49,Raw_Stripe!$D$6:$D$49,B11,Raw_Stripe!$O$6:$O$49,"UAE",Raw_Stripe!$C$6:$C$49,">="&(TODAY()-30)) -> 0 | E11: =SUMIFS(Raw_Stripe!$L$6:$L$49,Raw_Stripe!$D$6:$D$49,B11,Raw_Stripe!$O$6:$O$49,"UAE",Raw_Stripe!$C$6:$C$49,">="&(TODAY()-60),Raw_Stripe!$C$6:$C$49,"<"&(TODAY()-30)) -> 0 | F11: =SUMIFS(Raw_Stripe!$L$6:$L$49,Raw_Stripe!$D$6:$D$49,B11,Raw_Stripe!$O$6:$O$49,"UAE",Raw_Stripe!$C$6:$C$49,"<"&(TODAY()-60)) -> 0 | G11: AED | H11: =C11*Settings_FX!D$27 -> 0 | I11: =IFERROR(C11/$C$15,0) -> 0 | J11: =IFERROR(minifs(Raw_Stripe!$C$6:$C$49,Raw_Stripe!$D$6:$D$49,B11,Raw_Stripe!$L$6:$L$49,">0"),"") | K11: =IF(F11>0,"⚠ 60+ days",IF(E11>0,"⚠ 31-60 days","✓ Current")) -> ✓ Current
B12: Rak Bank Digital | C12: =SUMIFS(Raw_Stripe!$L$6:$L$49,Raw_Stripe!$D$6:$D$49,B12,Raw_Stripe!$O$6:$O$49,"UAE") -> 6800 | D12: =SUMIFS(Raw_Stripe!$L$6:$L$49,Raw_Stripe!$D$6:$D$49,B12,Raw_Stripe!$O$6:$O$49,"UAE",Raw_Stripe!$C$6:$C$49,">="&(TODAY()-30)) -> 0 | E12: =SUMIFS(Raw_Stripe!$L$6:$L$49,Raw_Stripe!$D$6:$D$49,B12,Raw_Stripe!$O$6:$O$49,"UAE",Raw_Stripe!$C$6:$C$49,">="&(TODAY()-60),Raw_Stripe!$C$6:$C$49,"<"&(TODAY()-30)) -> 0 | F12: =SUMIFS(Raw_Stripe!$L$6:$L$49,Raw_Stripe!$D$6:$D$49,B12,Raw_Stripe!$O$6:$O$49,"UAE",Raw_Stripe!$C$6:$C$49,"<"&(TODAY()-60)) -> 6800 | G12: AED | H12: =C12*Settings_FX!D$27 -> 1851.64 | I12: =IFERROR(C12/$C$15,0) -> 0.18107018 | J12: =IFERROR(minifs(Raw_Stripe!$C$6:$C$49,Raw_Stripe!$D$6:$D$49,B12,Raw_Stripe!$L$6:$L$49,">0"),"") | K12: =IF(F12>0,"⚠ 60+ days",IF(E12>0,"⚠ 31-60 days","✓ Current")) -> ⚠ 60+ days
B13: Global SaaS Inc | C13: =SUMIFS(Raw_Stripe!$L$6:$L$49,Raw_Stripe!$D$6:$D$49,B13,Raw_Stripe!$O$6:$O$49,"UAE") -> 0 | D13: =SUMIFS(Raw_Stripe!$L$6:$L$49,Raw_Stripe!$D$6:$D$49,B13,Raw_Stripe!$O$6:$O$49,"UAE",Raw_Stripe!$C$6:$C$49,">="&(TODAY()-30)) -> 0 | E13: =SUMIFS(Raw_Stripe!$L$6:$L$49,Raw_Stripe!$D$6:$D$49,B13,Raw_Stripe!$O$6:$O$49,"UAE",Raw_Stripe!$C$6:$C$49,">="&(TODAY()-60),Raw_Stripe!$C$6:$C$49,"<"&(TODAY()-30)) -> 0 | F13: =SUMIFS(Raw_Stripe!$L$6:$L$49,Raw_Stripe!$D$6:$D$49,B13,Raw_Stripe!$O$6:$O$49,"UAE",Raw_Stripe!$C$6:$C$49,"<"&(TODAY()-60)) -> 0 | G13: USD | H13: =C13 -> 0 | I13: =IFERROR(C13/$C$15,0) -> 0 | J13: =IFERROR(minifs(Raw_Stripe!$C$6:$C$49,Raw_Stripe!$D$6:$D$49,B13,Raw_Stripe!$L$6:$L$49,">0"),"") | K13: =IF(F13>0,"⚠ 60+ days",IF(E13>0,"⚠ 31-60 days","✓ Current")) -> ✓ Current
B14: Mena Apps FZ-LLC | C14: =SUMIFS(Raw_Stripe!$L$6:$L$49,Raw_Stripe!$D$6:$D$49,B14,Raw_Stripe!$O$6:$O$49,"UAE") -> 6500 | D14: =SUMIFS(Raw_Stripe!$L$6:$L$49,Raw_Stripe!$D$6:$D$49,B14,Raw_Stripe!$O$6:$O$49,"UAE",Raw_Stripe!$C$6:$C$49,">="&(TODAY()-30)) -> 0 | E14: =SUMIFS(Raw_Stripe!$L$6:$L$49,Raw_Stripe!$D$6:$D$49,B14,Raw_Stripe!$O$6:$O$49,"UAE",Raw_Stripe!$C$6:$C$49,">="&(TODAY()-60),Raw_Stripe!$C$6:$C$49,"<"&(TODAY()-30)) -> 0 | F14: =SUMIFS(Raw_Stripe!$L$6:$L$49,Raw_Stripe!$D$6:$D$49,B14,Raw_Stripe!$O$6:$O$49,"UAE",Raw_Stripe!$C$6:$C$49,"<"&(TODAY()-60)) -> 6500 | G14: USD | H14: =C14 -> 6500 | I14: =IFERROR(C14/$C$15,0) -> 0.17308179 | J14: =IFERROR(minifs(Raw_Stripe!$C$6:$C$49,Raw_Stripe!$D$6:$D$49,B14,Raw_Stripe!$L$6:$L$49,">0"),"") | K14: =IF(F14>0,"⚠ 60+ days",IF(E14>0,"⚠ 31-60 days","✓ Current")) -> ⚠ 60+ days
B15: TOTAL UAE | C15: =SUM(C7:C14) -> 37554.5 | D15: =SUM(D7:D14) -> 0 | E15: =SUM(E7:E14) -> 0 | F15: =SUM(F7:F14) -> 37554.5 | H15: =SUM(H7:H14) -> 21869.29
B18: Singapore Company (SG)
B19: Customer | C19: Total Outstanding | D19: Current (0-30) | E19: 31-60 days | F19: 60+ days | G19: Currency | H19: USD Equivalent | I19: % of Total | J19: Oldest Inv. | K19: Status
B20: Singapore FinTech Hub | C20: =SUMIFS(Raw_Stripe!$L$6:$L$49,Raw_Stripe!$D$6:$D$49,B20,Raw_Stripe!$O$6:$O$49,"SG") -> 4200 | D20: =SUMIFS(Raw_Stripe!$L$6:$L$49,Raw_Stripe!$D$6:$D$49,B20,Raw_Stripe!$O$6:$O$49,"SG",Raw_Stripe!$C$6:$C$49,">="&(TODAY()-30)) -> 0 | E20: =SUMIFS(Raw_Stripe!$L$6:$L$49,Raw_Stripe!$D$6:$D$49,B20,Raw_Stripe!$O$6:$O$49,"SG",Raw_Stripe!$C$6:$C$49,">="&(TODAY()-60),Raw_Stripe!$C$6:$C$49,"<"&(TODAY()-30)) -> 0 | F20: =SUMIFS(Raw_Stripe!$L$6:$L$49,Raw_Stripe!$D$6:$D$49,B20,Raw_Stripe!$O$6:$O$49,"SG",Raw_Stripe!$C$6:$C$49,"<"&(TODAY()-60)) -> 4200 | G20: SGD | H20: =C20*Settings_FX!E$27 -> 3137.4 | I20: =IFERROR(C20/$C$27,0) -> 0.11968233 | J20: =IFERROR(minifs(Raw_Stripe!$C$6:$C$49,Raw_Stripe!$D$6:$D$49,B20,Raw_Stripe!$L$6:$L$49,">0"),"") | K20: =IF(F20>0,"⚠ 60+ days",IF(E20>0,"⚠ 31-60 days","✓ Current")) -> ⚠ 60+ days
B21: Asia Pacific Solutions | C21: =SUMIFS(Raw_Stripe!$L$6:$L$49,Raw_Stripe!$D$6:$D$49,B21,Raw_Stripe!$O$6:$O$49,"SG") -> 0 | D21: =SUMIFS(Raw_Stripe!$L$6:$L$49,Raw_Stripe!$D$6:$D$49,B21,Raw_Stripe!$O$6:$O$49,"SG",Raw_Stripe!$C$6:$C$49,">="&(TODAY()-30)) -> 0 | E21: =SUMIFS(Raw_Stripe!$L$6:$L$49,Raw_Stripe!$D$6:$D$49,B21,Raw_Stripe!$O$6:$O$49,"SG",Raw_Stripe!$C$6:$C$49,">="&(TODAY()-60),Raw_Stripe!$C$6:$C$49,"<"&(TODAY()-30)) -> 0 | F21: =SUMIFS(Raw_Stripe!$L$6:$L$49,Raw_Stripe!$D$6:$D$49,B21,Raw_Stripe!$O$6:$O$49,"SG",Raw_Stripe!$C$6:$C$49,"<"&(TODAY()-60)) -> 0 | G21: USD | H21: =C21 -> 0 | I21: =IFERROR(C21/$C$27,0) -> 0 | J21: =IFERROR(minifs(Raw_Stripe!$C$6:$C$49,Raw_Stripe!$D$6:$D$49,B21,Raw_Stripe!$L$6:$L$49,">0"),"") | K21: =IF(F21>0,"⚠ 60+ days",IF(E21>0,"⚠ 31-60 days","✓ Current")) -> ✓ Current
B22: Marina Bay Holdings | C22: =SUMIFS(Raw_Stripe!$L$6:$L$49,Raw_Stripe!$D$6:$D$49,B22,Raw_Stripe!$O$6:$O$49,"SG") -> 1800 | D22: =SUMIFS(Raw_Stripe!$L$6:$L$49,Raw_Stripe!$D$6:$D$49,B22,Raw_Stripe!$O$6:$O$49,"SG",Raw_Stripe!$C$6:$C$49,">="&(TODAY()-30)) -> 0 | E22: =SUMIFS(Raw_Stripe!$L$6:$L$49,Raw_Stripe!$D$6:$D$49,B22,Raw_Stripe!$O$6:$O$49,"SG",Raw_Stripe!$C$6:$C$49,">="&(TODAY()-60),Raw_Stripe!$C$6:$C$49,"<"&(TODAY()-30)) -> 0 | F22: =SUMIFS(Raw_Stripe!$L$6:$L$49,Raw_Stripe!$D$6:$D$49,B22,Raw_Stripe!$O$6:$O$49,"SG",Raw_Stripe!$C$6:$C$49,"<"&(TODAY()-60)) -> 1800 | G22: SGD | H22: =C22*Settings_FX!E$27 -> 1344.6 | I22: =IFERROR(C22/$C$27,0) -> 0.051292427 | J22: =IFERROR(minifs(Raw_Stripe!$C$6:$C$49,Raw_Stripe!$D$6:$D$49,B22,Raw_Stripe!$L$6:$L$49,">0"),"") | K22: =IF(F22>0,"⚠ 60+ days",IF(E22>0,"⚠ 31-60 days","✓ Current")) -> ⚠ 60+ days
B23: Lion City Media | C23: =SUMIFS(Raw_Stripe!$L$6:$L$49,Raw_Stripe!$D$6:$D$49,B23,Raw_Stripe!$O$6:$O$49,"SG") -> 0 | D23: =SUMIFS(Raw_Stripe!$L$6:$L$49,Raw_Stripe!$D$6:$D$49,B23,Raw_Stripe!$O$6:$O$49,"SG",Raw_Stripe!$C$6:$C$49,">="&(TODAY()-30)) -> 0 | E23: =SUMIFS(Raw_Stripe!$L$6:$L$49,Raw_Stripe!$D$6:$D$49,B23,Raw_Stripe!$O$6:$O$49,"SG",Raw_Stripe!$C$6:$C$49,">="&(TODAY()-60),Raw_Stripe!$C$6:$C$49,"<"&(TODAY()-30)) -> 0 | F23: =SUMIFS(Raw_Stripe!$L$6:$L$49,Raw_Stripe!$D$6:$D$49,B23,Raw_Stripe!$O$6:$O$49,"SG",Raw_Stripe!$C$6:$C$49,"<"&(TODAY()-60)) -> 0 | G23: SGD | H23: =C23*Settings_FX!E$27 -> 0 | I23: =IFERROR(C23/$C$27,0) -> 0 | J23: =IFERROR(minifs(Raw_Stripe!$C$6:$C$49,Raw_Stripe!$D$6:$D$49,B23,Raw_Stripe!$L$6:$L$49,">0"),"") | K23: =IF(F23>0,"⚠ 60+ days",IF(E23>0,"⚠ 31-60 days","✓ Current")) -> ✓ Current
B24: Sentosa E-Commerce | C24: =SUMIFS(Raw_Stripe!$L$6:$L$49,Raw_Stripe!$D$6:$D$49,B24,Raw_Stripe!$O$6:$O$49,"SG") -> 24000 | D24: =SUMIFS(Raw_Stripe!$L$6:$L$49,Raw_Stripe!$D$6:$D$49,B24,Raw_Stripe!$O$6:$O$49,"SG",Raw_Stripe!$C$6:$C$49,">="&(TODAY()-30)) -> 0 | E24: =SUMIFS(Raw_Stripe!$L$6:$L$49,Raw_Stripe!$D$6:$D$49,B24,Raw_Stripe!$O$6:$O$49,"SG",Raw_Stripe!$C$6:$C$49,">="&(TODAY()-60),Raw_Stripe!$C$6:$C$49,"<"&(TODAY()-30)) -> 0 | F24: =SUMIFS(Raw_Stripe!$L$6:$L$49,Raw_Stripe!$D$6:$D$49,B24,Raw_Stripe!$O$6:$O$49,"SG",Raw_Stripe!$C$6:$C$49,"<"&(TODAY()-60)) -> 24000 | G24: USD | H24: =C24 -> 24000 | I24: =IFERROR(C24/$C$27,0) -> 0.68389902 | J24: =IFERROR(minifs(Raw_Stripe!$C$6:$C$49,Raw_Stripe!$D$6:$D$49,B24,Raw_Stripe!$L$6:$L$49,">0"),"") | K24: =IF(F24>0,"⚠ 60+ days",IF(E24>0,"⚠ 31-60 days","✓ Current")) -> ⚠ 60+ days
B25: Orchard Retail Pte | C25: =SUMIFS(Raw_Stripe!$L$6:$L$49,Raw_Stripe!$D$6:$D$49,B25,Raw_Stripe!$O$6:$O$49,"SG") -> 5092.9 | D25: =SUMIFS(Raw_Stripe!$L$6:$L$49,Raw_Stripe!$D$6:$D$49,B25,Raw_Stripe!$O$6:$O$49,"SG",Raw_Stripe!$C$6:$C$49,">="&(TODAY()-30)) -> 0 | E25: =SUMIFS(Raw_Stripe!$L$6:$L$49,Raw_Stripe!$D$6:$D$49,B25,Raw_Stripe!$O$6:$O$49,"SG",Raw_Stripe!$C$6:$C$49,">="&(TODAY()-60),Raw_Stripe!$C$6:$C$49,"<"&(TODAY()-30)) -> 0 | F25: =SUMIFS(Raw_Stripe!$L$6:$L$49,Raw_Stripe!$D$6:$D$49,B25,Raw_Stripe!$O$6:$O$49,"SG",Raw_Stripe!$C$6:$C$49,"<"&(TODAY()-60)) -> 5092.9 | G25: SGD | H25: =C25*Settings_FX!E$27 -> 3804.3963 | I25: =IFERROR(C25/$C$27,0) -> 0.14512622 | J25: =IFERROR(minifs(Raw_Stripe!$C$6:$C$49,Raw_Stripe!$D$6:$D$49,B25,Raw_Stripe!$L$6:$L$49,">0"),"") | K25: =IF(F25>0,"⚠ 60+ days",IF(E25>0,"⚠ 31-60 days","✓ Current")) -> ⚠ 60+ days
B26: Jakarta Digital Ventures | C26: =SUMIFS(Raw_Stripe!$L$6:$L$49,Raw_Stripe!$D$6:$D$49,B26,Raw_Stripe!$O$6:$O$49,"SG") -> 0 | D26: =SUMIFS(Raw_Stripe!$L$6:$L$49,Raw_Stripe!$D$6:$D$49,B26,Raw_Stripe!$O$6:$O$49,"SG",Raw_Stripe!$C$6:$C$49,">="&(TODAY()-30)) -> 0 | E26: =SUMIFS(Raw_Stripe!$L$6:$L$49,Raw_Stripe!$D$6:$D$49,B26,Raw_Stripe!$O$6:$O$49,"SG",Raw_Stripe!$C$6:$C$49,">="&(TODAY()-60),Raw_Stripe!$C$6:$C$49,"<"&(TODAY()-30)) -> 0 | F26: =SUMIFS(Raw_Stripe!$L$6:$L$49,Raw_Stripe!$D$6:$D$49,B26,Raw_Stripe!$O$6:$O$49,"SG",Raw_Stripe!$C$6:$C$49,"<"&(TODAY()-60)) -> 0 | G26: USD | H26: =C26 -> 0 | I26: =IFERROR(C26/$C$27,0) -> 0 | J26: =IFERROR(minifs(Raw_Stripe!$C$6:$C$49,Raw_Stripe!$D$6:$D$49,B26,Raw_Stripe!$L$6:$L$49,">0"),"") | K26: =IF(F26>0,"⚠ 60+ days",IF(E26>0,"⚠ 31-60 days","✓ Current")) -> ✓ Current
B27: TOTAL SG | C27: =SUM(C20:C26) -> 35092.9 | D27: =SUM(D20:D26) -> 0 | E27: =SUM(E20:E26) -> 0 | F27: =SUM(F20:F26) -> 35092.9 | H27: =SUM(H20:H26) -> 32286.396
B29: COMBINED A/R SUMMARY
B30: Total UAE Outstanding (USD) | C30: =H15 -> 21869.29
B31: Total SG Outstanding (USD) | C31: =H27 -> 32286.396
B32: Combined Outstanding (USD) | C32: =H15+H27 -> 54155.687
B33: Customers with 60+ days A/R | C33: =COUNTIF(K6:K14,"*60+*")+COUNTIF(K19:K26,"*60+*") -> 9

Sheet Customer_Receivables
B2: Customer Receivables · Xero + Stripe
B3: Per-customer invoice status breakdown — Draft · Unsent · AwaitPay · Partial · Paid · Void
B5: XERO CUSTOMER RECEIVABLES (per customer × invoice status)
B6: Customer | C6: Total Invoiced USD | D6: Draft | E6: Unsent | F6: Await Pay | G6: Partial | H6: Paid | I6: Void | J6: Outstanding USD | K6: # Invoices
B7: Alphabet Logistics LLC | C7: =SUMIFS(Raw_Xero_Invoices!$H$6:$H$26,Raw_Xero_Invoices!$D$6:$D$26,B7) -> 5527.69 | D7: =SUMIFS(Raw_Xero_Invoices!$H$6:$H$26,Raw_Xero_Invoices!$D$6:$D$26,B7,Raw_Xero_Invoices!$M$6:$M$26,"Draft") -> 0 | E7: =SUMIFS(Raw_Xero_Invoices!$H$6:$H$26,Raw_Xero_Invoices!$D$6:$D$26,B7,Raw_Xero_Invoices!$M$6:$M$26,"Unsent") -> 0 | F7: =SUMIFS(Raw_Xero_Invoices!$H$6:$H$26,Raw_Xero_Invoices!$D$6:$D$26,B7,Raw_Xero_Invoices!$M$6:$M$26,"Awaiting Payment") -> 1225.35 | G7: =SUMIFS(Raw_Xero_Invoices!$H$6:$H$26,Raw_Xero_Invoices!$D$6:$D$26,B7,Raw_Xero_Invoices!$M$6:$M$26,"Partial") -> 1034.74 | H7: =SUMIFS(Raw_Xero_Invoices!$H$6:$H$26,Raw_Xero_Invoices!$D$6:$D$26,B7,Raw_Xero_Invoices!$M$6:$M$26,"Paid") -> 3267.6 | I7: =SUMIFS(Raw_Xero_Invoices!$H$6:$H$26,Raw_Xero_Invoices!$D$6:$D$26,B7,Raw_Xero_Invoices!$M$6:$M$26,"Void") -> 0 | J7: =D7+E7+F7+G7 -> 2260.09 | K7: =COUNTIFS(Raw_Xero_Invoices!$D$6:$D$26,B7) -> 3
B8: Emirates Retail Group | C8: =SUMIFS(Raw_Xero_Invoices!$H$6:$H$26,Raw_Xero_Invoices!$D$6:$D$26,B8) -> 2178.4 | D8: =SUMIFS(Raw_Xero_Invoices!$H$6:$H$26,Raw_Xero_Invoices!$D$6:$D$26,B8,Raw_Xero_Invoices!$M$6:$M$26,"Draft") -> 0 | E8: =SUMIFS(Raw_Xero_Invoices!$H$6:$H$26,Raw_Xero_Invoices!$D$6:$D$26,B8,Raw_Xero_Invoices!$M$6:$M$26,"Unsent") -> 0 | F8: =SUMIFS(Raw_Xero_Invoices!$H$6:$H$26,Raw_Xero_Invoices!$D$6:$D$26,B8,Raw_Xero_Invoices!$M$6:$M$26,"Awaiting Payment") -> 0 | G8: =SUMIFS(Raw_Xero_Invoices!$H$6:$H$26,Raw_Xero_Invoices!$D$6:$D$26,B8,Raw_Xero_Invoices!$M$6:$M$26,"Partial") -> 0 | H8: =SUMIFS(Raw_Xero_Invoices!$H$6:$H$26,Raw_Xero_Invoices!$D$6:$D$26,B8,Raw_Xero_Invoices!$M$6:$M$26,"Paid") -> 1225.35 | I8: =SUMIFS(Raw_Xero_Invoices!$H$6:$H$26,Raw_Xero_Invoices!$D$6:$D$26,B8,Raw_Xero_Invoices!$M$6:$M$26,"Void") -> 953.05 | J8: =D8+E8+F8+G8 -> 0 | K8: =COUNTIFS(Raw_Xero_Invoices!$D$6:$D$26,B8) -> 2
B9: Gulf Tech Distribution | C9: =SUMIFS(Raw_Xero_Invoices!$H$6:$H$26,Raw_Xero_Invoices!$D$6:$D$26,B9) -> 27500 | D9: =SUMIFS(Raw_Xero_Invoices!$H$6:$H$26,Raw_Xero_Invoices!$D$6:$D$26,B9,Raw_Xero_Invoices!$M$6:$M$26,"Draft") -> 0 | E9: =SUMIFS(Raw_Xero_Invoices!$H$6:$H$26,Raw_Xero_Invoices!$D$6:$D$26,B9,Raw_Xero_Invoices!$M$6:$M$26,"Unsent") -> 9500 | F9: =SUMIFS(Raw_Xero_Invoices!$H$6:$H$26,Raw_Xero_Invoices!$D$6:$D$26,B9,Raw_Xero_Invoices!$M$6:$M$26,"Awaiting Payment") -> 0 | G9: =SUMIFS(Raw_Xero_Invoices!$H$6:$H$26,Raw_Xero_Invoices!$D$6:$D$26,B9,Raw_Xero_Invoices!$M$6:$M$26,"Partial") -> 0 | H9: =SUMIFS(Raw_Xero_Invoices!$H$6:$H$26,Raw_Xero_Invoices!$D$6:$D$26,B9,Raw_Xero_Invoices!$M$6:$M$26,"Paid") -> 18000 | I9: =SUMIFS(Raw_Xero_Invoices!$H$6:$H$26,Raw_Xero_Invoices!$D$6:$D$26,B9,Raw_Xero_Invoices!$M$6:$M$26,"Void") -> 0 | J9: =D9+E9+F9+G9 -> 9500 | K9: =COUNTIFS(Raw_Xero_Invoices!$D$6:$D$26,B9) -> 2
B10: Dubai Properties Co | C10: =SUMIFS(Raw_Xero_Invoices!$H$6:$H$26,Raw_Xero_Invoices!$D$6:$D$26,B10) -> 2586.85 | D10: =SUMIFS(Raw_Xero_Invoices!$H$6:$H$26,Raw_Xero_Invoices!$D$6:$D$26,B10,Raw_Xero_Invoices!$M$6:$M$26,"Draft") -> 0 | E10: =SUMIFS(Raw_Xero_Invoices!$H$6:$H$26,Raw_Xero_Invoices!$D$6:$D$26,B10,Raw_Xero_Invoices!$M$6:$M$26,"Unsent") -> 0 | F10: =SUMIFS(Raw_Xero_Invoices!$H$6:$H$26,Raw_Xero_Invoices!$D$6:$D$26,B10,Raw_Xero_Invoices!$M$6:$M$26,"Awaiting Payment") -> 0 | G10: =SUMIFS(Raw_Xero_Invoices!$H$6:$H$26,Raw_Xero_Invoices!$D$6:$D$26,B10,Raw_Xero_Invoices!$M$6:$M$26,"Partial") -> 2586.85 | H10: =SUMIFS(Raw_Xero_Invoices!$H$6:$H$26,Raw_Xero_Invoices!$D$6:$D$26,B10,Raw_Xero_Invoices!$M$6:$M$26,"Paid") -> 0 | I10: =SUMIFS(Raw_Xero_Invoices!$H$6:$H$26,Raw_Xero_Invoices!$D$6:$D$26,B10,Raw_Xero_Invoices!$M$6:$M$26,"Void") -> 0 | J10: =D10+E10+F10+G10 -> 2586.85 | K10: =COUNTIFS(Raw_Xero_Invoices!$D$6:$D$26,B10) -> 1
B11: Abu Dhabi Trading | C11: =SUMIFS(Raw_Xero_Invoices!$H$6:$H$26,Raw_Xero_Invoices!$D$6:$D$26,B11) -> 2042.25 | D11: =SUMIFS(Raw_Xero_Invoices!$H$6:$H$26,Raw_Xero_Invoices!$D$6:$D$26,B11,Raw_Xero_Invoices!$M$6:$M$26,"Draft") -> 0 | E11: =SUMIFS(Raw_Xero_Invoices!$H$6:$H$26,Raw_Xero_Invoices!$D$6:$D$26,B11,Raw_Xero_Invoices!$M$6:$M$26,"Unsent") -> 0 | F11: =SUMIFS(Raw_Xero_Invoices!$H$6:$H$26,Raw_Xero_Invoices!$D$6:$D$26,B11,Raw_Xero_Invoices!$M$6:$M$26,"Awaiting Payment") -> 0 | G11: =SUMIFS(Raw_Xero_Invoices!$H$6:$H$26,Raw_Xero_Invoices!$D$6:$D$26,B11,Raw_Xero_Invoices!$M$6:$M$26,"Partial") -> 0 | H11: =SUMIFS(Raw_Xero_Invoices!$H$6:$H$26,Raw_Xero_Invoices!$D$6:$D$26,B11,Raw_Xero_Invoices!$M$6:$M$26,"Paid") -> 2042.25 | I11: =SUMIFS(Raw_Xero_Invoices!$H$6:$H$26,Raw_Xero_Invoices!$D$6:$D$26,B11,Raw_Xero_Invoices!$M$6:$M$26,"Void") -> 0 | J11: =D11+E11+F11+G11 -> 0 | K11: =COUNTIFS(Raw_Xero_Invoices!$D$6:$D$26,B11) -> 1
B12: Rak Bank Digital | C12: =SUMIFS(Raw_Xero_Invoices!$H$6:$H$26,Raw_Xero_Invoices!$D$6:$D$26,B12) -> 2314.55 | D12: =SUMIFS(Raw_Xero_Invoices!$H$6:$H$26,Raw_Xero_Invoices!$D$6:$D$26,B12,Raw_Xero_Invoices!$M$6:$M$26,"Draft") -> 0 | E12: =SUMIFS(Raw_Xero_Invoices!$H$6:$H$26,Raw_Xero_Invoices!$D$6:$D$26,B12,Raw_Xero_Invoices!$M$6:$M$26,"Unsent") -> 0 | F12: =SUMIFS(Raw_Xero_Invoices!$H$6:$H$26,Raw_Xero_Invoices!$D$6:$D$26,B12,Raw_Xero_Invoices!$M$6:$M$26,"Awaiting Payment") -> 0 | G12: =SUMIFS(Raw_Xero_Invoices!$H$6:$H$26,Raw_Xero_Invoices!$D$6:$D$26,B12,Raw_Xero_Invoices!$M$6:$M$26,"Partial") -> 0 | H12: =SUMIFS(Raw_Xero_Invoices!$H$6:$H$26,Raw_Xero_Invoices!$D$6:$D$26,B12,Raw_Xero_Invoices!$M$6:$M$26,"Paid") -> 0 | I12: =SUMIFS(Raw_Xero_Invoices!$H$6:$H$26,Raw_Xero_Invoices!$D$6:$D$26,B12,Raw_Xero_Invoices!$M$6:$M$26,"Void") -> 2314.55 | J12: =D12+E12+F12+G12 -> 0 | K12: =COUNTIFS(Raw_Xero_Invoices!$D$6:$D$26,B12) -> 1
B13: Global SaaS Inc | C13: =SUMIFS(Raw_Xero_Invoices!$H$6:$H$26,Raw_Xero_Invoices!$D$6:$D$26,B13) -> 9200 | D13: =SUMIFS(Raw_Xero_Invoices!$H$6:$H$26,Raw_Xero_Invoices!$D$6:$D$26,B13,Raw_Xero_Invoices!$M$6:$M$26,"Draft") -> 9200 | E13: =SUMIFS(Raw_Xero_Invoices!$H$6:$H$26,Raw_Xero_Invoices!$D$6:$D$26,B13,Raw_Xero_Invoices!$M$6:$M$26,"Unsent") -> 0 | F13: =SUMIFS(Raw_Xero_Invoices!$H$6:$H$26,Raw_Xero_Invoices!$D$6:$D$26,B13,Raw_Xero_Invoices!$M$6:$M$26,"Awaiting Payment") -> 0 | G13: =SUMIFS(Raw_Xero_Invoices!$H$6:$H$26,Raw_Xero_Invoices!$D$6:$D$26,B13,Raw_Xero_Invoices!$M$6:$M$26,"Partial") -> 0 | H13: =SUMIFS(Raw_Xero_Invoices!$H$6:$H$26,Raw_Xero_Invoices!$D$6:$D$26,B13,Raw_Xero_Invoices!$M$6:$M$26,"Paid") -> 0 | I13: =SUMIFS(Raw_Xero_Invoices!$H$6:$H$26,Raw_Xero_Invoices!$D$6:$D$26,B13,Raw_Xero_Invoices!$M$6:$M$26,"Void") -> 0 | J13: =D13+E13+F13+G13 -> 9200 | K13: =COUNTIFS(Raw_Xero_Invoices!$D$6:$D$26,B13) -> 1
B14: Mena Apps FZ-LLC | C14: =SUMIFS(Raw_Xero_Invoices!$H$6:$H$26,Raw_Xero_Invoices!$D$6:$D$26,B14) -> 5800 | D14: =SUMIFS(Raw_Xero_Invoices!$H$6:$H$26,Raw_Xero_Invoices!$D$6:$D$26,B14,Raw_Xero_Invoices!$M$6:$M$26,"Draft") -> 0 | E14: =SUMIFS(Raw_Xero_Invoices!$H$6:$H$26,Raw_Xero_Invoices!$D$6:$D$26,B14,Raw_Xero_Invoices!$M$6:$M$26,"Unsent") -> 0 | F14: =SUMIFS(Raw_Xero_Invoices!$H$6:$H$26,Raw_Xero_Invoices!$D$6:$D$26,B14,Raw_Xero_Invoices!$M$6:$M$26,"Awaiting Payment") -> 0 | G14: =SUMIFS(Raw_Xero_Invoices!$H$6:$H$26,Raw_Xero_Invoices!$D$6:$D$26,B14,Raw_Xero_Invoices!$M$6:$M$26,"Partial") -> 0 | H14: =SUMIFS(Raw_Xero_Invoices!$H$6:$H$26,Raw_Xero_Invoices!$D$6:$D$26,B14,Raw_Xero_Invoices!$M$6:$M$26,"Paid") -> 5800 | I14: =SUMIFS(Raw_Xero_Invoices!$H$6:$H$26,Raw_Xero_Invoices!$D$6:$D$26,B14,Raw_Xero_Invoices!$M$6:$M$26,"Void") -> 0 | J14: =D14+E14+F14+G14 -> 0 | K14: =COUNTIFS(Raw_Xero_Invoices!$D$6:$D$26,B14) -> 1
B15: Singapore FinTech Hub | C15: =SUMIFS(Raw_Xero_Invoices!$H$6:$H$26,Raw_Xero_Invoices!$D$6:$D$26,B15) -> 8189.8 | D15: =SUMIFS(Raw_Xero_Invoices!$H$6:$H$26,Raw_Xero_Invoices!$D$6:$D$26,B15,Raw_Xero_Invoices!$M$6:$M$26,"Draft") -> 3137.4 | E15: =SUMIFS(Raw_Xero_Invoices!$H$6:$H$26,Raw_Xero_Invoices!$D$6:$D$26,B15,Raw_Xero_Invoices!$M$6:$M$26,"Unsent") -> 0 | F15: =SUMIFS(Raw_Xero_Invoices!$H$6:$H$26,Raw_Xero_Invoices!$D$6:$D$26,B15,Raw_Xero_Invoices!$M$6:$M$26,"Awaiting Payment") -> 0 | G15: =SUMIFS(Raw_Xero_Invoices!$H$6:$H$26,Raw_Xero_Invoices!$D$6:$D$26,B15,Raw_Xero_Invoices!$M$6:$M$26,"Partial") -> 0 | H15: =SUMIFS(Raw_Xero_Invoices!$H$6:$H$26,Raw_Xero_Invoices!$D$6:$D$26,B15,Raw_Xero_Invoices!$M$6:$M$26,"Paid") -> 5052.4 | I15: =SUMIFS(Raw_Xero_Invoices!$H$6:$H$26,Raw_Xero_Invoices!$D$6:$D$26,B15,Raw_Xero_Invoices!$M$6:$M$26,"Void") -> 0 | J15: =D15+E15+F15+G15 -> 3137.4 | K15: =COUNTIFS(Raw_Xero_Invoices!$D$6:$D$26,B15) -> 2
B16: Asia Pacific Solutions | C16: =SUMIFS(Raw_Xero_Invoices!$H$6:$H$26,Raw_Xero_Invoices!$D$6:$D$26,B16) -> 15500 | D16: =SUMIFS(Raw_Xero_Invoices!$H$6:$H$26,Raw_Xero_Invoices!$D$6:$D$26,B16,Raw_Xero_Invoices!$M$6:$M$26,"Draft") -> 0 | E16: =SUMIFS(Raw_Xero_Invoices!$H$6:$H$26,Raw_Xero_Invoices!$D$6:$D$26,B16,Raw_Xero_Invoices!$M$6:$M$26,"Unsent") -> 0 | F16: =SUMIFS(Raw_Xero_Invoices!$H$6:$H$26,Raw_Xero_Invoices!$D$6:$D$26,B16,Raw_Xero_Invoices!$M$6:$M$26,"Awaiting Payment") -> 0 | G16: =SUMIFS(Raw_Xero_Invoices!$H$6:$H$26,Raw_Xero_Invoices!$D$6:$D$26,B16,Raw_Xero_Invoices!$M$6:$M$26,"Partial") -> 0 | H16: =SUMIFS(Raw_Xero_Invoices!$H$6:$H$26,Raw_Xero_Invoices!$D$6:$D$26,B16,Raw_Xero_Invoices!$M$6:$M$26,"Paid") -> 15500 | I16: =SUMIFS(Raw_Xero_Invoices!$H$6:$H$26,Raw_Xero_Invoices!$D$6:$D$26,B16,Raw_Xero_Invoices!$M$6:$M$26,"Void") -> 0 | J16: =D16+E16+F16+G16 -> 0 | K16: =COUNTIFS(Raw_Xero_Invoices!$D$6:$D$26,B16) -> 1
B17: Marina Bay Holdings | C17: =SUMIFS(Raw_Xero_Invoices!$H$6:$H$26,Raw_Xero_Invoices!$D$6:$D$26,B17) -> 22758.9 | D17: =SUMIFS(Raw_Xero_Invoices!$H$6:$H$26,Raw_Xero_Invoices!$D$6:$D$26,B17,Raw_Xero_Invoices!$M$6:$M$26,"Draft") -> 0 | E17: =SUMIFS(Raw_Xero_Invoices!$H$6:$H$26,Raw_Xero_Invoices!$D$6:$D$26,B17,Raw_Xero_Invoices!$M$6:$M$26,"Unsent") -> 0 | F17: =SUMIFS(Raw_Xero_Invoices!$H$6:$H$26,Raw_Xero_Invoices!$D$6:$D$26,B17,Raw_Xero_Invoices!$M$6:$M$26,"Awaiting Payment") -> 4926.9 | G17: =SUMIFS(Raw_Xero_Invoices!$H$6:$H$26,Raw_Xero_Invoices!$D$6:$D$26,B17,Raw_Xero_Invoices!$M$6:$M$26,"Partial") -> 0 | H17: =SUMIFS(Raw_Xero_Invoices!$H$6:$H$26,Raw_Xero_Invoices!$D$6:$D$26,B17,Raw_Xero_Invoices!$M$6:$M$26,"Paid") -> 17832 | I17: =SUMIFS(Raw_Xero_Invoices!$H$6:$H$26,Raw_Xero_Invoices!$D$6:$D$26,B17,Raw_Xero_Invoices!$M$6:$M$26,"Void") -> 0 | J17: =D17+E17+F17+G17 -> 4926.9 | K17: =COUNTIFS(Raw_Xero_Invoices!$D$6:$D$26,B17) -> 2
B18: Lion City Media | C18: =SUMIFS(Raw_Xero_Invoices!$H$6:$H$26,Raw_Xero_Invoices!$D$6:$D$26,B18) -> 3124.8 | D18: =SUMIFS(Raw_Xero_Invoices!$H$6:$H$26,Raw_Xero_Invoices!$D$6:$D$26,B18,Raw_Xero_Invoices!$M$6:$M$26,"Draft") -> 0 | E18: =SUMIFS(Raw_Xero_Invoices!$H$6:$H$26,Raw_Xero_Invoices!$D$6:$D$26,B18,Raw_Xero_Invoices!$M$6:$M$26,"Unsent") -> 0 | F18: =SUMIFS(Raw_Xero_Invoices!$H$6:$H$26,Raw_Xero_Invoices!$D$6:$D$26,B18,Raw_Xero_Invoices!$M$6:$M$26,"Awaiting Payment") -> 0 | G18: =SUMIFS(Raw_Xero_Invoices!$H$6:$H$26,Raw_Xero_Invoices!$D$6:$D$26,B18,Raw_Xero_Invoices!$M$6:$M$26,"Partial") -> 0 | H18: =SUMIFS(Raw_Xero_Invoices!$H$6:$H$26,Raw_Xero_Invoices!$D$6:$D$26,B18,Raw_Xero_Invoices!$M$6:$M$26,"Paid") -> 3124.8 | I18: =SUMIFS(Raw_Xero_Invoices!$H$6:$H$26,Raw_Xero_Invoices!$D$6:$D$26,B18,Raw_Xero_Invoices!$M$6:$M$26,"Void") -> 0 | J18: =D18+E18+F18+G18 -> 0 | K18: =COUNTIFS(Raw_Xero_Invoices!$D$6:$D$26,B18) -> 1
... B21: Jakarta Digital Ventures | C21: =SUMIFS(Raw_Xero_Invoices!$H$6:$H$26,Raw_Xero_Invoices!$D$6:$D$26,B21) -> 11500 | D21: =SUMIFS(Raw_Xero_Invoices!$H$6:$H$26,Raw_Xero_Invoices!$D$6:$D$26,B21,Raw_Xero_Invoices!$M$6:$M$26,"Draft") -> 0 | E21: =SUMIFS(Raw_Xero_Invoices!$H$6:$H$26,Raw_Xero_Invoices!$D$6:$D$26,B21,Raw_Xero_Invoices!$M$6:$M$26,"Unsent") -> 11500 | F21: =SUMIFS(Raw_Xero_Invoices!$H$6:$H$26,Raw_Xero_Invoices!$D$6:$D$26,B21,Raw_Xero_Invoices!$M$6:$M$26,"Awaiting Payment") -> 0 | G21: =SUMIFS(Raw_Xero_Invoices!$H$6:$H$26,Raw_Xero_Invoices!$D$6:$D$26,B21,Raw_Xero_Invoices!$M$6:$M$26,"Partial") -> 0 | H21: =SUMIFS(Raw_Xero_Invoices!$H$6:$H$26,Raw_Xero_Invoices!$D$6:$D$26,B21,Raw_Xero_Invoices!$M$6:$M$26,"Paid") -> 0 | I21: =SUMIFS(Raw_Xero_Invoices!$H$6:$H$26,Raw_Xero_Invoices!$D$6:$D$26,B21,Raw_Xero_Invoices!$M$6:$M$26,"Void") -> 0 | J21: =D21+E21+F21+G21 -> 11500 | K21: =COUNTIFS(Raw_Xero_Invoices!$D$6:$D$26,B21) -> 1
B22: TOTAL | C22: =SUM(C7:C21) -> 134873.99 | D22: =SUM(D7:D21) -> 12337.4 | E22: =SUM(E7:E21) -> 21000 | F22: =SUM(F7:F21) -> 6152.25 | G22: =SUM(G7:G21) -> 13672.34 | H22: =SUM(H7:H21) -> 78444.4 | I22: =SUM(I7:I21) -> 3267.6 | J22: =SUM(J7:J21) -> 53161.99 | K22: =SUM(K7:K21) -> 21
B25: STRIPE CUSTOMER RECEIVABLES (per customer × invoice status)
B26: Customer | C26: Total Invoiced USD | D26: Draft | E26: Unsent | F26: Await Pay | G26: Partial | H26: Paid | I26: Void | J26: Outstanding USD | K26: # Invoices
B27: Alphabet Logistics LLC | C27: =SUMIFS(Raw_Stripe!$H$6:$H$49,Raw_Stripe!$D$6:$D$49,B27) -> 9394.35 | D27: =SUMIFS(Raw_Stripe!$H$6:$H$49,Raw_Stripe!$D$6:$D$49,B27,Raw_Stripe!$P$6:$P$49,"Draft") -> 0 | E27: =SUMIFS(Raw_Stripe!$H$6:$H$49,Raw_Stripe!$D$6:$D$49,B27,Raw_Stripe!$P$6:$P$49,"Unsent") -> 2314.55 | F27: =SUMIFS(Raw_Stripe!$H$6:$H$49,Raw_Stripe!$D$6:$D$49,B27,Raw_Stripe!$P$6:$P$49,"Awaiting Payment") -> 0 | G27: =SUMIFS(Raw_Stripe!$H$6:$H$49,Raw_Stripe!$D$6:$D$49,B27,Raw_Stripe!$P$6:$P$49,"Partial") -> 1279.81 | H27: =SUMIFS(Raw_Stripe!$H$6:$H$49,Raw_Stripe!$D$6:$D$49,B27,Raw_Stripe!$P$6:$P$49,"Paid") -> 5799.99 | I27: =SUMIFS(Raw_Stripe!$H$6:$H$49,Raw_Stripe!$D$6:$D$49,B27,Raw_Stripe!$P$6:$P$49,"Void") -> 0 | J27: =D27+E27+F27+G27 -> 3594.36 | K27: =COUNTIFS(Raw_Stripe!$D$6:$D$49,B27) -> 7
B28: Emirates Retail Group | C28: =SUMIFS(Raw_Stripe!$H$6:$H$49,Raw_Stripe!$D$6:$D$49,B28) -> 3322.06 | D28: =SUMIFS(Raw_Stripe!$H$6:$H$49,Raw_Stripe!$D$6:$D$49,B28,Raw_Stripe!$P$6:$P$49,"Draft") -> 0 | E28: =SUMIFS(Raw_Stripe!$H$6:$H$49,Raw_Stripe!$D$6:$D$49,B28,Raw_Stripe!$P$6:$P$49,"Unsent") -> 1143.66 | F28: =SUMIFS(Raw_Stripe!$H$6:$H$49,Raw_Stripe!$D$6:$D$49,B28,Raw_Stripe!$P$6:$P$49,"Awaiting Payment") -> 0 | G28: =SUMIFS(Raw_Stripe!$H$6:$H$49,Raw_Stripe!$D$6:$D$49,B28,Raw_Stripe!$P$6:$P$49,"Partial") -> 0 | H28: =SUMIFS(Raw_Stripe!$H$6:$H$49,Raw_Stripe!$D$6:$D$49,B28,Raw_Stripe!$P$6:$P$49,"Paid") -> 2178.4 | I28: =SUMIFS(Raw_Stripe!$H$6:$H$49,Raw_Stripe!$D$6:$D$49,B28,Raw_Stripe!$P$6:$P$49,"Void") -> 0 | J28: =D28+E28+F28+G28 -> 1143.66 | K28: =COUNTIFS(Raw_Stripe!$D$6:$D$49,B28) -> 5
B29: Gulf Tech Distribution | C29: =SUMIFS(Raw_Stripe!$H$6:$H$49,Raw_Stripe!$D$6:$D$49,B29) -> 46000 | D29: =SUMIFS(Raw_Stripe!$H$6:$H$49,Raw_Stripe!$D$6:$D$49,B29,Raw_Stripe!$P$6:$P$49,"Draft") -> 9500 | E29: =SUMIFS(Raw_Stripe!$H$6:$H$49,Raw_Stripe!$D$6:$D$49,B29,Raw_Stripe!$P$6:$P$49,"Unsent") -> 0 | F29: =SUMIFS(Raw_Stripe!$H$6:$H$49,Raw_Stripe!$D$6:$D$49,B29,Raw_Stripe!$P$6:$P$49,"Awaiting Payment") -> 0 | G29: =SUMIFS(Raw_Stripe!$H$6:$H$49,Raw_Stripe!$D$6:$D$49,B29,Raw_Stripe!$P$6:$P$49,"Partial") -> 0 | H29: =SUMIFS(Raw_Stripe!$H$6:$H$49,Raw_Stripe!$D$6:$D$49,B29,Raw_Stripe!$P$6:$P$49,"Paid") -> 36500 | I29: =SUMIFS(Raw_Stripe!$H$6:$H$49,Raw_Stripe!$D$6:$D$49,B29,Raw_Stripe!$P$6:$P$49,"Void") -> 0 | J29: =D29+E29+F29+G29 -> 9500 | K29: =COUNTIFS(Raw_Stripe!$D$6:$D$49,B29) -> 5
B30: Dubai Properties Co | C30: =SUMIFS(Raw_Stripe!$H$6:$H$49,Raw_Stripe!$D$6:$D$49,B30) -> 4656.33 | D30: =SUMIFS(Raw_Stripe!$H$6:$H$49,Raw_Stripe!$D$6:$D$49,B30,Raw_Stripe!$P$6:$P$49,"Draft") -> 0 | E30: =SUMIFS(Raw_Stripe!$H$6:$H$49,Raw_Stripe!$D$6:$D$49,B30,Raw_Stripe!$P$6:$P$49,"Unsent") -> 0 | F30: =SUMIFS(Raw_Stripe!$H$6:$H$49,Raw_Stripe!$D$6:$D$49,B30,Raw_Stripe!$P$6:$P$49,"Awaiting Payment") -> 0 | G30: =SUMIFS(Raw_Stripe!$H$6:$H$49,Raw_Stripe!$D$6:$D$49,B30,Raw_Stripe!$P$6:$P$49,"Partial") -> 0 | H30: =SUMIFS(Raw_Stripe!$H$6:$H$49,Raw_Stripe!$D$6:$D$49,B30,Raw_Stripe!$P$6:$P$49,"Paid") -> 4656.33 | I30: =SUMIFS(Raw_Stripe!$H$6:$H$49,Raw_Stripe!$D$6:$D$49,B30,Raw_Stripe!$P$6:$P$49,"Void") -> 0 | J30: =D30+E30+F30+G30 -> 0 | K30: =COUNTIFS(Raw_Stripe!$D$6:$D$49,B30) -> 3
B31: Abu Dhabi Trading | C31: =SUMIFS(Raw_Stripe!$H$6:$H$49,Raw_Stripe!$D$6:$D$49,B31) -> 1715.49 | D31: =SUMIFS(Raw_Stripe!$H$6:$H$49,Raw_Stripe!$D$6:$D$49,B31,Raw_Stripe!$P$6:$P$49,"Draft") -> 0 | E31: =SUMIFS(Raw_Stripe!$H$6:$H$49,Raw_Stripe!$D$6:$D$49,B31,Raw_Stripe!$P$6:$P$49,"Unsent") -> 0 | F31: =SUMIFS(Raw_Stripe!$H$6:$H$49,Raw_Stripe!$D$6:$D$49,B31,Raw_Stripe!$P$6:$P$49,"Awaiting Payment") -> 0 | G31: =SUMIFS(Raw_Stripe!$H$6:$H$49,Raw_Stripe!$D$6:$D$49,B31,Raw_Stripe!$P$6:$P$49,"Partial") -> 0 | H31: =SUMIFS(Raw_Stripe!$H$6:$H$49,Raw_Stripe!$D$6:$D$49,B31,Raw_Stripe!$P$6:$P$49,"Paid") -> 1715.49 | I31: =SUMIFS(Raw_Stripe!$H$6:$H$49,Raw_Stripe!$D$6:$D$49,B31,Raw_Stripe!$P$6:$P$49,"Void") -> 0 | J31: =D31+E31+F31+G31 -> 0 | K31: =COUNTIFS(Raw_Stripe!$D$6:$D$49,B31) -> 2
B32: Rak Bank Digital | C32: =SUMIFS(Raw_Stripe!$H$6:$H$49,Raw_Stripe!$D$6:$D$49,B32) -> 4438.49 | D32: =SUMIFS(Raw_Stripe!$H$6:$H$49,Raw_Stripe!$D$6:$D$49,B32,Raw_Stripe!$P$6:$P$49,"Draft") -> 0 | E32: =SUMIFS(Raw_Stripe!$H$6:$H$49,Raw_Stripe!$D$6:$D$49,B32,Raw_Stripe!$P$6:$P$49,"Unsent") -> 0 | F32: =SUMIFS(Raw_Stripe!$H$6:$H$49,Raw_Stripe!$D$6:$D$49,B32,Raw_Stripe!$P$6:$P$49,"Awaiting Payment") -> 0 | G32: =SUMIFS(Raw_Stripe!$H$6:$H$49,Raw_Stripe!$D$6:$D$49,B32,Raw_Stripe!$P$6:$P$49,"Partial") -> 0 | H32: =SUMIFS(Raw_Stripe!$H$6:$H$49,Raw_Stripe!$D$6:$D$49,B32,Raw_Stripe!$P$6:$P$49,"Paid") -> 2586.85 | I32: =SUMIFS(Raw_Stripe!$H$6:$H$49,Raw_Stripe!$D$6:$D$49,B32,Raw_Stripe!$P$6:$P$49,"Void") -> 1851.64 | J32: =D32+E32+F32+G32 -> 0 | K32: =COUNTIFS(Raw_Stripe!$D$6:$D$49,B32) -> 2
B33: Global SaaS Inc | C33: =SUMIFS(Raw_Stripe!$H$6:$H$49,Raw_Stripe!$D$6:$D$49,B33) -> 24000 | D33: =SUMIFS(Raw_Stripe!$H$6:$H$49,Raw_Stripe!$D$6:$D$49,B33,Raw_Stripe!$P$6:$P$49,"Draft") -> 0 | E33: =SUMIFS(Raw_Stripe!$H$6:$H$49,Raw_Stripe!$D$6:$D$49,B33,Raw_Stripe!$P$6:$P$49,"Unsent") -> 0 | F33: =SUMIFS(Raw_Stripe!$H$6:$H$49,Raw_Stripe!$D$6:$D$49,B33,Raw_Stripe!$P$6:$P$49,"Awaiting Payment") -> 0 | G33: =SUMIFS(Raw_Stripe!$H$6:$H$49,Raw_Stripe!$D$6:$D$49,B33,Raw_Stripe!$P$6:$P$49,"Partial") -> 0 | H33: =SUMIFS(Raw_Stripe!$H$6:$H$49,Raw_Stripe!$D$6:$D$49,B33,Raw_Stripe!$P$6:$P$49,"Paid") -> 24000 | I33: =SUMIFS(Raw_Stripe!$H$6:$H$49,Raw_Stripe!$D$6:$D$49,B33,Raw_Stripe!$P$6:$P$49,"Void") -> 0 | J33: =D33+E33+F33+G33 -> 0 | K33: =COUNTIFS(Raw_Stripe!$D$6:$D$49,B33) -> 1
B34: Mena Apps FZ-LLC | C34: =SUMIFS(Raw_Stripe!$H$6:$H$49,Raw_Stripe!$D$6:$D$49,B34) -> 11900 | D34: =SUMIFS(Raw_Stripe!$H$6:$H$49,Raw_Stripe!$D$6:$D$49,B34,Raw_Stripe!$P$6:$P$49,"Draft") -> 0 | E34: =SUMIFS(Raw_Stripe!$H$6:$H$49,Raw_Stripe!$D$6:$D$49,B34,Raw_Stripe!$P$6:$P$49,"Unsent") -> 6500 | F34: =SUMIFS(Raw_Stripe!$H$6:$H$49,Raw_Stripe!$D$6:$D$49,B34,Raw_Stripe!$P$6:$P$49,"Awaiting Payment") -> 0 | G34: =SUMIFS(Raw_Stripe!$H$6:$H$49,Raw_Stripe!$D$6:$D$49,B34,Raw_Stripe!$P$6:$P$49,"Partial") -> 0 | H34: =SUMIFS(Raw_Stripe!$H$6:$H$49,Raw_Stripe!$D$6:$D$49,B34,Raw_Stripe!$P$6:$P$49,"Paid") -> 5400 | I34: =SUMIFS(Raw_Stripe!$H$6:$H$49,Raw_Stripe!$D$6:$D$49,B34,Raw_Stripe!$P$6:$P$49,"Void") -> 0 | J34: =D34+E34+F34+G34 -> 6500 | K34: =COUNTIFS(Raw_Stripe!$D$6:$D$49,B34) -> 2
B35: Singapore FinTech Hub | C35: =SUMIFS(Raw_Stripe!$H$6:$H$49,Raw_Stripe!$D$6:$D$49,B35) -> 17744.4 | D35: =SUMIFS(Raw_Stripe!$H$6:$H$49,Raw_Stripe!$D$6:$D$49,B35,Raw_Stripe!$P$6:$P$49,"Draft") -> 3135.3 | E35: =SUMIFS(Raw_Stripe!$H$6:$H$49,Raw_Stripe!$D$6:$D$49,B35,Raw_Stripe!$P$6:$P$49,"Unsent") -> 0 | F35: =SUMIFS(Raw_Stripe!$H$6:$H$49,Raw_Stripe!$D$6:$D$49,B35,Raw_Stripe!$P$6:$P$49,"Awaiting Payment") -> 0 | G35: =SUMIFS(Raw_Stripe!$H$6:$H$49,Raw_Stripe!$D$6:$D$49,B35,Raw_Stripe!$P$6:$P$49,"Partial") -> 0 | H35: =SUMIFS(Raw_Stripe!$H$6:$H$49,Raw_Stripe!$D$6:$D$49,B35,Raw_Stripe!$P$6:$P$49,"Paid") -> 14609.1 | I35: =SUMIFS(Raw_Stripe!$H$6:$H$49,Raw_Stripe!$D$6:$D$49,B35,Raw_Stripe!$P$6:$P$49,"Void") -> 0 | J35: =D35+E35+F35+G35 -> 3135.3 | K35: =COUNTIFS(Raw_Stripe!$D$6:$D$49,B35) -> 5
B36: Asia Pacific Solutions | C36: =SUMIFS(Raw_Stripe!$H$6:$H$49,Raw_Stripe!$D$6:$D$49,B36) -> 23000 | D36: =SUMIFS(Raw_Stripe!$H$6:$H$49,Raw_Stripe!$D$6:$D$49,B36,Raw_Stripe!$P$6:$P$49,"Draft") -> 0 | E36: =SUMIFS(Raw_Stripe!$H$6:$H$49,Raw_Stripe!$D$6:$D$49,B36,Raw_Stripe!$P$6:$P$49,"Unsent") -> 0 | F36: =SUMIFS(Raw_Stripe!$H$6:$H$49,Raw_Stripe!$D$6:$D$49,B36,Raw_Stripe!$P$6:$P$49,"Awaiting Payment") -> 0 | G36: =SUMIFS(Raw_Stripe!$H$6:$H$49,Raw_Stripe!$D$6:$D$49,B36,Raw_Stripe!$P$6:$P$49,"Partial") -> 0 | H36: =SUMIFS(Raw_Stripe!$H$6:$H$49,Raw_Stripe!$D$6:$D$49,B36,Raw_Stripe!$P$6:$P$49,"Paid") -> 23000 | I36: =SUMIFS(Raw_Stripe!$H$6:$H$49,Raw_Stripe!$D$6:$D$49,B36,Raw_Stripe!$P$6:$P$49,"Void") -> 0 | J36: =D36+E36+F36+G36 -> 0 | K36: =COUNTIFS(Raw_Stripe!$D$6:$D$49,B36) -> 2
B37: Marina Bay Holdings | C37: =SUMIFS(Raw_Stripe!$H$6:$H$49,Raw_Stripe!$D$6:$D$49,B37) -> 19400.4 | D37: =SUMIFS(Raw_Stripe!$H$6:$H$49,Raw_Stripe!$D$6:$D$49,B37,Raw_Stripe!$P$6:$P$49,"Draft") -> 0 | E37: =SUMIFS(Raw_Stripe!$H$6:$H$49,Raw_Stripe!$D$6:$D$49,B37,Raw_Stripe!$P$6:$P$49,"Unsent") -> 0 | F37: =SUMIFS(Raw_Stripe!$H$6:$H$49,Raw_Stripe!$D$6:$D$49,B37,Raw_Stripe!$P$6:$P$49,"Awaiting Payment") -> 0 | G37: =SUMIFS(Raw_Stripe!$H$6:$H$49,Raw_Stripe!$D$6:$D$49,B37,Raw_Stripe!$P$6:$P$49,"Partial") -> 0 | H37: =SUMIFS(Raw_Stripe!$H$6:$H$49,Raw_Stripe!$D$6:$D$49,B37,Raw_Stripe!$P$6:$P$49,"Paid") -> 18056.7 | I37: =SUMIFS(Raw_Stripe!$H$6:$H$49,Raw_Stripe!$D$6:$D$49,B37,Raw_Stripe!$P$6:$P$49,"Void") -> 1343.7 | J37: =D37+E37+F37+G37 -> 0 | K37: =COUNTIFS(Raw_Stripe!$D$6:$D$49,B37) -> 4
B38: Lion City Media | C38: =SUMIFS(Raw_Stripe!$H$6:$H$49,Raw_Stripe!$D$6:$D$49,B38) -> 5873.5 | D38: =SUMIFS(Raw_Stripe!$H$6:$H$49,Raw_Stripe!$D$6:$D$49,B38,Raw_Stripe!$P$6:$P$49,"Draft") -> 0 | E38: =SUMIFS(Raw_Stripe!$H$6:$H$49,Raw_Stripe!$D$6:$D$49,B38,Raw_Stripe!$P$6:$P$49,"Unsent") -> 0 | F38: =SUMIFS(Raw_Stripe!$H$6:$H$49,Raw_Stripe!$D$6:$D$49,B38,Raw_Stripe!$P$6:$P$49,"Awaiting Payment") -> 0 | G38: =SUMIFS(Raw_Stripe!$H$6:$H$49,Raw_Stripe!$D$6:$D$49,B38,Raw_Stripe!$P$6:$P$49,"Partial") -> 0 | H38: =SUMIFS(Raw_Stripe!$H$6:$H$49,Raw_Stripe!$D$6:$D$49,B38,Raw_Stripe!$P$6:$P$49,"Paid") -> 5873.5 | I38: =SUMIFS(Raw_Stripe!$H$6:$H$49,Raw_Stripe!$D$6:$D$49,B38,Raw_Stripe!$P$6:$P$49,"Void") -> 0 | J38: =D38+E38+F38+G38 -> 0 | K38: =COUNTIFS(Raw_Stripe!$D$6:$D$49,B38) -> 2
... B41: Jakarta Digital Ventures | C41: =SUMIFS(Raw_Stripe!$H$6:$H$49,Raw_Stripe!$D$6:$D$49,B41) -> 11200 | D41: =SUMIFS(Raw_Stripe!$H$6:$H$49,Raw_Stripe!$D$6:$D$49,B41,Raw_Stripe!$P$6:$P$49,"Draft") -> 0 | E41: =SUMIFS(Raw_Stripe!$H$6:$H$49,Raw_Stripe!$D$6:$D$49,B41,Raw_Stripe!$P$6:$P$49,"Unsent") -> 0 | F41: =SUMIFS(Raw_Stripe!$H$6:$H$49,Raw_Stripe!$D$6:$D$49,B41,Raw_Stripe!$P$6:$P$49,"Awaiting Payment") -> 0 | G41: =SUMIFS(Raw_Stripe!$H$6:$H$49,Raw_Stripe!$D$6:$D$49,B41,Raw_Stripe!$P$6:$P$49,"Partial") -> 0 | H41: =SUMIFS(Raw_Stripe!$H$6:$H$49,Raw_Stripe!$D$6:$D$49,B41,Raw_Stripe!$P$6:$P$49,"Paid") -> 11200 | I41: =SUMIFS(Raw_Stripe!$H$6:$H$49,Raw_Stripe!$D$6:$D$49,B41,Raw_Stripe!$P$6:$P$49,"Void") -> 0 | J41: =D41+E41+F41+G41 -> 0 | K41: =COUNTIFS(Raw_Stripe!$D$6:$D$49,B41) -> 1
B42: TOTAL | C42: =SUM(C27:C41) -> 218895.77 | D42: =SUM(D27:D41) -> 36635.3 | E42: =SUM(E27:E41) -> 9958.21 | F42: =SUM(F27:F41) -> 0 | G42: =SUM(G27:G41) -> 11330.56 | H42: =SUM(H27:H41) -> 157776.36 | I42: =SUM(I27:I41) -> 3195.34 | J42: =SUM(J27:J41) -> 57924.07 | K42: =SUM(K27:K41) -> 44
B44: COMBINED RECEIVABLES SUMMARY
B45: Xero: Total Invoiced (USD) | C45: =C22 -> 134873.99
B46: Xero: Outstanding (USD) | C46: =J22 -> 53161.99
B47: Stripe: Total Charged (USD) | C47: =C42 -> 218895.77
B48: Stripe: Outstanding (USD) | C48: =J42 -> 57924.07
B49: Combined Outstanding (USD) | C49: =J22+J42 -> 111086.06
B50: Xero: # Invoices Total | C50: =K22 -> 21
B51: Stripe: # Transactions Total | C51: =K42 -> 44
B52: Xero: Draft Invoices Count | C52: =COUNTIF(Raw_Xero_Invoices!M6:M26,"Draft") -> 2
B53: Xero: Unsent Invoices Count | C53: =COUNTIF(Raw_Xero_Invoices!M6:M26,"Unsent") -> 2
B54: Xero: Void Invoices Count | C54: =COUNTIF(Raw_Xero_Invoices!M6:M26,"Void") -> 2
B55: Stripe: Draft Transactions Count | C55: =COUNTIF(Raw_Stripe!P6:P49,"Draft") -> 3
B56: Stripe: Unsent Transactions Count | C56: =COUNTIF(Raw_Stripe!P6:P49,"Unsent") -> 3
B57: Stripe: Void Transactions Count | C57: =COUNTIF(Raw_Stripe!P6:P49,"Void") -> 2
B60: STATUS LEGEND
B61: Draft | C61: Invoice created but not yet finalized/sent. Cannot be paid yet.
B62: Unsent | C62: Invoice finalized but not yet emailed to customer.
B63: Awaiting Payment | C63: Invoice sent to customer, awaiting payment (overdue if past due).
B64: Partial | C64: Customer has paid part of the invoice; balance still owed.
B65: Paid | C65: Invoice fully paid. Counted in revenue but not in outstanding.
B66: Void | C66: Invoice cancelled. Excluded from revenue and outstanding totals.

Sheet Meta_Expenses
B2: Meta Expenses · With Discount Add-Back
B3: Per-customer Meta cost: Net Paid + Discount Given = Amount With Add-Back (USD)
B5: PER-CUSTOMER META COST (USD equivalent, with add-back)
B6: Customer | C6: Gross Billed | D6: Discount Given | E6: Net Paid | F6: Amount With AddBack | G6: % Discount | H6: # Invoices | I6: Jan | J6: Feb | K6: Mar | L6: Apr | M6: May | N6: Jun | O6: Jul-Aug-Dec
B7: Alphabet Logistics LLC | C7: =SUMIFS(Raw_Meta!$L$6:$L$28,Raw_Meta!$E$6:$E$28,B7) -> 35700 | D7: =IFERROR(SUMIFS(Raw_Meta!$L$6:$L$28,Raw_Meta!$E$6:$E$28,B7)*SUMIFS(Raw_Meta!$H$6:$H$28,Raw_Meta!$E$6:$E$28,B7)/SUMIFS(Raw_Meta!$G$6:$G$28,Raw_Meta!$E$6:$E$28,B7),0) -> 3500 | E7: =C7-D7 -> 32200 | F7: =C7 -> 35700 | G7: =IFERROR(D7/C7,0) -> 0.098039216 | H7: =COUNTIFS(Raw_Meta!$E$6:$E$28,B7) -> 6 | I7: =SUMIFS(Raw_Meta!$L$6:$L$28,Raw_Meta!$E$6:$E$28,B7,Raw_Meta!$N$6:$N$28,"Jan-25") -> 5200 | J7: =SUMIFS(Raw_Meta!$L$6:$L$28,Raw_Meta!$E$6:$E$28,B7,Raw_Meta!$N$6:$N$28,"Feb-25") -> 5500 | K7: =SUMIFS(Raw_Meta!$L$6:$L$28,Raw_Meta!$E$6:$E$28,B7,Raw_Meta!$N$6:$N$28,"Mar-25") -> 5800 | L7: =SUMIFS(Raw_Meta!$L$6:$L$28,Raw_Meta!$E$6:$E$28,B7,Raw_Meta!$N$6:$N$28,"Apr-25") -> 6100 | M7: =SUMIFS(Raw_Meta!$L$6:$L$28,Raw_Meta!$E$6:$E$28,B7,Raw_Meta!$N$6:$N$28,"May-25") -> 6300 | N7: =SUMIFS(Raw_Meta!$L$6:$L$28,Raw_Meta!$E$6:$E$28,B7,Raw_Meta!$N$6:$N$28,"Jun-25") -> 0 | O7: =SUMIFS(Raw_Meta!$L$6:$L$28,Raw_Meta!$E$6:$E$28,B7,Raw_Meta!$N$6:$N$28,"Jul-25")+SUMIFS(Raw_Meta!$L$6:$L$28,Raw_Meta!$E$6:$E$28,B7,Raw_Meta!$N$6:$N$28,"Aug-25")+SUMIFS(Raw_Meta!$L$6:$L$28,Raw_Meta!$E$6:$E$28,B7,Raw_Meta!$N$6:$N$28,"Sep-25")+SUMIFS(Raw_Meta!$L$6:$L$28,Raw_Meta!$E$6:$E$28,B7,Raw_Meta!$N$6:$N$28,"Oct-25")+SUMIFS(Raw_Meta!$L$6:$L$28,Raw_Meta!$E$6:$E$28,B7,Raw_Meta!$N$6:$N$28,"Nov-25")+SUMIFS(Raw_Meta!$L$6:$L$28,Raw_Meta!$E$6:$E$28,B7,Raw_Meta!$N$6:$N$28,"Dec-25") -> 6800
B8: Emirates Retail Group | C8: =SUMIFS(Raw_Meta!$L$6:$L$28,Raw_Meta!$E$6:$E$28,B8) -> 7800 | D8: =IFERROR(SUMIFS(Raw_Meta!$L$6:$L$28,Raw_Meta!$E$6:$E$28,B8)*SUMIFS(Raw_Meta!$H$6:$H$28,Raw_Meta!$E$6:$E$28,B8)/SUMIFS(Raw_Meta!$G$6:$G$28,Raw_Meta!$E$6:$E$28,B8),0) -> 600 | E8: =C8-D8 -> 7200 | F8: =C8 -> 7800 | G8: =IFERROR(D8/C8,0) -> 0.076923077 | H8: =COUNTIFS(Raw_Meta!$E$6:$E$28,B8) -> 2 | I8: =SUMIFS(Raw_Meta!$L$6:$L$28,Raw_Meta!$E$6:$E$28,B8,Raw_Meta!$N$6:$N$28,"Jan-25") -> 3800 | J8: =SUMIFS(Raw_Meta!$L$6:$L$28,Raw_Meta!$E$6:$E$28,B8,Raw_Meta!$N$6:$N$28,"Feb-25") -> 4000 | K8: =SUMIFS(Raw_Meta!$L$6:$L$28,Raw_Meta!$E$6:$E$28,B8,Raw_Meta!$N$6:$N$28,"Mar-25") -> 0 | L8: =SUMIFS(Raw_Meta!$L$6:$L$28,Raw_Meta!$E$6:$E$28,B8,Raw_Meta!$N$6:$N$28,"Apr-25") -> 0 | M8: =SUMIFS(Raw_Meta!$L$6:$L$28,Raw_Meta!$E$6:$E$28,B8,Raw_Meta!$N$6:$N$28,"May-25") -> 0 | N8: =SUMIFS(Raw_Meta!$L$6:$L$28,Raw_Meta!$E$6:$E$28,B8,Raw_Meta!$N$6:$N$28,"Jun-25") -> 0 | O8: =SUMIFS(Raw_Meta!$L$6:$L$28,Raw_Meta!$E$6:$E$28,B8,Raw_Meta!$N$6:$N$28,"Jul-25")+SUMIFS(Raw_Meta!$L$6:$L$28,Raw_Meta!$E$6:$E$28,B8,Raw_Meta!$N$6:$N$28,"Aug-25")+SUMIFS(Raw_Meta!$L$6:$L$28,Raw_Meta!$E$6:$E$28,B8,Raw_Meta!$N$6:$N$28,"Sep-25")+SUMIFS(Raw_Meta!$L$6:$L$28,Raw_Meta!$E$6:$E$28,B8,Raw_Meta!$N$6:$N$28,"Oct-25")+SUMIFS(Raw_Meta!$L$6:$L$28,Raw_Meta!$E$6:$E$28,B8,Raw_Meta!$N$6:$N$28,"Nov-25")+SUMIFS(Raw_Meta!$L$6:$L$28,Raw_Meta!$E$6:$E$28,B8,Raw_Meta!$N$6:$N$28,"Dec-25") -> 0
B9: Gulf Tech Distribution | C9: =SUMIFS(Raw_Meta!$L$6:$L$28,Raw_Meta!$E$6:$E$28,B9) -> 20400 | D9: =IFERROR(SUMIFS(Raw_Meta!$L$6:$L$28,Raw_Meta!$E$6:$E$28,B9)*SUMIFS(Raw_Meta!$H$6:$H$28,Raw_Meta!$E$6:$E$28,B9)/SUMIFS(Raw_Meta!$G$6:$G$28,Raw_Meta!$E$6:$E$28,B9),0) -> 1650 | E9: =C9-D9 -> 18750 | F9: =C9 -> 20400 | G9: =IFERROR(D9/C9,0) -> 0.080882353 | H9: =COUNTIFS(Raw_Meta!$E$6:$E$28,B9) -> 3 | I9: =SUMIFS(Raw_Meta!$L$6:$L$28,Raw_Meta!$E$6:$E$28,B9,Raw_Meta!$N$6:$N$28,"Jan-25") -> 6500 | J9: =SUMIFS(Raw_Meta!$L$6:$L$28,Raw_Meta!$E$6:$E$28,B9,Raw_Meta!$N$6:$N$28,"Feb-25") -> 6800 | K9: =SUMIFS(Raw_Meta!$L$6:$L$28,Raw_Meta!$E$6:$E$28,B9,Raw_Meta!$N$6:$N$28,"Mar-25") -> 0 | L9: =SUMIFS(Raw_Meta!$L$6:$L$28,Raw_Meta!$E$6:$E$28,B9,Raw_Meta!$N$6:$N$28,"Apr-25") -> 0 | M9: =SUMIFS(Raw_Meta!$L$6:$L$28,Raw_Meta!$E$6:$E$28,B9,Raw_Meta!$N$6:$N$28,"May-25") -> 7100 | N9: =SUMIFS(Raw_Meta!$L$6:$L$28,Raw_Meta!$E$6:$E$28,B9,Raw_Meta!$N$6:$N$28,"Jun-25") -> 0 | O9: =SUMIFS(Raw_Meta!$L$6:$L$28,Raw_Meta!$E$6:$E$28,B9,Raw_Meta!$N$6:$N$28,"Jul-25")+SUMIFS(Raw_Meta!$L$6:$L$28,Raw_Meta!$E$6:$E$28,B9,Raw_Meta!$N$6:$N$28,"Aug-25")+SUMIFS(Raw_Meta!$L$6:$L$28,Raw_Meta!$E$6:$E$28,B9,Raw_Meta!$N$6:$N$28,"Sep-25")+SUMIFS(Raw_Meta!$L$6:$L$28,Raw_Meta!$E$6:$E$28,B9,Raw_Meta!$N$6:$N$28,"Oct-25")+SUMIFS(Raw_Meta!$L$6:$L$28,Raw_Meta!$E$6:$E$28,B9,Raw_Meta!$N$6:$N$28,"Nov-25")+SUMIFS(Raw_Meta!$L$6:$L$28,Raw_Meta!$E$6:$E$28,B9,Raw_Meta!$N$6:$N$28,"Dec-25") -> 0
B10: Singapore FinTech Hub | C10: =SUMIFS(Raw_Meta!$L$6:$L$28,Raw_Meta!$E$6:$E$28,B10) -> 8700 | D10: =IFERROR(SUMIFS(Raw_Meta!$L$6:$L$28,Raw_Meta!$E$6:$E$28,B10)*SUMIFS(Raw_Meta!$H$6:$H$28,Raw_Meta!$E$6:$E$28,B10)/SUMIFS(Raw_Meta!$G$6:$G$28,Raw_Meta!$E$6:$E$28,B10),0) -> 750 | E10: =C10-D10 -> 7950 | F10: =C10 -> 8700 | G10: =IFERROR(D10/C10,0) -> 0.086206897 | H10: =COUNTIFS(Raw_Meta!$E$6:$E$28,B10) -> 2 | I10: =SUMIFS(Raw_Meta!$L$6:$L$28,Raw_Meta!$E$6:$E$28,B10,Raw_Meta!$N$6:$N$28,"Jan-25") -> 4200 | J10: =SUMIFS(Raw_Meta!$L$6:$L$28,Raw_Meta!$E$6:$E$28,B10,Raw_Meta!$N$6:$N$28,"Feb-25") -> 0 | K10: =SUMIFS(Raw_Meta!$L$6:$L$28,Raw_Meta!$E$6:$E$28,B10,Raw_Meta!$N$6:$N$28,"Mar-25") -> 0 | L10: =SUMIFS(Raw_Meta!$L$6:$L$28,Raw_Meta!$E$6:$E$28,B10,Raw_Meta!$N$6:$N$28,"Apr-25") -> 0 | M10: =SUMIFS(Raw_Meta!$L$6:$L$28,Raw_Meta!$E$6:$E$28,B10,Raw_Meta!$N$6:$N$28,"May-25") -> 0 | N10: =SUMIFS(Raw_Meta!$L$6:$L$28,Raw_Meta!$E$6:$E$28,B10,Raw_Meta!$N$6:$N$28,"Jun-25") -> 0 | O10: =SUMIFS(Raw_Meta!$L$6:$L$28,Raw_Meta!$E$6:$E$28,B10,Raw_Meta!$N$6:$N$28,"Jul-25")+SUMIFS(Raw_Meta!$L$6:$L$28,Raw_Meta!$E$6:$E$28,B10,Raw_Meta!$N$6:$N$28,"Aug-25")+SUMIFS(Raw_Meta!$L$6:$L$28,Raw_Meta!$E$6:$E$28,B10,Raw_Meta!$N$6:$N$28,"Sep-25")+SUMIFS(Raw_Meta!$L$6:$L$28,Raw_Meta!$E$6:$E$28,B10,Raw_Meta!$N$6:$N$28,"Oct-25")+SUMIFS(Raw_Meta!$L$6:$L$28,Raw_Meta!$E$6:$E$28,B10,Raw_Meta!$N$6:$N$28,"Nov-25")+SUMIFS(Raw_Meta!$L$6:$L$28,Raw_Meta!$E$6:$E$28,B10,Raw_Meta!$N$6:$N$28,"Dec-25") -> 4500
B11: Abu Dhabi Trading | C11: =SUMIFS(Raw_Meta!$L$6:$L$28,Raw_Meta!$E$6:$E$28,B11) -> 4500 | D11: =IFERROR(SUMIFS(Raw_Meta!$L$6:$L$28,Raw_Meta!$E$6:$E$28,B11)*SUMIFS(Raw_Meta!$H$6:$H$28,Raw_Meta!$E$6:$E$28,B11)/SUMIFS(Raw_Meta!$G$6:$G$28,Raw_Meta!$E$6:$E$28,B11),0) -> 400 | E11: =C11-D11 -> 4100 | F11: =C11 -> 4500 | G11: =IFERROR(D11/C11,0) -> 0.088888889 | H11: =COUNTIFS(Raw_Meta!$E$6:$E$28,B11) -> 1 | I11: =SUMIFS(Raw_Meta!$L$6:$L$28,Raw_Meta!$E$6:$E$28,B11,Raw_Meta!$N$6:$N$28,"Jan-25") -> 0 | J11: =SUMIFS(Raw_Meta!$L$6:$L$28,Raw_Meta!$E$6:$E$28,B11,Raw_Meta!$N$6:$N$28,"Feb-25") -> 0 | K11: =SUMIFS(Raw_Meta!$L$6:$L$28,Raw_Meta!$E$6:$E$28,B11,Raw_Meta!$N$6:$N$28,"Mar-25") -> 4500 | L11: =SUMIFS(Raw_Meta!$L$6:$L$28,Raw_Meta!$E$6:$E$28,B11,Raw_Meta!$N$6:$N$28,"Apr-25") -> 0 | M11: =SUMIFS(Raw_Meta!$L$6:$L$28,Raw_Meta!$E$6:$E$28,B11,Raw_Meta!$N$6:$N$28,"May-25") -> 0 | N11: =SUMIFS(Raw_Meta!$L$6:$L$28,Raw_Meta!$E$6:$E$28,B11,Raw_Meta!$N$6:$N$28,"Jun-25") -> 0 | O11: =SUMIFS(Raw_Meta!$L$6:$L$28,Raw_Meta!$E$6:$E$28,B11,Raw_Meta!$N$6:$N$28,"Jul-25")+SUMIFS(Raw_Meta!$L$6:$L$28,Raw_Meta!$E$6:$E$28,B11,Raw_Meta!$N$6:$N$28,"Aug-25")+SUMIFS(Raw_Meta!$L$6:$L$28,Raw_Meta!$E$6:$E$28,B11,Raw_Meta!$N$6:$N$28,"Sep-25")+SUMIFS(Raw_Meta!$L$6:$L$28,Raw_Meta!$E$6:$E$28,B11,Raw_Meta!$N$6:$N$28,"Oct-25")+SUMIFS(Raw_Meta!$L$6:$L$28,Raw_Meta!$E$6:$E$28,B11,Raw_Meta!$N$6:$N$28,"Nov-25")+SUMIFS(Raw_Meta!$L$6:$L$28,Raw_Meta!$E$6:$E$28,B11,Raw_Meta!$N$6:$N$28,"Dec-25") -> 0
B12: Rak Bank Digital | C12: =SUMIFS(Raw_Meta!$L$6:$L$28,Raw_Meta!$E$6:$E$28,B12) -> 7200 | D12: =IFERROR(SUMIFS(Raw_Meta!$L$6:$L$28,Raw_Meta!$E$6:$E$28,B12)*SUMIFS(Raw_Meta!$H$6:$H$28,Raw_Meta!$E$6:$E$28,B12)/SUMIFS(Raw_Meta!$G$6:$G$28,Raw_Meta!$E$6:$E$28,B12),0) -> 600 | E12: =C12-D12 -> 6600 | F12: =C12 -> 7200 | G12: =IFERROR(D12/C12,0) -> 0.083333333 | H12: =COUNTIFS(Raw_Meta!$E$6:$E$28,B12) -> 1 | I12: =SUMIFS(Raw_Meta!$L$6:$L$28,Raw_Meta!$E$6:$E$28,B12,Raw_Meta!$N$6:$N$28,"Jan-25") -> 0 | J12: =SUMIFS(Raw_Meta!$L$6:$L$28,Raw_Meta!$E$6:$E$28,B12,Raw_Meta!$N$6:$N$28,"Feb-25") -> 0 | K12: =SUMIFS(Raw_Meta!$L$6:$L$28,Raw_Meta!$E$6:$E$28,B12,Raw_Meta!$N$6:$N$28,"Mar-25") -> 7200 | L12: =SUMIFS(Raw_Meta!$L$6:$L$28,Raw_Meta!$E$6:$E$28,B12,Raw_Meta!$N$6:$N$28,"Apr-25") -> 0 | M12: =SUMIFS(Raw_Meta!$L$6:$L$28,Raw_Meta!$E$6:$E$28,B12,Raw_Meta!$N$6:$N$28,"May-25") -> 0 | N12: =SUMIFS(Raw_Meta!$L$6:$L$28,Raw_Meta!$E$6:$E$28,B12,Raw_Meta!$N$6:$N$28,"Jun-25") -> 0 | O12: =SUMIFS(Raw_Meta!$L$6:$L$28,Raw_Meta!$E$6:$E$28,B12,Raw_Meta!$N$6:$N$28,"Jul-25")+SUMIFS(Raw_Meta!$L$6:$L$28,Raw_Meta!$E$6:$E$28,B12,Raw_Meta!$N$6:$N$28,"Aug-25")+SUMIFS(Raw_Meta!$L$6:$L$28,Raw_Meta!$E$6:$E$28,B12,Raw_Meta!$N$6:$N$28,"Sep-25")+SUMIFS(Raw_Meta!$L$6:$L$28,Raw_Meta!$E$6:$E$28,B12,Raw_Meta!$N$6:$N$28,"Oct-25")+SUMIFS(Raw_Meta!$L$6:$L$28,Raw_Meta!$E$6:$E$28,B12,Raw_Meta!$N$6:$N$28,"Nov-25")+SUMIFS(Raw_Meta!$L$6:$L$28,Raw_Meta!$E$6:$E$28,B12,Raw_Meta!$N$6:$N$28,"Dec-25") -> 0
B13: Asia Pacific Solutions | C13: =SUMIFS(Raw_Meta!$L$6:$L$28,Raw_Meta!$E$6:$E$28,B13) -> 8500 | D13: =IFERROR(SUMIFS(Raw_Meta!$L$6:$L$28,Raw_Meta!$E$6:$E$28,B13)*SUMIFS(Raw_Meta!$H$6:$H$28,Raw_Meta!$E$6:$E$28,B13)/SUMIFS(Raw_Meta!$G$6:$G$28,Raw_Meta!$E$6:$E$28,B13),0) -> 700 | E13: =C13-D13 -> 7800 | F13: =C13 -> 8500 | G13: =IFERROR(D13/C13,0) -> 0.082352941 | H13: =COUNTIFS(Raw_Meta!$E$6:$E$28,B13) -> 1 | I13: =SUMIFS(Raw_Meta!$L$6:$L$28,Raw_Meta!$E$6:$E$28,B13,Raw_Meta!$N$6:$N$28,"Jan-25") -> 0 | J13: =SUMIFS(Raw_Meta!$L$6:$L$28,Raw_Meta!$E$6:$E$28,B13,Raw_Meta!$N$6:$N$28,"Feb-25") -> 0 | K13: =SUMIFS(Raw_Meta!$L$6:$L$28,Raw_Meta!$E$6:$E$28,B13,Raw_Meta!$N$6:$N$28,"Mar-25") -> 8500 | L13: =SUMIFS(Raw_Meta!$L$6:$L$28,Raw_Meta!$E$6:$E$28,B13,Raw_Meta!$N$6:$N$28,"Apr-25") -> 0 | M13: =SUMIFS(Raw_Meta!$L$6:$L$28,Raw_Meta!$E$6:$E$28,B13,Raw_Meta!$N$6:$N$28,"May-25") -> 0 | N13: =SUMIFS(Raw_Meta!$L$6:$L$28,Raw_Meta!$E$6:$E$28,B13,Raw_Meta!$N$6:$N$28,"Jun-25") -> 0 | O13: =SUMIFS(Raw_Meta!$L$6:$L$28,Raw_Meta!$E$6:$E$28,B13,Raw_Meta!$N$6:$N$28,"Jul-25")+SUMIFS(Raw_Meta!$L$6:$L$28,Raw_Meta!$E$6:$E$28,B13,Raw_Meta!$N$6:$N$28,"Aug-25")+SUMIFS(Raw_Meta!$L$6:$L$28,Raw_Meta!$E$6:$E$28,B13,Raw_Meta!$N$6:$N$28,"Sep-25")+SUMIFS(Raw_Meta!$L$6:$L$28,Raw_Meta!$E$6:$E$28,B13,Raw_Meta!$N$6:$N$28,"Oct-25")+SUMIFS(Raw_Meta!$L$6:$L$28,Raw_Meta!$E$6:$E$28,B13,Raw_Meta!$N$6:$N$28,"Nov-25")+SUMIFS(Raw_Meta!$L$6:$L$28,Raw_Meta!$E$6:$E$28,B13,Raw_Meta!$N$6:$N$28,"Dec-25") -> 0
B14: Lion City Media | C14: =SUMIFS(Raw_Meta!$L$6:$L$28,Raw_Meta!$E$6:$E$28,B14) -> 4300 | D14: =IFERROR(SUMIFS(Raw_Meta!$L$6:$L$28,Raw_Meta!$E$6:$E$28,B14)*SUMIFS(Raw_Meta!$H$6:$H$28,Raw_Meta!$E$6:$E$28,B14)/SUMIFS(Raw_Meta!$G$6:$G$28,Raw_Meta!$E$6:$E$28,B14),0) -> 350 | E14: =C14-D14 -> 3950 | F14: =C14 -> 4300 | G14: =IFERROR(D14/C14,0) -> 0.081395349 | H14: =COUNTIFS(Raw_Meta!$E$6:$E$28,B14) -> 1 | I14: =SUMIFS(Raw_Meta!$L$6:$L$28,Raw_Meta!$E$6:$E$28,B14,Raw_Meta!$N$6:$N$28,"Jan-25") -> 0 | J14: =SUMIFS(Raw_Meta!$L$6:$L$28,Raw_Meta!$E$6:$E$28,B14,Raw_Meta!$N$6:$N$28,"Feb-25") -> 0 | K14: =SUMIFS(Raw_Meta!$L$6:$L$28,Raw_Meta!$E$6:$E$28,B14,Raw_Meta!$N$6:$N$28,"Mar-25") -> 4300 | L14: =SUMIFS(Raw_Meta!$L$6:$L$28,Raw_Meta!$E$6:$E$28,B14,Raw_Meta!$N$6:$N$28,"Apr-25") -> 0 | M14: =SUMIFS(Raw_Meta!$L$6:$L$28,Raw_Meta!$E$6:$E$28,B14,Raw_Meta!$N$6:$N$28,"May-25") -> 0 | N14: =SUMIFS(Raw_Meta!$L$6:$L$28,Raw_Meta!$E$6:$E$28,B14,Raw_Meta!$N$6:$N$28,"Jun-25") -> 0 | O14: =SUMIFS(Raw_Meta!$L$6:$L$28,Raw_Meta!$E$6:$E$28,B14,Raw_Meta!$N$6:$N$28,"Jul-25")+SUMIFS(Raw_Meta!$L$6:$L$28,Raw_Meta!$E$6:$E$28,B14,Raw_Meta!$N$6:$N$28,"Aug-25")+SUMIFS(Raw_Meta!$L$6:$L$28,Raw_Meta!$E$6:$E$28,B14,Raw_Meta!$N$6:$N$28,"Sep-25")+SUMIFS(Raw_Meta!$L$6:$L$28,Raw_Meta!$E$6:$E$28,B14,Raw_Meta!$N$6:$N$28,"Oct-25")+SUMIFS(Raw_Meta!$L$6:$L$28,Raw_Meta!$E$6:$E$28,B14,Raw_Meta!$N$6:$N$28,"Nov-25")+SUMIFS(Raw_Meta!$L$6:$L$28,Raw_Meta!$E$6:$E$28,B14,Raw_Meta!$N$6:$N$28,"Dec-25") -> 0
B15: Sentosa E-Commerce | C15: =SUMIFS(Raw_Meta!$L$6:$L$28,Raw_Meta!$E$6:$E$28,B15) -> 3200 | D15: =IFERROR(SUMIFS(Raw_Meta!$L$6:$L$28,Raw_Meta!$E$6:$E$28,B15)*SUMIFS(Raw_Meta!$H$6:$H$28,Raw_Meta!$E$6:$E$28,B15)/SUMIFS(Raw_Meta!$G$6:$G$28,Raw_Meta!$E$6:$E$28,B15),0) -> 250 | E15: =C15-D15 -> 2950 | F15: =C15 -> 3200 | G15: =IFERROR(D15/C15,0) -> 0.078125 | H15: =COUNTIFS(Raw_Meta!$E$6:$E$28,B15) -> 1 | I15: =SUMIFS(Raw_Meta!$L$6:$L$28,Raw_Meta!$E$6:$E$28,B15,Raw_Meta!$N$6:$N$28,"Jan-25") -> 0 | J15: =SUMIFS(Raw_Meta!$L$6:$L$28,Raw_Meta!$E$6:$E$28,B15,Raw_Meta!$N$6:$N$28,"Feb-25") -> 0 | K15: =SUMIFS(Raw_Meta!$L$6:$L$28,Raw_Meta!$E$6:$E$28,B15,Raw_Meta!$N$6:$N$28,"Mar-25") -> 0 | L15: =SUMIFS(Raw_Meta!$L$6:$L$28,Raw_Meta!$E$6:$E$28,B15,Raw_Meta!$N$6:$N$28,"Apr-25") -> 3200 | M15: =SUMIFS(Raw_Meta!$L$6:$L$28,Raw_Meta!$E$6:$E$28,B15,Raw_Meta!$N$6:$N$28,"May-25") -> 0 | N15: =SUMIFS(Raw_Meta!$L$6:$L$28,Raw_Meta!$E$6:$E$28,B15,Raw_Meta!$N$6:$N$28,"Jun-25") -> 0 | O15: =SUMIFS(Raw_Meta!$L$6:$L$28,Raw_Meta!$E$6:$E$28,B15,Raw_Meta!$N$6:$N$28,"Jul-25")+SUMIFS(Raw_Meta!$L$6:$L$28,Raw_Meta!$E$6:$E$28,B15,Raw_Meta!$N$6:$N$28,"Aug-25")+SUMIFS(Raw_Meta!$L$6:$L$28,Raw_Meta!$E$6:$E$28,B15,Raw_Meta!$N$6:$N$28,"Sep-25")+SUMIFS(Raw_Meta!$L$6:$L$28,Raw_Meta!$E$6:$E$28,B15,Raw_Meta!$N$6:$N$28,"Oct-25")+SUMIFS(Raw_Meta!$L$6:$L$28,Raw_Meta!$E$6:$E$28,B15,Raw_Meta!$N$6:$N$28,"Nov-25")+SUMIFS(Raw_Meta!$L$6:$L$28,Raw_Meta!$E$6:$E$28,B15,Raw_Meta!$N$6:$N$28,"Dec-25") -> 0
B16: Marina Bay Holdings | C16: =SUMIFS(Raw_Meta!$L$6:$L$28,Raw_Meta!$E$6:$E$28,B16) -> 3900 | D16: =IFERROR(SUMIFS(Raw_Meta!$L$6:$L$28,Raw_Meta!$E$6:$E$28,B16)*SUMIFS(Raw_Meta!$H$6:$H$28,Raw_Meta!$E$6:$E$28,B16)/SUMIFS(Raw_Meta!$G$6:$G$28,Raw_Meta!$E$6:$E$28,B16),0) -> 300 | E16: =C16-D16 -> 3600 | F16: =C16 -> 3900 | G16: =IFERROR(D16/C16,0) -> 0.076923077 | H16: =COUNTIFS(Raw_Meta!$E$6:$E$28,B16) -> 1 | I16: =SUMIFS(Raw_Meta!$L$6:$L$28,Raw_Meta!$E$6:$E$28,B16,Raw_Meta!$N$6:$N$28,"Jan-25") -> 0 | J16: =SUMIFS(Raw_Meta!$L$6:$L$28,Raw_Meta!$E$6:$E$28,B16,Raw_Meta!$N$6:$N$28,"Feb-25") -> 0 | K16: =SUMIFS(Raw_Meta!$L$6:$L$28,Raw_Meta!$E$6:$E$28,B16,Raw_Meta!$N$6:$N$28,"Mar-25") -> 0 | L16: =SUMIFS(Raw_Meta!$L$6:$L$28,Raw_Meta!$E$6:$E$28,B16,Raw_Meta!$N$6:$N$28,"Apr-25") -> 0 | M16: =SUMIFS(Raw_Meta!$L$6:$L$28,Raw_Meta!$E$6:$E$28,B16,Raw_Meta!$N$6:$N$28,"May-25") -> 3900 | N16: =SUMIFS(Raw_Meta!$L$6:$L$28,Raw_Meta!$E$6:$E$28,B16,Raw_Meta!$N$6:$N$28,"Jun-25") -> 0 | O16: =SUMIFS(Raw_Meta!$L$6:$L$28,Raw_Meta!$E$6:$E$28,B16,Raw_Meta!$N$6:$N$28,"Jul-25")+SUMIFS(Raw_Meta!$L$6:$L$28,Raw_Meta!$E$6:$E$28,B16,Raw_Meta!$N$6:$N$28,"Aug-25")+SUMIFS(Raw_Meta!$L$6:$L$28,Raw_Meta!$E$6:$E$28,B16,Raw_Meta!$N$6:$N$28,"Sep-25")+SUMIFS(Raw_Meta!$L$6:$L$28,Raw_Meta!$E$6:$E$28,B16,Raw_Meta!$N$6:$N$28,"Oct-25")+SUMIFS(Raw_Meta!$L$6:$L$28,Raw_Meta!$E$6:$E$28,B16,Raw_Meta!$N$6:$N$28,"Nov-25")+SUMIFS(Raw_Meta!$L$6:$L$28,Raw_Meta!$E$6:$E$28,B16,Raw_Meta!$N$6:$N$28,"Dec-25") -> 0
B17: Dubai Properties Co | C17: =SUMIFS(Raw_Meta!$L$6:$L$28,Raw_Meta!$E$6:$E$28,B17) -> 6600 | D17: =IFERROR(SUMIFS(Raw_Meta!$L$6:$L$28,Raw_Meta!$E$6:$E$28,B17)*SUMIFS(Raw_Meta!$H$6:$H$28,Raw_Meta!$E$6:$E$28,B17)/SUMIFS(Raw_Meta!$G$6:$G$28,Raw_Meta!$E$6:$E$28,B17),0) -> 700 | E17: =C17-D17 -> 5900 | F17: =C17 -> 6600 | G17: =IFERROR(D17/C17,0) -> 0.10606061 | H17: =COUNTIFS(Raw_Meta!$E$6:$E$28,B17) -> 1 | I17: =SUMIFS(Raw_Meta!$L$6:$L$28,Raw_Meta!$E$6:$E$28,B17,Raw_Meta!$N$6:$N$28,"Jan-25") -> 0 | J17: =SUMIFS(Raw_Meta!$L$6:$L$28,Raw_Meta!$E$6:$E$28,B17,Raw_Meta!$N$6:$N$28,"Feb-25") -> 0 | K17: =SUMIFS(Raw_Meta!$L$6:$L$28,Raw_Meta!$E$6:$E$28,B17,Raw_Meta!$N$6:$N$28,"Mar-25") -> 0 | L17: =SUMIFS(Raw_Meta!$L$6:$L$28,Raw_Meta!$E$6:$E$28,B17,Raw_Meta!$N$6:$N$28,"Apr-25") -> 0 | M17: =SUMIFS(Raw_Meta!$L$6:$L$28,Raw_Meta!$E$6:$E$28,B17,Raw_Meta!$N$6:$N$28,"May-25") -> 0 | N17: =SUMIFS(Raw_Meta!$L$6:$L$28,Raw_Meta!$E$6:$E$28,B17,Raw_Meta!$N$6:$N$28,"Jun-25") -> 6600 | O17: =SUMIFS(Raw_Meta!$L$6:$L$28,Raw_Meta!$E$6:$E$28,B17,Raw_Meta!$N$6:$N$28,"Jul-25")+SUMIFS(Raw_Meta!$L$6:$L$28,Raw_Meta!$E$6:$E$28,B17,Raw_Meta!$N$6:$N$28,"Aug-25")+SUMIFS(Raw_Meta!$L$6:$L$28,Raw_Meta!$E$6:$E$28,B17,Raw_Meta!$N$6:$N$28,"Sep-25")+SUMIFS(Raw_Meta!$L$6:$L$28,Raw_Meta!$E$6:$E$28,B17,Raw_Meta!$N$6:$N$28,"Oct-25")+SUMIFS(Raw_Meta!$L$6:$L$28,Raw_Meta!$E$6:$E$28,B17,Raw_Meta!$N$6:$N$28,"Nov-25")+SUMIFS(Raw_Meta!$L$6:$L$28,Raw_Meta!$E$6:$E$28,B17,Raw_Meta!$N$6:$N$28,"Dec-25") -> 0
B18: Mena Apps FZ-LLC | C18: =SUMIFS(Raw_Meta!$L$6:$L$28,Raw_Meta!$E$6:$E$28,B18) -> 5800 | D18: =IFERROR(SUMIFS(Raw_Meta!$L$6:$L$28,Raw_Meta!$E$6:$E$28,B18)*SUMIFS(Raw_Meta!$H$6:$H$28,Raw_Meta!$E$6:$E$28,B18)/SUMIFS(Raw_Meta!$G$6:$G$28,Raw_Meta!$E$6:$E$28,B18),0) -> 450 | E18: =C18-D18 -> 5350 | F18: =C18 -> 5800 | G18: =IFERROR(D18/C18,0) -> 0.077586207 | H18: =COUNTIFS(Raw_Meta!$E$6:$E$28,B18) -> 1 | I18: =SUMIFS(Raw_Meta!$L$6:$L$28,Raw_Meta!$E$6:$E$28,B18,Raw_Meta!$N$6:$N$28,"Jan-25") -> 0 | J18: =SUMIFS(Raw_Meta!$L$6:$L$28,Raw_Meta!$E$6:$E$28,B18,Raw_Meta!$N$6:$N$28,"Feb-25") -> 0 | K18: =SUMIFS(Raw_Meta!$L$6:$L$28,Raw_Meta!$E$6:$E$28,B18,Raw_Meta!$N$6:$N$28,"Mar-25") -> 0 | L18: =SUMIFS(Raw_Meta!$L$6:$L$28,Raw_Meta!$E$6:$E$28,B18,Raw_Meta!$N$6:$N$28,"Apr-25") -> 0 | M18: =SUMIFS(Raw_Meta!$L$6:$L$28,Raw_Meta!$E$6:$E$28,B18,Raw_Meta!$N$6:$N$28,"May-25") -> 0 | N18: =SUMIFS(Raw_Meta!$L$6:$L$28,Raw_Meta!$E$6:$E$28,B18,Raw_Meta!$N$6:$N$28,"Jun-25") -> 5800 | O18: =SUMIFS(Raw_Meta!$L$6:$L$28,Raw_Meta!$E$6:$E$28,B18,Raw_Meta!$N$6:$N$28,"Jul-25")+SUMIFS(Raw_Meta!$L$6:$L$28,Raw_Meta!$E$6:$E$28,B18,Raw_Meta!$N$6:$N$28,"Aug-25")+SUMIFS(Raw_Meta!$L$6:$L$28,Raw_Meta!$E$6:$E$28,B18,Raw_Meta!$N$6:$N$28,"Sep-25")+SUMIFS(Raw_Meta!$L$6:$L$28,Raw_Meta!$E$6:$E$28,B18,Raw_Meta!$N$6:$N$28,"Oct-25")+SUMIFS(Raw_Meta!$L$6:$L$28,Raw_Meta!$E$6:$E$28,B18,Raw_Meta!$N$6:$N$28,"Nov-25")+SUMIFS(Raw_Meta!$L$6:$L$28,Raw_Meta!$E$6:$E$28,B18,Raw_Meta!$N$6:$N$28,"Dec-25") -> 0
... B20: Jakarta Digital Ventures | C20: =SUMIFS(Raw_Meta!$L$6:$L$28,Raw_Meta!$E$6:$E$28,B20) -> 9800 | D20: =IFERROR(SUMIFS(Raw_Meta!$L$6:$L$28,Raw_Meta!$E$6:$E$28,B20)*SUMIFS(Raw_Meta!$H$6:$H$28,Raw_Meta!$E$6:$E$28,B20)/SUMIFS(Raw_Meta!$G$6:$G$28,Raw_Meta!$E$6:$E$28,B20),0) -> 800 | E20: =C20-D20 -> 9000 | F20: =C20 -> 9800 | G20: =IFERROR(D20/C20,0) -> 0.081632653 | H20: =COUNTIFS(Raw_Meta!$E$6:$E$28,B20) -> 1 | I20: =SUMIFS(Raw_Meta!$L$6:$L$28,Raw_Meta!$E$6:$E$28,B20,Raw_Meta!$N$6:$N$28,"Jan-25") -> 0 | J20: =SUMIFS(Raw_Meta!$L$6:$L$28,Raw_Meta!$E$6:$E$28,B20,Raw_Meta!$N$6:$N$28,"Feb-25") -> 0 | K20: =SUMIFS(Raw_Meta!$L$6:$L$28,Raw_Meta!$E$6:$E$28,B20,Raw_Meta!$N$6:$N$28,"Mar-25") -> 0 | L20: =SUMIFS(Raw_Meta!$L$6:$L$28,Raw_Meta!$E$6:$E$28,B20,Raw_Meta!$N$6:$N$28,"Apr-25") -> 0 | M20: =SUMIFS(Raw_Meta!$L$6:$L$28,Raw_Meta!$E$6:$E$28,B20,Raw_Meta!$N$6:$N$28,"May-25") -> 0 | N20: =SUMIFS(Raw_Meta!$L$6:$L$28,Raw_Meta!$E$6:$E$28,B20,Raw_Meta!$N$6:$N$28,"Jun-25") -> 0 | O20: =SUMIFS(Raw_Meta!$L$6:$L$28,Raw_Meta!$E$6:$E$28,B20,Raw_Meta!$N$6:$N$28,"Jul-25")+SUMIFS(Raw_Meta!$L$6:$L$28,Raw_Meta!$E$6:$E$28,B20,Raw_Meta!$N$6:$N$28,"Aug-25")+SUMIFS(Raw_Meta!$L$6:$L$28,Raw_Meta!$E$6:$E$28,B20,Raw_Meta!$N$6:$N$28,"Sep-25")+SUMIFS(Raw_Meta!$L$6:$L$28,Raw_Meta!$E$6:$E$28,B20,Raw_Meta!$N$6:$N$28,"Oct-25")+SUMIFS(Raw_Meta!$L$6:$L$28,Raw_Meta!$E$6:$E$28,B20,Raw_Meta!$N$6:$N$28,"Nov-25")+SUMIFS(Raw_Meta!$L$6:$L$28,Raw_Meta!$E$6:$E$28,B20,Raw_Meta!$N$6:$N$28,"Dec-25") -> 9800
B21: TOTAL | C21: =SUM(C7:C20) -> 133600 | D21: =SUM(D7:D20) -> 11650 | E21: =SUM(E7:E20) -> 121950 | F21: =SUM(F7:F20) -> 133600 | G21: =IFERROR(D21/C21,0) -> 0.087200599 | H21: =SUM(H7:H20) -> 23 | I21: =SUM(I7:I20) -> 19700 | J21: =SUM(J7:J20) -> 16300 | K21: =SUM(K7:K20) -> 30300 | L21: =SUM(L7:L20) -> 9300 | M21: =SUM(M7:M20) -> 17300 | N21: =SUM(N7:N20) -> 12400 | O21: =SUM(O7:O20) -> 28300
B24: MONTHLY META COST TREND (USD with add-back)
B25: Month | C25: Net Paid USD | D25: Discount USD | E25: AddBack USD
B26: Jan-25 | C26: =E26-D26 -> 18100 | D26: =IFERROR(SUMIFS(Raw_Meta!$L$6:$L$28,Raw_Meta!$N$6:$N$28,B26)*SUMIFS(Raw_Meta!$H$6:$H$28,Raw_Meta!$N$6:$N$28,B26)/SUMIFS(Raw_Meta!$G$6:$G$28,Raw_Meta!$N$6:$N$28,B26),0) -> 1600 | E26: =SUMIFS(Raw_Meta!$L$6:$L$28,Raw_Meta!$N$6:$N$28,B26) -> 19700
B27: Feb-25 | C27: =E27-D27 -> 14950 | D27: =IFERROR(SUMIFS(Raw_Meta!$L$6:$L$28,Raw_Meta!$N$6:$N$28,B27)*SUMIFS(Raw_Meta!$H$6:$H$28,Raw_Meta!$N$6:$N$28,B27)/SUMIFS(Raw_Meta!$G$6:$G$28,Raw_Meta!$N$6:$N$28,B27),0) -> 1350 | E27: =SUMIFS(Raw_Meta!$L$6:$L$28,Raw_Meta!$N$6:$N$28,B27) -> 16300
B28: Mar-25 | C28: =E28-D28 -> 27650 | D28: =IFERROR(SUMIFS(Raw_Meta!$L$6:$L$28,Raw_Meta!$N$6:$N$28,B28)*SUMIFS(Raw_Meta!$H$6:$H$28,Raw_Meta!$N$6:$N$28,B28)/SUMIFS(Raw_Meta!$G$6:$G$28,Raw_Meta!$N$6:$N$28,B28),0) -> 2650 | E28: =SUMIFS(Raw_Meta!$L$6:$L$28,Raw_Meta!$N$6:$N$28,B28) -> 30300
B29: Apr-25 | C29: =E29-D29 -> 8450 | D29: =IFERROR(SUMIFS(Raw_Meta!$L$6:$L$28,Raw_Meta!$N$6:$N$28,B29)*SUMIFS(Raw_Meta!$H$6:$H$28,Raw_Meta!$N$6:$N$28,B29)/SUMIFS(Raw_Meta!$G$6:$G$28,Raw_Meta!$N$6:$N$28,B29),0) -> 850 | E29: =SUMIFS(Raw_Meta!$L$6:$L$28,Raw_Meta!$N$6:$N$28,B29) -> 9300
B30: May-25 | C30: =E30-D30 -> 15750 | D30: =IFERROR(SUMIFS(Raw_Meta!$L$6:$L$28,Raw_Meta!$N$6:$N$28,B30)*SUMIFS(Raw_Meta!$H$6:$H$28,Raw_Meta!$N$6:$N$28,B30)/SUMIFS(Raw_Meta!$G$6:$G$28,Raw_Meta!$N$6:$N$28,B30),0) -> 1550 | E30: =SUMIFS(Raw_Meta!$L$6:$L$28,Raw_Meta!$N$6:$N$28,B30) -> 17300
B31: Jun-25 | C31: =E31-D31 -> 11250 | D31: =IFERROR(SUMIFS(Raw_Meta!$L$6:$L$28,Raw_Meta!$N$6:$N$28,B31)*SUMIFS(Raw_Meta!$H$6:$H$28,Raw_Meta!$N$6:$N$28,B31)/SUMIFS(Raw_Meta!$G$6:$G$28,Raw_Meta!$N$6:$N$28,B31),0) -> 1150 | E31: =SUMIFS(Raw_Meta!$L$6:$L$28,Raw_Meta!$N$6:$N$28,B31) -> 12400
B32: Jul-25 | C32: =E32-D32 -> 12700 | D32: =IFERROR(SUMIFS(Raw_Meta!$L$6:$L$28,Raw_Meta!$N$6:$N$28,B32)*SUMIFS(Raw_Meta!$H$6:$H$28,Raw_Meta!$N$6:$N$28,B32)/SUMIFS(Raw_Meta!$G$6:$G$28,Raw_Meta!$N$6:$N$28,B32),0) -> 1300 | E32: =SUMIFS(Raw_Meta!$L$6:$L$28,Raw_Meta!$N$6:$N$28,B32) -> 14000
B33: Aug-25 | C33: =E33-D33 -> 4100 | D33: =IFERROR(SUMIFS(Raw_Meta!$L$6:$L$28,Raw_Meta!$N$6:$N$28,B33)*SUMIFS(Raw_Meta!$H$6:$H$28,Raw_Meta!$N$6:$N$28,B33)/SUMIFS(Raw_Meta!$G$6:$G$28,Raw_Meta!$N$6:$N$28,B33),0) -> 400 | E33: =SUMIFS(Raw_Meta!$L$6:$L$28,Raw_Meta!$N$6:$N$28,B33) -> 4500
B34: Sep-25 | C34: =E34-D34 -> 9000 | D34: =IFERROR(SUMIFS(Raw_Meta!$L$6:$L$28,Raw_Meta!$N$6:$N$28,B34)*SUMIFS(Raw_Meta!$H$6:$H$28,Raw_Meta!$N$6:$N$28,B34)/SUMIFS(Raw_Meta!$G$6:$G$28,Raw_Meta!$N$6:$N$28,B34),0) -> 800 | E34: =SUMIFS(Raw_Meta!$L$6:$L$28,Raw_Meta!$N$6:$N$28,B34) -> 9800
B35: Oct-25 | C35: =E35-D35 -> 0 | D35: =IFERROR(SUMIFS(Raw_Meta!$L$6:$L$28,Raw_Meta!$N$6:$N$28,B35)*SUMIFS(Raw_Meta!$H$6:$H$28,Raw_Meta!$N$6:$N$28,B35)/SUMIFS(Raw_Meta!$G$6:$G$28,Raw_Meta!$N$6:$N$28,B35),0) -> 0 | E35: =SUMIFS(Raw_Meta!$L$6:$L$28,Raw_Meta!$N$6:$N$28,B35) -> 0
B36: Nov-25 | C36: =E36-D36 -> 0 | D36: =IFERROR(SUMIFS(Raw_Meta!$L$6:$L$28,Raw_Meta!$N$6:$N$28,B36)*SUMIFS(Raw_Meta!$H$6:$H$28,Raw_Meta!$N$6:$N$28,B36)/SUMIFS(Raw_Meta!$G$6:$G$28,Raw_Meta!$N$6:$N$28,B36),0) -> 0 | E36: =SUMIFS(Raw_Meta!$L$6:$L$28,Raw_Meta!$N$6:$N$28,B36) -> 0
B37: Dec-25 | C37: =E37-D37 -> 0 | D37: =IFERROR(SUMIFS(Raw_Meta!$L$6:$L$28,Raw_Meta!$N$6:$N$28,B37)*SUMIFS(Raw_Meta!$H$6:$H$28,Raw_Meta!$N$6:$N$28,B37)/SUMIFS(Raw_Meta!$G$6:$G$28,Raw_Meta!$N$6:$N$28,B37),0) -> 0 | E37: =SUMIFS(Raw_Meta!$L$6:$L$28,Raw_Meta!$N$6:$N$28,B37) -> 0
B38: YTD TOTAL | C38: =SUM(C26:C37) -> 121950 | D38: =SUM(D26:D37) -> 11650 | E38: =SUM(E26:E37) -> 133600
B41: META COST CHART (Net Paid vs Add-Back, monthly)

Sheet PnL_Statement
B2: P&L Statement · Monthly FY2025
B3: Revenue − Meta Costs − Stripe Fees − OpEx (Xero) − Bank Charges = Net Profit
B5: PROFIT & LOSS (USD equivalent)
B6: Line Item | C6: Jan-25 | D6: Feb-25 | E6: Mar-25 | F6: Apr-25 | G6: May-25 | H6: Jun-25 | I6: Jul-25 | J6: Aug-25 | K6: Sep-25 | L6: Oct-25 | M6: Nov-25 | N6: Dec-25 | O6: YTD Total | P6: % Rev
B7: WhatsApp Revenue | C7: =SUMIFS(Raw_Stripe!$H$6:$H$49,Raw_Stripe!$M$6:$M$49,"Jan-25",Raw_Stripe!$N$6:$N$49,"WhatsApp") -> 4202.01 | D7: =SUMIFS(Raw_Stripe!$H$6:$H$49,Raw_Stripe!$M$6:$M$49,"Feb-25",Raw_Stripe!$N$6:$N$49,"WhatsApp") -> 3825.85 | E7: =SUMIFS(Raw_Stripe!$H$6:$H$49,Raw_Stripe!$M$6:$M$49,"Mar-25",Raw_Stripe!$N$6:$N$49,"WhatsApp") -> 4625.64 | F7: =SUMIFS(Raw_Stripe!$H$6:$H$49,Raw_Stripe!$M$6:$M$49,"Apr-25",Raw_Stripe!$N$6:$N$49,"WhatsApp") -> 1279.81 | G7: =SUMIFS(Raw_Stripe!$H$6:$H$49,Raw_Stripe!$M$6:$M$49,"May-25",Raw_Stripe!$N$6:$N$49,"WhatsApp") -> 1334.27 | H7: =SUMIFS(Raw_Stripe!$H$6:$H$49,Raw_Stripe!$M$6:$M$49,"Jun-25",Raw_Stripe!$N$6:$N$49,"WhatsApp") -> 7061.03 | I7: =SUMIFS(Raw_Stripe!$H$6:$H$49,Raw_Stripe!$M$6:$M$49,"Jul-25",Raw_Stripe!$N$6:$N$49,"WhatsApp") -> 1415.96 | J7: =SUMIFS(Raw_Stripe!$H$6:$H$49,Raw_Stripe!$M$6:$M$49,"Aug-25",Raw_Stripe!$N$6:$N$49,"WhatsApp") -> 2831 | K7: =SUMIFS(Raw_Stripe!$H$6:$H$49,Raw_Stripe!$M$6:$M$49,"Sep-25",Raw_Stripe!$N$6:$N$49,"WhatsApp") -> 1851.64 | L7: =SUMIFS(Raw_Stripe!$H$6:$H$49,Raw_Stripe!$M$6:$M$49,"Oct-25",Raw_Stripe!$N$6:$N$49,"WhatsApp") -> 0 | M7: =SUMIFS(Raw_Stripe!$H$6:$H$49,Raw_Stripe!$M$6:$M$49,"Nov-25",Raw_Stripe!$N$6:$N$49,"WhatsApp") -> 3135.3 | N7: =SUMIFS(Raw_Stripe!$H$6:$H$49,Raw_Stripe!$M$6:$M$49,"Dec-25",Raw_Stripe!$N$6:$N$49,"WhatsApp") -> 0 | O7: =SUM(C7:N7) -> 31562.51 | P7: =IFERROR(O7/$O$11,0) -> 0.14418968
B8: Subscription Revenue | C8: =SUMIFS(Raw_Stripe!$H$6:$H$49,Raw_Stripe!$M$6:$M$49,"Jan-25",Raw_Stripe!$N$6:$N$49,"Subscription") -> 13782.45 | D8: =SUMIFS(Raw_Stripe!$H$6:$H$49,Raw_Stripe!$M$6:$M$49,"Feb-25",Raw_Stripe!$N$6:$N$49,"Subscription") -> 408.45 | E8: =SUMIFS(Raw_Stripe!$H$6:$H$49,Raw_Stripe!$M$6:$M$49,"Mar-25",Raw_Stripe!$N$6:$N$49,"Subscription") -> 408.45 | F8: =SUMIFS(Raw_Stripe!$H$6:$H$49,Raw_Stripe!$M$6:$M$49,"Apr-25",Raw_Stripe!$N$6:$N$49,"Subscription") -> 2608.45 | G8: =SUMIFS(Raw_Stripe!$H$6:$H$49,Raw_Stripe!$M$6:$M$49,"May-25",Raw_Stripe!$N$6:$N$49,"Subscription") -> 1339.2 | H8: =SUMIFS(Raw_Stripe!$H$6:$H$49,Raw_Stripe!$M$6:$M$49,"Jun-25",Raw_Stripe!$N$6:$N$49,"Subscription") -> 24000 | I8: =SUMIFS(Raw_Stripe!$H$6:$H$49,Raw_Stripe!$M$6:$M$49,"Jul-25",Raw_Stripe!$N$6:$N$49,"Subscription") -> 0 | J8: =SUMIFS(Raw_Stripe!$H$6:$H$49,Raw_Stripe!$M$6:$M$49,"Aug-25",Raw_Stripe!$N$6:$N$49,"Subscription") -> 0 | K8: =SUMIFS(Raw_Stripe!$H$6:$H$49,Raw_Stripe!$M$6:$M$49,"Sep-25",Raw_Stripe!$N$6:$N$49,"Subscription") -> 0 | L8: =SUMIFS(Raw_Stripe!$H$6:$H$49,Raw_Stripe!$M$6:$M$49,"Oct-25",Raw_Stripe!$N$6:$N$49,"Subscription") -> 24000 | M8: =SUMIFS(Raw_Stripe!$H$6:$H$49,Raw_Stripe!$M$6:$M$49,"Nov-25",Raw_Stripe!$N$6:$N$49,"Subscription") -> 1343.7 | N8: =SUMIFS(Raw_Stripe!$H$6:$H$49,Raw_Stripe!$M$6:$M$49,"Dec-25",Raw_Stripe!$N$6:$N$49,"Subscription") -> 0 | O8: =SUM(C8:N8) -> 67890.7 | P8: =IFERROR(O8/$O$11,0) -> 0.31015081
B9: Development Revenue | C9: =SUMIFS(Raw_Stripe!$H$6:$H$49,Raw_Stripe!$M$6:$M$49,"Jan-25",Raw_Stripe!$N$6:$N$49,"Development") -> 6800 | D9: =SUMIFS(Raw_Stripe!$H$6:$H$49,Raw_Stripe!$M$6:$M$49,"Feb-25",Raw_Stripe!$N$6:$N$49,"Development") -> 12000 | E9: =SUMIFS(Raw_Stripe!$H$6:$H$49,Raw_Stripe!$M$6:$M$49,"Mar-25",Raw_Stripe!$N$6:$N$49,"Development") -> 18086.85 | F9: =SUMIFS(Raw_Stripe!$H$6:$H$49,Raw_Stripe!$M$6:$M$49,"Apr-25",Raw_Stripe!$N$6:$N$49,"Development") -> 0 | G9: =SUMIFS(Raw_Stripe!$H$6:$H$49,Raw_Stripe!$M$6:$M$49,"May-25",Raw_Stripe!$N$6:$N$49,"Development") -> 8500 | H9: =SUMIFS(Raw_Stripe!$H$6:$H$49,Raw_Stripe!$M$6:$M$49,"Jun-25",Raw_Stripe!$N$6:$N$49,"Development") -> 0 | I9: =SUMIFS(Raw_Stripe!$H$6:$H$49,Raw_Stripe!$M$6:$M$49,"Jul-25",Raw_Stripe!$N$6:$N$49,"Development") -> 10050.75 | J9: =SUMIFS(Raw_Stripe!$H$6:$H$49,Raw_Stripe!$M$6:$M$49,"Aug-25",Raw_Stripe!$N$6:$N$49,"Development") -> 0 | K9: =SUMIFS(Raw_Stripe!$H$6:$H$49,Raw_Stripe!$M$6:$M$49,"Sep-25",Raw_Stripe!$N$6:$N$49,"Development") -> 11200 | L9: =SUMIFS(Raw_Stripe!$H$6:$H$49,Raw_Stripe!$M$6:$M$49,"Oct-25",Raw_Stripe!$N$6:$N$49,"Development") -> 2314.55 | M9: =SUMIFS(Raw_Stripe!$H$6:$H$49,Raw_Stripe!$M$6:$M$49,"Nov-25",Raw_Stripe!$N$6:$N$49,"Development") -> 0 | N9: =SUMIFS(Raw_Stripe!$H$6:$H$49,Raw_Stripe!$M$6:$M$49,"Dec-25",Raw_Stripe!$N$6:$N$49,"Development") -> 9500 | O9: =SUM(C9:N9) -> 78452.15 | P9: =IFERROR(O9/$O$11,0) -> 0.35839957
B10: Other Services Revenue | C10: =SUMIFS(Raw_Stripe!$H$6:$H$49,Raw_Stripe!$M$6:$M$49,"Jan-25",Raw_Stripe!$N$6:$N$49,"Other Services") -> 953.05 | D10: =SUMIFS(Raw_Stripe!$H$6:$H$49,Raw_Stripe!$M$6:$M$49,"Feb-25",Raw_Stripe!$N$6:$N$49,"Other Services") -> 6800 | E10: =SUMIFS(Raw_Stripe!$H$6:$H$49,Raw_Stripe!$M$6:$M$49,"Mar-25",Raw_Stripe!$N$6:$N$49,"Other Services") -> 3343.5 | F10: =SUMIFS(Raw_Stripe!$H$6:$H$49,Raw_Stripe!$M$6:$M$49,"Apr-25",Raw_Stripe!$N$6:$N$49,"Other Services") -> 9200 | G10: =SUMIFS(Raw_Stripe!$H$6:$H$49,Raw_Stripe!$M$6:$M$49,"May-25",Raw_Stripe!$N$6:$N$49,"Other Services") -> 1415.96 | H10: =SUMIFS(Raw_Stripe!$H$6:$H$49,Raw_Stripe!$M$6:$M$49,"Jun-25",Raw_Stripe!$N$6:$N$49,"Other Services") -> 2827.2 | I10: =SUMIFS(Raw_Stripe!$H$6:$H$49,Raw_Stripe!$M$6:$M$49,"Jul-25",Raw_Stripe!$N$6:$N$49,"Other Services") -> 1307.04 | J10: =SUMIFS(Raw_Stripe!$H$6:$H$49,Raw_Stripe!$M$6:$M$49,"Aug-25",Raw_Stripe!$N$6:$N$49,"Other Services") -> 7500 | K10: =SUMIFS(Raw_Stripe!$H$6:$H$49,Raw_Stripe!$M$6:$M$49,"Sep-25",Raw_Stripe!$N$6:$N$49,"Other Services") -> 0 | L10: =SUMIFS(Raw_Stripe!$H$6:$H$49,Raw_Stripe!$M$6:$M$49,"Oct-25",Raw_Stripe!$N$6:$N$49,"Other Services") -> 0 | M10: =SUMIFS(Raw_Stripe!$H$6:$H$49,Raw_Stripe!$M$6:$M$49,"Nov-25",Raw_Stripe!$N$6:$N$49,"Other Services") -> 6500 | N10: =SUMIFS(Raw_Stripe!$H$6:$H$49,Raw_Stripe!$M$6:$M$49,"Dec-25",Raw_Stripe!$N$6:$N$49,"Other Services") -> 1143.66 | O10: =SUM(C10:N10) -> 40990.41 | P10: =IFERROR(O10/$O$11,0) -> 0.18725995
B11: TOTAL REVENUE | C11: =SUM(C7:C10) -> 25737.51 | D11: =SUM(D7:D10) -> 23034.3 | E11: =SUM(E7:E10) -> 26464.44 | F11: =SUM(F7:F10) -> 13088.26 | G11: =SUM(G7:G10) -> 12589.43 | H11: =SUM(H7:H10) -> 33888.23 | I11: =SUM(I7:I10) -> 12773.75 | J11: =SUM(J7:J10) -> 10331 | ... N11: =SUM(N7:N10) -> 10643.66 | O11: =SUM(C11:N11) -> 218895.77 | P11: 1
B13: COST OF REVENUE
B14: Meta Cost (with add-back) | C14: =SUMIFS(Raw_Meta!$L$6:$L$28,Raw_Meta!$N$6:$N$28,"Jan-25") -> 19700 | D14: =SUMIFS(Raw_Meta!$L$6:$L$28,Raw_Meta!$N$6:$N$28,"Feb-25") -> 16300 | E14: =SUMIFS(Raw_Meta!$L$6:$L$28,Raw_Meta!$N$6:$N$28,"Mar-25") -> 30300 | F14: =SUMIFS(Raw_Meta!$L$6:$L$28,Raw_Meta!$N$6:$N$28,"Apr-25") -> 9300 | G14: =SUMIFS(Raw_Meta!$L$6:$L$28,Raw_Meta!$N$6:$N$28,"May-25") -> 17300 | H14: =SUMIFS(Raw_Meta!$L$6:$L$28,Raw_Meta!$N$6:$N$28,"Jun-25") -> 12400 | I14: =SUMIFS(Raw_Meta!$L$6:$L$28,Raw_Meta!$N$6:$N$28,"Jul-25") -> 14000 | J14: =SUMIFS(Raw_Meta!$L$6:$L$28,Raw_Meta!$N$6:$N$28,"Aug-25") -> 4500 | K14: =SUMIFS(Raw_Meta!$L$6:$L$28,Raw_Meta!$N$6:$N$28,"Sep-25") -> 9800 | L14: =SUMIFS(Raw_Meta!$L$6:$L$28,Raw_Meta!$N$6:$N$28,"Oct-25") -> 0 | M14: =SUMIFS(Raw_Meta!$L$6:$L$28,Raw_Meta!$N$6:$N$28,"Nov-25") -> 0 | N14: =SUMIFS(Raw_Meta!$L$6:$L$28,Raw_Meta!$N$6:$N$28,"Dec-25") -> 0 | O14: =SUM(C14:N14) -> 133600
B15: Total COGS | C15: =C14 -> 19700 | D15: =D14 -> 16300 | E15: =E14 -> 30300 | F15: =F14 -> 9300 | G15: =G14 -> 17300 | H15: =H14 -> 12400 | I15: =I14 -> 14000 | J15: =J14 -> 4500 | ... N15: =N14 -> 0 | O15: =SUM(C15:N15) -> 133600 | P15: =IFERROR(O15/$O$11,0) -> 0.61033614
B16: GROSS PROFIT | C16: =C11-C15 -> 6037.51 | D16: =D11-D15 -> 6734.3 | E16: =E11-E15 -> -3835.56 | F16: =F11-F15 -> 3788.26 | G16: =G11-G15 -> -4710.57 | H16: =H11-H15 -> 21488.23 | I16: =I11-I15 -> -1226.25 | J16: =J11-J15 -> 5831 | ... N16: =N11-N15 -> 10643.66 | O16: =SUM(C16:N16) -> 85295.77 | P16: =IFERROR(O16/$O$11,0) -> 0.38966386
B18: OPERATING EXPENSES
B19: Stripe Processing Fees | C19: =SUMIFS(Raw_Stripe!$I$6:$I$49,Raw_Stripe!$M$6:$M$49,"Jan-25") -> 1196.9 | D19: =SUMIFS(Raw_Stripe!$I$6:$I$49,Raw_Stripe!$M$6:$M$49,"Feb-25") -> 837 | E19: =SUMIFS(Raw_Stripe!$I$6:$I$49,Raw_Stripe!$M$6:$M$49,"Mar-25") -> 1230.3 | F19: =SUMIFS(Raw_Stripe!$I$6:$I$49,Raw_Stripe!$M$6:$M$49,"Apr-25") -> 523.5 | G19: =SUMIFS(Raw_Stripe!$I$6:$I$49,Raw_Stripe!$M$6:$M$49,"May-25") -> 614.2 | H19: =SUMIFS(Raw_Stripe!$I$6:$I$49,Raw_Stripe!$M$6:$M$49,"Jun-25") -> 1156.7 | I19: =SUMIFS(Raw_Stripe!$I$6:$I$49,Raw_Stripe!$M$6:$M$49,"Jul-25") -> 717.1 | J19: =SUMIFS(Raw_Stripe!$I$6:$I$49,Raw_Stripe!$M$6:$M$49,"Aug-25") -> 332.6 | K19: =SUMIFS(Raw_Stripe!$I$6:$I$49,Raw_Stripe!$M$6:$M$49,"Sep-25") -> 325.2 | L19: =SUMIFS(Raw_Stripe!$I$6:$I$49,Raw_Stripe!$M$6:$M$49,"Oct-25") -> 0 | M19: =SUMIFS(Raw_Stripe!$I$6:$I$49,Raw_Stripe!$M$6:$M$49,"Nov-25") -> 0 | N19: =SUMIFS(Raw_Stripe!$I$6:$I$49,Raw_Stripe!$M$6:$M$49,"Dec-25") -> 0 | O19: =SUM(C19:N19) -> 6933.5 | P19: =IFERROR(O19/$O$11,0) -> 0.031674893
B20: Bank Charges | C20: =SUMIFS(Raw_Bank!$H$6:$H$26,Raw_Bank!$J$6:$J$26,"Jan-25",Raw_Bank!$E$6:$E$26,">0") -> -53.235 | D20: =SUMIFS(Raw_Bank!$H$6:$H$26,Raw_Bank!$J$6:$J$26,"Feb-25",Raw_Bank!$E$6:$E$26,">0") -> -27.23 | E20: =SUMIFS(Raw_Bank!$H$6:$H$26,Raw_Bank!$J$6:$J$26,"Mar-25",Raw_Bank!$E$6:$E$26,">0") -> -27.23 | F20: =SUMIFS(Raw_Bank!$H$6:$H$26,Raw_Bank!$J$6:$J$26,"Apr-25",Raw_Bank!$E$6:$E$26,">0") -> -27.23 | G20: =SUMIFS(Raw_Bank!$H$6:$H$26,Raw_Bank!$J$6:$J$26,"May-25",Raw_Bank!$E$6:$E$26,">0") -> 0 | H20: =SUMIFS(Raw_Bank!$H$6:$H$26,Raw_Bank!$J$6:$J$26,"Jun-25",Raw_Bank!$E$6:$E$26,">0") -> -27.23 | I20: =SUMIFS(Raw_Bank!$H$6:$H$26,Raw_Bank!$J$6:$J$26,"Jul-25",Raw_Bank!$E$6:$E$26,">0") -> 0 | J20: =SUMIFS(Raw_Bank!$H$6:$H$26,Raw_Bank!$J$6:$J$26,"Aug-25",Raw_Bank!$E$6:$E$26,">0") -> 0 | K20: =SUMIFS(Raw_Bank!$H$6:$H$26,Raw_Bank!$J$6:$J$26,"Sep-25",Raw_Bank!$E$6:$E$26,">0") -> -27.23 | L20: =SUMIFS(Raw_Bank!$H$6:$H$26,Raw_Bank!$J$6:$J$26,"Oct-25",Raw_Bank!$E$6:$E$26,">0") -> 0 | M20: =SUMIFS(Raw_Bank!$H$6:$H$26,Raw_Bank!$J$6:$J$26,"Nov-25",Raw_Bank!$E$6:$E$26,">0") -> 0 | N20: =SUMIFS(Raw_Bank!$H$6:$H$26,Raw_Bank!$J$6:$J$26,"Dec-25",Raw_Bank!$E$6:$E$26,">0") -> 0 | O20: =SUM(C20:N20) -> -189.385 | P20: =IFERROR(O20/$O$11,0) -> -0.00086518346
B21: Salaries & Wages | C21: =SUMIFS(Raw_Xero!$I$6:$I$30,Raw_Xero!$K$6:$K$30,"Jan-25",Raw_Xero!$C$6:$C$30,"5000") -> 28599.5 | D21: =SUMIFS(Raw_Xero!$I$6:$I$30,Raw_Xero!$K$6:$K$30,"Feb-25",Raw_Xero!$C$6:$C$30,"5000") -> 29887.1 | E21: =SUMIFS(Raw_Xero!$I$6:$I$30,Raw_Xero!$K$6:$K$30,"Mar-25",Raw_Xero!$C$6:$C$30,"5000") -> 31447 | F21: =SUMIFS(Raw_Xero!$I$6:$I$30,Raw_Xero!$K$6:$K$30,"Apr-25",Raw_Xero!$C$6:$C$30,"5000") -> 32747.1 | G21: =SUMIFS(Raw_Xero!$I$6:$I$30,Raw_Xero!$K$6:$K$30,"May-25",Raw_Xero!$C$6:$C$30,"5000") -> 14976.5 | H21: =SUMIFS(Raw_Xero!$I$6:$I$30,Raw_Xero!$K$6:$K$30,"Jun-25",Raw_Xero!$C$6:$C$30,"5000") -> 15793.4 | I21: =SUMIFS(Raw_Xero!$I$6:$I$30,Raw_Xero!$K$6:$K$30,"Jul-25",Raw_Xero!$C$6:$C$30,"5000") -> 16882.6 | J21: =SUMIFS(Raw_Xero!$I$6:$I$30,Raw_Xero!$K$6:$K$30,"Aug-25",Raw_Xero!$C$6:$C$30,"5000") -> 0 | K21: =SUMIFS(Raw_Xero!$I$6:$I$30,Raw_Xero!$K$6:$K$30,"Sep-25",Raw_Xero!$C$6:$C$30,"5000") -> 0 | L21: =SUMIFS(Raw_Xero!$I$6:$I$30,Raw_Xero!$K$6:$K$30,"Oct-25",Raw_Xero!$C$6:$C$30,"5000") -> 0 | M21: =SUMIFS(Raw_Xero!$I$6:$I$30,Raw_Xero!$K$6:$K$30,"Nov-25",Raw_Xero!$C$6:$C$30,"5000") -> 0 | N21: =SUMIFS(Raw_Xero!$I$6:$I$30,Raw_Xero!$K$6:$K$30,"Dec-25",Raw_Xero!$C$6:$C$30,"5000") -> 0 | O21: =SUM(C21:N21) -> 170333.2 | P21: =IFERROR(O21/$O$11,0) -> 0.77814752
B22: Office Rent | C22: =SUMIFS(Raw_Xero!$I$6:$I$30,Raw_Xero!$K$6:$K$30,"Jan-25",Raw_Xero!$C$6:$C$30,"4000") -> 9211.6 | D22: =SUMIFS(Raw_Xero!$I$6:$I$30,Raw_Xero!$K$6:$K$30,"Feb-25",Raw_Xero!$C$6:$C$30,"4000") -> 9211.6 | E22: =SUMIFS(Raw_Xero!$I$6:$I$30,Raw_Xero!$K$6:$K$30,"Mar-25",Raw_Xero!$C$6:$C$30,"4000") -> 9211.6 | F22: =SUMIFS(Raw_Xero!$I$6:$I$30,Raw_Xero!$K$6:$K$30,"Apr-25",Raw_Xero!$C$6:$C$30,"4000") -> 9215.6 | G22: =SUMIFS(Raw_Xero!$I$6:$I$30,Raw_Xero!$K$6:$K$30,"May-25",Raw_Xero!$C$6:$C$30,"4000") -> 3267.6 | H22: =SUMIFS(Raw_Xero!$I$6:$I$30,Raw_Xero!$K$6:$K$30,"Jun-25",Raw_Xero!$C$6:$C$30,"4000") -> 3267.6 | I22: =SUMIFS(Raw_Xero!$I$6:$I$30,Raw_Xero!$K$6:$K$30,"Jul-25",Raw_Xero!$C$6:$C$30,"4000") -> 3403.75 | J22: =SUMIFS(Raw_Xero!$I$6:$I$30,Raw_Xero!$K$6:$K$30,"Aug-25",Raw_Xero!$C$6:$C$30,"4000") -> 0 | K22: =SUMIFS(Raw_Xero!$I$6:$I$30,Raw_Xero!$K$6:$K$30,"Sep-25",Raw_Xero!$C$6:$C$30,"4000") -> 0 | L22: =SUMIFS(Raw_Xero!$I$6:$I$30,Raw_Xero!$K$6:$K$30,"Oct-25",Raw_Xero!$C$6:$C$30,"4000") -> 0 | M22: =SUMIFS(Raw_Xero!$I$6:$I$30,Raw_Xero!$K$6:$K$30,"Nov-25",Raw_Xero!$C$6:$C$30,"4000") -> 0 | N22: =SUMIFS(Raw_Xero!$I$6:$I$30,Raw_Xero!$K$6:$K$30,"Dec-25",Raw_Xero!$C$6:$C$30,"4000") -> 0 | O22: =SUM(C22:N22) -> 46789.35 | P22: =IFERROR(O22/$O$11,0) -> 0.21375173
B23: Utilities | C23: =SUMIFS(Raw_Xero!$I$6:$I$30,Raw_Xero!$K$6:$K$30,"Jan-25",Raw_Xero!$C$6:$C$30,"6100") -> 680.75 | D23: =SUMIFS(Raw_Xero!$I$6:$I$30,Raw_Xero!$K$6:$K$30,"Feb-25",Raw_Xero!$C$6:$C$30,"6100") -> 707.98 | E23: =SUMIFS(Raw_Xero!$I$6:$I$30,Raw_Xero!$K$6:$K$30,"Mar-25",Raw_Xero!$C$6:$C$30,"6100") -> 653.52 | F23: =SUMIFS(Raw_Xero!$I$6:$I$30,Raw_Xero!$K$6:$K$30,"Apr-25",Raw_Xero!$C$6:$C$30,"6100") -> 0 | G23: =SUMIFS(Raw_Xero!$I$6:$I$30,Raw_Xero!$K$6:$K$30,"May-25",Raw_Xero!$C$6:$C$30,"6100") -> 0 | H23: =SUMIFS(Raw_Xero!$I$6:$I$30,Raw_Xero!$K$6:$K$30,"Jun-25",Raw_Xero!$C$6:$C$30,"6100") -> 0 | I23: =SUMIFS(Raw_Xero!$I$6:$I$30,Raw_Xero!$K$6:$K$30,"Jul-25",Raw_Xero!$C$6:$C$30,"6100") -> 0 | J23: =SUMIFS(Raw_Xero!$I$6:$I$30,Raw_Xero!$K$6:$K$30,"Aug-25",Raw_Xero!$C$6:$C$30,"6100") -> 0 | K23: =SUMIFS(Raw_Xero!$I$6:$I$30,Raw_Xero!$K$6:$K$30,"Sep-25",Raw_Xero!$C$6:$C$30,"6100") -> 0 | L23: =SUMIFS(Raw_Xero!$I$6:$I$30,Raw_Xero!$K$6:$K$30,"Oct-25",Raw_Xero!$C$6:$C$30,"6100") -> 0 | M23: =SUMIFS(Raw_Xero!$I$6:$I$30,Raw_Xero!$K$6:$K$30,"Nov-25",Raw_Xero!$C$6:$C$30,"6100") -> 0 | N23: =SUMIFS(Raw_Xero!$I$6:$I$30,Raw_Xero!$K$6:$K$30,"Dec-25",Raw_Xero!$C$6:$C$30,"6100") -> 0 | O23: =SUM(C23:N23) -> 2042.25 | P23: =IFERROR(O23/$O$11,0) -> 0.0093297828
B24: Total Operating Expenses | C24: =SUM(C19:C23) -> 39635.515 | D24: =SUM(D19:D23) -> 40616.45 | E24: =SUM(E19:E23) -> 42515.19 | F24: =SUM(F19:F23) -> 42458.97 | G24: =SUM(G19:G23) -> 18858.3 | H24: =SUM(H19:H23) -> 20190.47 | I24: =SUM(I19:I23) -> 21003.45 | J24: =SUM(J19:J23) -> 332.6 | ... N24: =SUM(N19:N23) -> 0 | O24: =SUM(C24:N24) -> 225908.92 | P24: =IFERROR(O24/$O$11,0) -> 1.0320387
B26: NET PROFIT | C26: =C16-C24 -> -33598.005 | D26: =D16-D24 -> -33882.15 | E26: =E16-E24 -> -46350.75 | F26: =F16-F24 -> -38670.71 | G26: =G16-G24 -> -23568.87 | H26: =H16-H24 -> 1297.76 | I26: =I16-I24 -> -22229.7 | J26: =J16-J24 -> 5498.4 | ... N26: =N16-N24 -> 10643.66 | O26: =SUM(C26:N26) -> -140613.14 | P26: =IFERROR(O26/$O$11,0) -> -0.64237488
B27: Net Profit Margin % | C27: =IFERROR(C26/C11,0) -> -1.3054101 | D27: =IFERROR(D26/D11,0) -> -1.4709433 | E27: =IFERROR(E26/E11,0) -> -1.7514351 | F27: =IFERROR(F26/F11,0) -> -2.9546105 | G27: =IFERROR(G26/G11,0) -> -1.8721157 | H27: =IFERROR(H26/H11,0) -> 0.038295302 | I27: =IFERROR(I26/I11,0) -> -1.7402642 | J27: =IFERROR(J26/J11,0) -> 0.53222341 | ... O27: =IFERROR(O26/O11,0) -> -0.64237488
B30: P&L TREND (Revenue, Total OpEx, Net Profit)

Sheet Formula_Audit
B2: Formula Audit Trail
B3: Every key live formula in the workbook — transparency & verification
B5: KEY FORMULAS BY SHEET
B6: Sheet | C6: Cell(s) | D6: Formula | E6: Description
B7: Raw_Stripe | C7: H6:H49 | D7: '=F*INDEX(Settings_FX!$C$16:$I$27, MATCH(TEXT(C,"mmm-yy"),Settings_FX!$B$16:$B$27,0), MATCH(G,Settings_FX!$C$15:$I$15,0)) | E7: Converts native-currency amount to USD using the monthly FX rate table.
B8: Raw_Stripe | C8: J6:J49 | D8: '=F-I (Amount − Stripe Fee) | E8: Net amount after Stripe processing fee deducted.
B9: Raw_Stripe | C9: L6:L49 | D9: '=J-K (Net Amount − Amount Received) | E9: Outstanding A/R — drives the Receivables_Aging sheet.
B10: Raw_Stripe | C10: M6:M49 | D10: '=TEXT(C,"mmm-yy") | E10: Derives the month label (Jan-25, Feb-25…) used by SUMIFS in dashboards.
B11: Raw_Meta | C11: K6:K28 | D11: '=I+H (Net Paid + Discount Given) | E11: ★ META ADD-BACK LOGIC — reverses Meta's discount to show the full gross charge per customer.
B12: Raw_Meta | C12: L6:L28 | D12: '=K*INDEX(...) MATCH(currency) | E12: Converts the add-back amount to USD using monthly FX rates.
B13: Settings_FX | C13: B16:I27 | D13: (editable FX rate table) | E13: User-maintained table: 1 unit of currency = X USD. Update monthly.
B14: Settings_FX | C14: B32:H46 | D14: (customer master table) | E14: Maps customer name → entity (UAE/SG), default currency, primary category.
B15: Revenue_Dashboard | C15: C7:N9 | D15: '=SUMIFS(Raw_Stripe!$H:$H, Raw_Stripe!$M:$M, "Jan-25", Raw_Stripe!$N:$N, "WhatsApp") | E15: Sums USD-equivalent Stripe revenue by month and category (WhatsApp/Subscription/Development).
B16: Revenue_Dashboard | C16: O7:O9 | D16: '=SUM(C:N) for the row | E16: YTD total per category.
B17: Revenue_Dashboard | C17: C10:N10 | D17: '=SUM(C7:C9) | E17: Total monthly revenue across all three categories.
... B51: Executive_Summary | C51: H9 | D51: '=SUM(Raw_Meta!L:L) | E51: YTD Meta Cost with add-back.
B54: ★ = Meta discount add-back logic (the unique feature of this dashboard). All other formulas follow standard SUMIFS / INDEX-MATCH patterns. Edit any blue input cell — every dependent formula refreshes automatically.

Sheet Raw_Stripe
B2: Raw Stripe Transactions
B3: Paste Stripe export rows below — formulas in grey columns auto-calculate
B5: Txn ID | C5: Date | D5: Customer | E5: Description | F5: Amount | G5: Currency | H5: Amount USD | I5: Stripe Fee | J5: Net Amount | K5: Amount Received | L5: Outstanding | M5: Month | N5: Category | O5: Entity | P5: Status
B6: ch_001 | C6: 45662 | D6: Alphabet Logistics LLC | E6: WABA msgs Jan | F6: 4200 | G6: AED | H6: =F6*IFERROR(INDEX(Settings_FX!$C$16:$I$27,MATCH(TEXT(C6,"mmm-yy"),Settings_FX!$B$16:$B$27,0),MATCH(G6,Settings_FX!$C$15:$I$15,0)),1) -> 1143.66 | I6: 130.2 | J6: =F6-I6 -> 4069.8 | K6: 4069.8 | L6: =J6-K6 -> 0 | M6: =TEXT(C6,"mmm-yy") -> Jan-25 | N6: WhatsApp | O6: UAE | P6: Paid
B7: ch_002 | C7: 45665 | D7: Emirates Retail Group | E7: Sub monthly Jan | F7: 1500 | G7: AED | H7: =F7*IFERROR(INDEX(Settings_FX!$C$16:$I$27,MATCH(TEXT(C7,"mmm-yy"),Settings_FX!$B$16:$B$27,0),MATCH(G7,Settings_FX!$C$15:$I$15,0)),1) -> 408.45 | I7: 46.5 | J7: =F7-I7 -> 1453.5 | K7: 1453.5 | L7: =J7-K7 -> 0 | M7: =TEXT(C7,"mmm-yy") -> Jan-25 | N7: Subscription | O7: UAE | P7: Paid
B8: ch_003 | C8: 45669 | D8: Gulf Tech Distribution | E8: Dev hourly 40h | F8: 6800 | G8: USD | H8: =F8*IFERROR(INDEX(Settings_FX!$C$16:$I$27,MATCH(TEXT(C8,"mmm-yy"),Settings_FX!$B$16:$B$27,0),MATCH(G8,Settings_FX!$C$15:$I$15,0)),1) -> 6800 | I8: 197.8 | J8: =F8-I8 -> 6602.2 | K8: 6602.2 | L8: =J8-K8 -> 0 | M8: =TEXT(C8,"mmm-yy") -> Jan-25 | N8: Development | O8: UAE | P8: Paid
B9: ch_004 | C9: 45675 | D9: Singapore FinTech Hub | E9: WABA msgs Jan | F9: 3200 | G9: SGD | H9: =F9*IFERROR(INDEX(Settings_FX!$C$16:$I$27,MATCH(TEXT(C9,"mmm-yy"),Settings_FX!$B$16:$B$27,0),MATCH(G9,Settings_FX!$C$15:$I$15,0)),1) -> 2377.6 | I9: 96.4 | J9: =F9-I9 -> 3103.6 | K9: 3103.6 | L9: =J9-K9 -> 0 | M9: =TEXT(C9,"mmm-yy") -> Jan-25 | N9: WhatsApp | O9: SG | P9: Paid
B10: ch_005 | C10: 45679 | D10: Marina Bay Holdings | E10: Sub annual | F10: 18000 | G10: SGD | H10: =F10*IFERROR(INDEX(Settings_FX!$C$16:$I$27,MATCH(TEXT(C10,"mmm-yy"),Settings_FX!$B$16:$B$27,0),MATCH(G10,Settings_FX!$C$15:$I$15,0)),1) -> 13374 | I10: 540 | J10: =F10-I10 -> 17460 | K10: 17460 | L10: =J10-K10 -> 0 | M10: =TEXT(C10,"mmm-yy") -> Jan-25 | N10: Subscription | O10: SG | P10: Paid
B11: ch_006 | C11: 45685 | D11: Alphabet Logistics LLC | E11: WABA topup | F11: 2500 | G11: AED | H11: =F11*IFERROR(INDEX(Settings_FX!$C$16:$I$27,MATCH(TEXT(C11,"mmm-yy"),Settings_FX!$B$16:$B$27,0),MATCH(G11,Settings_FX!$C$15:$I$15,0)),1) -> 680.75 | I11: 77.5 | J11: =F11-I11 -> 2422.5 | K11: 2422.5 | L11: =J11-K11 -> 0 | M11: =TEXT(C11,"mmm-yy") -> Jan-25 | N11: WhatsApp | O11: UAE | P11: Paid
B12: ch_007 | C12: 45692 | D12: Alphabet Logistics LLC | E12: WABA msgs Feb | F12: 4500 | G12: AED | H12: =F12*IFERROR(INDEX(Settings_FX!$C$16:$I$27,MATCH(TEXT(C12,"mmm-yy"),Settings_FX!$B$16:$B$27,0),MATCH(G12,Settings_FX!$C$15:$I$15,0)),1) -> 1225.35 | I12: 139.5 | J12: =F12-I12 -> 4360.5 | K12: 4360.5 | L12: =J12-K12 -> 0 | M12: =TEXT(C12,"mmm-yy") -> Feb-25 | N12: WhatsApp | O12: UAE | P12: Paid
B13: ch_008 | C13: 45697 | D13: Emirates Retail Group | E13: Sub monthly Feb | F13: 1500 | G13: AED | H13: =F13*IFERROR(INDEX(Settings_FX!$C$16:$I$27,MATCH(TEXT(C13,"mmm-yy"),Settings_FX!$B$16:$B$27,0),MATCH(G13,Settings_FX!$C$15:$I$15,0)),1) -> 408.45 | I13: 46.5 | J13: =F13-I13 -> 1453.5 | K13: 1453.5 | L13: =J13-K13 -> 0 | M13: =TEXT(C13,"mmm-yy") -> Feb-25 | N13: Subscription | O13: UAE | P13: Paid
B14: ch_009 | C14: 45702 | D14: Gulf Tech Distribution | E14: Dev fixed phase 2 | F14: 12000 | G14: USD | H14: =F14*IFERROR(INDEX(Settings_FX!$C$16:$I$27,MATCH(TEXT(C14,"mmm-yy"),Settings_FX!$B$16:$B$27,0),MATCH(G14,Settings_FX!$C$15:$I$15,0)),1) -> 12000 | I14: 348.3 | J14: =F14-I14 -> 11651.7 | K14: 11651.7 | L14: =J14-K14 -> 0 | M14: =TEXT(C14,"mmm-yy") -> Feb-25 | N14: Development | O14: UAE | P14: Paid
B15: ch_010 | C15: 45708 | D15: Singapore FinTech Hub | E15: WABA msgs Feb | F15: 3500 | G15: SGD | H15: =F15*IFERROR(INDEX(Settings_FX!$C$16:$I$27,MATCH(TEXT(C15,"mmm-yy"),Settings_FX!$B$16:$B$27,0),MATCH(G15,Settings_FX!$C$15:$I$15,0)),1) -> 2600.5 | I15: 105.5 | J15: =F15-I15 -> 3394.5 | K15: 3394.5 | L15: =J15-K15 -> 0 | M15: =TEXT(C15,"mmm-yy") -> Feb-25 | N15: WhatsApp | O15: SG | P15: Paid
B16: ch_011 | C16: 45719 | D16: Dubai Properties Co | E16: WABA msgs Mar | F16: 5800 | G16: AED | H16: =F16*IFERROR(INDEX(Settings_FX!$C$16:$I$27,MATCH(TEXT(C16,"mmm-yy"),Settings_FX!$B$16:$B$27,0),MATCH(G16,Settings_FX!$C$15:$I$15,0)),1) -> 1579.34 | I16: 180.1 | J16: =F16-I16 -> 5619.9 | K16: 5619.9 | L16: =J16-K16 -> 0 | M16: =TEXT(C16,"mmm-yy") -> Mar-25 | N16: WhatsApp | O16: UAE | P16: Paid
B17: ch_012 | C17: 45723 | D17: Abu Dhabi Trading | E17: Sub monthly Mar | F17: 1500 | G17: AED | H17: =F17*IFERROR(INDEX(Settings_FX!$C$16:$I$27,MATCH(TEXT(C17,"mmm-yy"),Settings_FX!$B$16:$B$27,0),MATCH(G17,Settings_FX!$C$15:$I$15,0)),1) -> 408.45 | I17: 46.5 | J17: =F17-I17 -> 1453.5 | K17: 1453.5 | L17: =J17-K17 -> 0 | M17: =TEXT(C17,"mmm-yy") -> Mar-25 | N17: Subscription | O17: UAE | P17: Paid
... B49: ch_044 | C49: 46001 | D49: Emirates Retail Group | E49: Onsite training Dec | F49: 4200 | G49: AED | H49: =F49*IFERROR(INDEX(Settings_FX!$C$16:$I$27,MATCH(TEXT(C49,"mmm-yy"),Settings_FX!$B$16:$B$27,0),MATCH(G49,Settings_FX!$C$15:$I$15,0)),1) -> 1143.66 | I49: 0 | J49: =F49-I49 -> 4200 | K49: 0 | L49: =J49-K49 -> 4200 | M49: =TEXT(C49,"mmm-yy") -> Dec-25 | N49: Other Services | O49: UAE | P49: Unsent
B50: TOTAL | F50: =SUM(F6:F49) -> 297700 | H50: =SUM(H6:H49) -> 218895.77 | I50: =SUM(I6:I49) -> 6933.5 | J50: =SUM(J6:J49) -> 290766.5 | K50: =SUM(K6:K49) -> 218119.1 | L50: =SUM(L6:L49) -> 72647.4
B52: Blue cells = paste from Stripe export · Italic grey cells = live formulas · Add new rows above the TOTAL row to keep formulas intact.

Sheet Raw_Xero
B2: Raw Xero Journal Entries
B3: Paste Xero trial balance / journal export — opex & bank charges flow to P&L
B5: Date | C5: Account Code | D5: Account Name | E5: Description | F5: Debit | G5: Credit | H5: Currency | I5: Amount USD | J5: Entity | K5: Month
B6: 45672 | C6: 4000 | D6: Office Rent | E6: Jan office rent | F6: 12000 | G6: 0 | H6: AED | I6: =(F6-G6)*IFERROR(INDEX(Settings_FX!$C$16:$I$27,MATCH(TEXT(B6,"mmm-yy"),Settings_FX!$B$16:$B$27,0),MATCH(H6,Settings_FX!$C$15:$I$15,0)),1) -> 3267.6 | J6: UAE | K6: =TEXT(B6,"mmm-yy") -> Jan-25
B7: 45677 | C7: 5000 | D7: Salaries | E7: Jan payroll | F7: 45000 | G7: 0 | H7: AED | I7: =(F7-G7)*IFERROR(INDEX(Settings_FX!$C$16:$I$27,MATCH(TEXT(B7,"mmm-yy"),Settings_FX!$B$16:$B$27,0),MATCH(H7,Settings_FX!$C$15:$I$15,0)),1) -> 12253.5 | J7: UAE | K7: =TEXT(B7,"mmm-yy") -> Jan-25
B8: 45685 | C8: 6100 | D8: Utilities | E8: Jan utilities | F8: 2500 | G8: 0 | H8: AED | I8: =(F8-G8)*IFERROR(INDEX(Settings_FX!$C$16:$I$27,MATCH(TEXT(B8,"mmm-yy"),Settings_FX!$B$16:$B$27,0),MATCH(H8,Settings_FX!$C$15:$I$15,0)),1) -> 680.75 | J8: UAE | K8: =TEXT(B8,"mmm-yy") -> Jan-25
B9: 45703 | C9: 4000 | D9: Office Rent | E9: Feb office rent | F9: 12000 | G9: 0 | H9: AED | I9: =(F9-G9)*IFERROR(INDEX(Settings_FX!$C$16:$I$27,MATCH(TEXT(B9,"mmm-yy"),Settings_FX!$B$16:$B$27,0),MATCH(H9,Settings_FX!$C$15:$I$15,0)),1) -> 3267.6 | J9: UAE | K9: =TEXT(B9,"mmm-yy") -> Feb-25
B10: 45708 | C10: 5000 | D10: Salaries | E10: Feb payroll | F10: 47000 | G10: 0 | H10: AED | I10: =(F10-G10)*IFERROR(INDEX(Settings_FX!$C$16:$I$27,MATCH(TEXT(B10,"mmm-yy"),Settings_FX!$B$16:$B$27,0),MATCH(H10,Settings_FX!$C$15:$I$15,0)),1) -> 12798.1 | J10: UAE | K10: =TEXT(B10,"mmm-yy") -> Feb-25
B11: 45716 | C11: 6100 | D11: Utilities | E11: Feb utilities | F11: 2600 | G11: 0 | H11: AED | I11: =(F11-G11)*IFERROR(INDEX(Settings_FX!$C$16:$I$27,MATCH(TEXT(B11,"mmm-yy"),Settings_FX!$B$16:$B$27,0),MATCH(H11,Settings_FX!$C$15:$I$15,0)),1) -> 707.98 | J11: UAE | K11: =TEXT(B11,"mmm-yy") -> Feb-25
B12: 45731 | C12: 4000 | D12: Office Rent | E12: Mar office rent | F12: 12000 | G12: 0 | H12: AED | I12: =(F12-G12)*IFERROR(INDEX(Settings_FX!$C$16:$I$27,MATCH(TEXT(B12,"mmm-yy"),Settings_FX!$B$16:$B$27,0),MATCH(H12,Settings_FX!$C$15:$I$15,0)),1) -> 3267.6 | J12: UAE | K12: =TEXT(B12,"mmm-yy") -> Mar-25
B13: 45736 | C13: 5000 | D13: Salaries | E13: Mar payroll | F13: 50000 | G13: 0 | H13: AED | I13: =(F13-G13)*IFERROR(INDEX(Settings_FX!$C$16:$I$27,MATCH(TEXT(B13,"mmm-yy"),Settings_FX!$B$16:$B$27,0),MATCH(H13,Settings_FX!$C$15:$I$15,0)),1) -> 13615 | J13: UAE | K13: =TEXT(B13,"mmm-yy") -> Mar-25
B14: 45744 | C14: 6100 | D14: Utilities | E14: Mar utilities | F14: 2400 | G14: 0 | H14: AED | I14: =(F14-G14)*IFERROR(INDEX(Settings_FX!$C$16:$I$27,MATCH(TEXT(B14,"mmm-yy"),Settings_FX!$B$16:$B$27,0),MATCH(H14,Settings_FX!$C$15:$I$15,0)),1) -> 653.52 | J14: UAE | K14: =TEXT(B14,"mmm-yy") -> Mar-25
B15: 45672 | C15: 4000 | D15: Office Rent | E15: Jan SG rent | F15: 8000 | G15: 0 | H15: SGD | I15: =(F15-G15)*IFERROR(INDEX(Settings_FX!$C$16:$I$27,MATCH(TEXT(B15,"mmm-yy"),Settings_FX!$B$16:$B$27,0),MATCH(H15,Settings_FX!$C$15:$I$15,0)),1) -> 5944 | J15: SG | K15: =TEXT(B15,"mmm-yy") -> Jan-25
B16: 45682 | C16: 5000 | D16: Salaries | E16: Jan SG payroll | F16: 22000 | G16: 0 | H16: SGD | I16: =(F16-G16)*IFERROR(INDEX(Settings_FX!$C$16:$I$27,MATCH(TEXT(B16,"mmm-yy"),Settings_FX!$B$16:$B$27,0),MATCH(H16,Settings_FX!$C$15:$I$15,0)),1) -> 16346 | J16: SG | K16: =TEXT(B16,"mmm-yy") -> Jan-25
B17: 45703 | C17: 4000 | D17: Office Rent | E17: Feb SG rent | F17: 8000 | G17: 0 | H17: SGD | I17: =(F17-G17)*IFERROR(INDEX(Settings_FX!$C$16:$I$27,MATCH(TEXT(B17,"mmm-yy"),Settings_FX!$B$16:$B$27,0),MATCH(H17,Settings_FX!$C$15:$I$15,0)),1) -> 5944 | J17: SG | K17: =TEXT(B17,"mmm-yy") -> Feb-25
... B30: 45858 | C30: 5000 | D30: Salaries | E30: Jul payroll | F30: 62000 | G30: 0 | H30: AED | I30: =(F30-G30)*IFERROR(INDEX(Settings_FX!$C$16:$I$27,MATCH(TEXT(B30,"mmm-yy"),Settings_FX!$B$16:$B$27,0),MATCH(H30,Settings_FX!$C$15:$I$15,0)),1) -> 16882.6 | J30: UAE | K30: =TEXT(B30,"mmm-yy") -> Jul-25
B31: TOTAL | F31: =SUM(F6:F30) -> 587000 | G31: =SUM(G6:G30) -> 0 | I31: =SUM(I6:I30) -> 219164.8

Sheet Raw_Xero_Invoices
B2: Raw Xero Customer Invoices
B3: Invoice-level paste-zone — feeds Customer_Receivables sheet (Void/Draft/Unsent/AwaitPay/Paid)
B4: Status values: Draft · Unsent · Awaiting Payment · Partial · Paid · Void
B5: Invoice # | C5: Date | D5: Customer | E5: Description | F5: Amount | G5: Currency | H5: Amount USD | I5: Amount Paid | J5: Outstanding | K5: Entity | L5: Month | M5: Status
B6: XINV-001 | C6: 45667 | D6: Alphabet Logistics LLC | E6: WABA setup Jan | F6: 12000 | G6: AED | H6: =F6*IFERROR(INDEX(Settings_FX!$C$16:$I$27,MATCH(TEXT(C6,"mmm-yy"),Settings_FX!$B$16:$B$27,0),MATCH(G6,Settings_FX!$C$15:$I$15,0)),1) -> 3267.6 | I6: 12000 | J6: =H6-(I6*IFERROR(INDEX(Settings_FX!$C$16:$I$27,MATCH(TEXT(C6,"mmm-yy"),Settings_FX!$B$16:$B$27,0),MATCH(G6,Settings_FX!$C$15:$I$15,0)),1)) -> 0 | K6: UAE | L6: =TEXT(C6,"mmm-yy") -> Jan-25 | M6: Paid
B7: XINV-002 | C7: 45672 | D7: Emirates Retail Group | E7: Sub Q1 invoice | F7: 4500 | G7: AED | H7: =F7*IFERROR(INDEX(Settings_FX!$C$16:$I$27,MATCH(TEXT(C7,"mmm-yy"),Settings_FX!$B$16:$B$27,0),MATCH(G7,Settings_FX!$C$15:$I$15,0)),1) -> 1225.35 | I7: 4500 | J7: =H7-(I7*IFERROR(INDEX(Settings_FX!$C$16:$I$27,MATCH(TEXT(C7,"mmm-yy"),Settings_FX!$B$16:$B$27,0),MATCH(G7,Settings_FX!$C$15:$I$15,0)),1)) -> 0 | K7: UAE | L7: =TEXT(C7,"mmm-yy") -> Jan-25 | M7: Paid
B8: XINV-003 | C8: 45696 | D8: Gulf Tech Distribution | E8: Dev phase 1 | F8: 18000 | G8: USD | H8: =F8*IFERROR(INDEX(Settings_FX!$C$16:$I$27,MATCH(TEXT(C8,"mmm-yy"),Settings_FX!$B$16:$B$27,0),MATCH(G8,Settings_FX!$C$15:$I$15,0)),1) -> 18000 | I8: 18000 | J8: =H8-(I8*IFERROR(INDEX(Settings_FX!$C$16:$I$27,MATCH(TEXT(C8,"mmm-yy"),Settings_FX!$B$16:$B$27,0),MATCH(G8,Settings_FX!$C$15:$I$15,0)),1)) -> 0 | K8: UAE | L8: =TEXT(C8,"mmm-yy") -> Feb-25 | M8: Paid
B9: XINV-004 | C9: 45708 | D9: Singapore FinTech Hub | E9: WABA platform Feb | F9: 6800 | G9: SGD | H9: =F9*IFERROR(INDEX(Settings_FX!$C$16:$I$27,MATCH(TEXT(C9,"mmm-yy"),Settings_FX!$B$16:$B$27,0),MATCH(G9,Settings_FX!$C$15:$I$15,0)),1) -> 5052.4 | I9: 6800 | J9: =H9-(I9*IFERROR(INDEX(Settings_FX!$C$16:$I$27,MATCH(TEXT(C9,"mmm-yy"),Settings_FX!$B$16:$B$27,0),MATCH(G9,Settings_FX!$C$15:$I$15,0)),1)) -> 0 | K9: SG | L9: =TEXT(C9,"mmm-yy") -> Feb-25 | M9: Paid
B10: XINV-005 | C10: 45721 | D10: Marina Bay Holdings | E10: Sub annual Mar | F10: 24000 | G10: SGD | H10: =F10*IFERROR(INDEX(Settings_FX!$C$16:$I$27,MATCH(TEXT(C10,"mmm-yy"),Settings_FX!$B$16:$B$27,0),MATCH(G10,Settings_FX!$C$15:$I$15,0)),1) -> 17832 | I10: 24000 | J10: =H10-(I10*IFERROR(INDEX(Settings_FX!$C$16:$I$27,MATCH(TEXT(C10,"mmm-yy"),Settings_FX!$B$16:$B$27,0),MATCH(G10,Settings_FX!$C$15:$I$15,0)),1)) -> 0 | K10: SG | L10: =TEXT(C10,"mmm-yy") -> Mar-25 | M10: Paid
B11: XINV-006 | C11: 45734 | D11: Alphabet Logistics LLC | E11: Add-on services | F11: 3800 | G11: AED | H11: =F11*IFERROR(INDEX(Settings_FX!$C$16:$I$27,MATCH(TEXT(C11,"mmm-yy"),Settings_FX!$B$16:$B$27,0),MATCH(G11,Settings_FX!$C$15:$I$15,0)),1) -> 1034.74 | I11: 2000 | J11: =H11-(I11*IFERROR(INDEX(Settings_FX!$C$16:$I$27,MATCH(TEXT(C11,"mmm-yy"),Settings_FX!$B$16:$B$27,0),MATCH(G11,Settings_FX!$C$15:$I$15,0)),1)) -> 490.14 | K11: UAE | L11: =TEXT(C11,"mmm-yy") -> Mar-25 | M11: Partial
B12: XINV-007 | C12: 45759 | D12: Abu Dhabi Trading | E12: Consulting Apr | F12: 7500 | G12: AED | H12: =F12*IFERROR(INDEX(Settings_FX!$C$16:$I$27,MATCH(TEXT(C12,"mmm-yy"),Settings_FX!$B$16:$B$27,0),MATCH(G12,Settings_FX!$C$15:$I$15,0)),1) -> 2042.25 | I12: 7500 | J12: =H12-(I12*IFERROR(INDEX(Settings_FX!$C$16:$I$27,MATCH(TEXT(C12,"mmm-yy"),Settings_FX!$B$16:$B$27,0),MATCH(G12,Settings_FX!$C$15:$I$15,0)),1)) -> 0 | K12: UAE | L12: =TEXT(C12,"mmm-yy") -> Apr-25 | M12: Paid
B13: XINV-008 | C13: 45769 | D13: Asia Pacific Solutions | E13: Dev retainer Apr | F13: 15500 | G13: USD | H13: =F13*IFERROR(INDEX(Settings_FX!$C$16:$I$27,MATCH(TEXT(C13,"mmm-yy"),Settings_FX!$B$16:$B$27,0),MATCH(G13,Settings_FX!$C$15:$I$15,0)),1) -> 15500 | I13: 15500 | J13: =H13-(I13*IFERROR(INDEX(Settings_FX!$C$16:$I$27,MATCH(TEXT(C13,"mmm-yy"),Settings_FX!$B$16:$B$27,0),MATCH(G13,Settings_FX!$C$15:$I$15,0)),1)) -> 0 | K13: SG | L13: =TEXT(C13,"mmm-yy") -> Apr-25 | M13: Paid
B14: XINV-009 | C14: 45785 | D14: Lion City Media | E14: WABA campaign May | F14: 4200 | G14: SGD | H14: =F14*IFERROR(INDEX(Settings_FX!$C$16:$I$27,MATCH(TEXT(C14,"mmm-yy"),Settings_FX!$B$16:$B$27,0),MATCH(G14,Settings_FX!$C$15:$I$15,0)),1) -> 3124.8 | I14: 4200 | J14: =H14-(I14*IFERROR(INDEX(Settings_FX!$C$16:$I$27,MATCH(TEXT(C14,"mmm-yy"),Settings_FX!$B$16:$B$27,0),MATCH(G14,Settings_FX!$C$15:$I$15,0)),1)) -> 0 | K14: SG | L14: =TEXT(C14,"mmm-yy") -> May-25 | M14: Paid
B15: XINV-010 | C15: 45797 | D15: Sentosa E-Commerce | E15: Sub Q2 invoice | F15: 6600 | G15: USD | H15: =F15*IFERROR(INDEX(Settings_FX!$C$16:$I$27,MATCH(TEXT(C15,"mmm-yy"),Settings_FX!$B$16:$B$27,0),MATCH(G15,Settings_FX!$C$15:$I$15,0)),1) -> 6600 | I15: 6600 | J15: =H15-(I15*IFERROR(INDEX(Settings_FX!$C$16:$I$27,MATCH(TEXT(C15,"mmm-yy"),Settings_FX!$B$16:$B$27,0),MATCH(G15,Settings_FX!$C$15:$I$15,0)),1)) -> 0 | K15: SG | L15: =TEXT(C15,"mmm-yy") -> May-25 | M15: Paid
B16: XINV-011 | C16: 45823 | D16: Dubai Properties Co | E16: Migration service | F16: 9500 | G16: AED | H16: =F16*IFERROR(INDEX(Settings_FX!$C$16:$I$27,MATCH(TEXT(C16,"mmm-yy"),Settings_FX!$B$16:$B$27,0),MATCH(G16,Settings_FX!$C$15:$I$15,0)),1) -> 2586.85 | I16: 5000 | J16: =H16-(I16*IFERROR(INDEX(Settings_FX!$C$16:$I$27,MATCH(TEXT(C16,"mmm-yy"),Settings_FX!$B$16:$B$27,0),MATCH(G16,Settings_FX!$C$15:$I$15,0)),1)) -> 1225.35 | K16: UAE | L16: =TEXT(C16,"mmm-yy") -> Jun-25 | M16: Partial
B17: XINV-012 | C17: 45836 | D17: Mena Apps FZ-LLC | E17: WABA msgs Jun | F17: 5800 | G17: USD | H17: =F17*IFERROR(INDEX(Settings_FX!$C$16:$I$27,MATCH(TEXT(C17,"mmm-yy"),Settings_FX!$B$16:$B$27,0),MATCH(G17,Settings_FX!$C$15:$I$15,0)),1) -> 5800 | I17: 5800 | J17: =H17-(I17*IFERROR(INDEX(Settings_FX!$C$16:$I$27,MATCH(TEXT(C17,"mmm-yy"),Settings_FX!$B$16:$B$27,0),MATCH(G17,Settings_FX!$C$15:$I$15,0)),1)) -> 0 | K17: UAE | L17: =TEXT(C17,"mmm-yy") -> Jun-25 | M17: Paid
... B26: XINV-021 | C26: 46006 | D26: Emirates Retail Group | E26: Year-end bonus svc | F26: 3500 | G26: AED | H26: =F26*IFERROR(INDEX(Settings_FX!$C$16:$I$27,MATCH(TEXT(C26,"mmm-yy"),Settings_FX!$B$16:$B$27,0),MATCH(G26,Settings_FX!$C$15:$I$15,0)),1) -> 953.05 | I26: 0 | J26: =H26-(I26*IFERROR(INDEX(Settings_FX!$C$16:$I$27,MATCH(TEXT(C26,"mmm-yy"),Settings_FX!$B$16:$B$27,0),MATCH(G26,Settings_FX!$C$15:$I$15,0)),1)) -> 953.05 | K26: UAE | L26: =TEXT(C26,"mmm-yy") -> Dec-25 | M26: Void
B27: TOTAL | F27: =SUM(F6:F26) -> 189200 | H27: =SUM(H6:H26) -> 134873.99 | I27: =SUM(I6:I26) -> 119900 | J27: =SUM(J6:J26) -> 48567.49

Sheet Raw_Bank
B2: Raw Bank Statements
B3: Paste bank statement rows — used for cash flow & bank charge reconciliation
B5: Date | C5: Description | D5: Account | E5: Debit | F5: Credit | G5: Currency | H5: Amount USD | I5: Entity | J5: Month
B6: 45660 | C6: Stripe payout ch_001-005 | D6: Mashreq UAE | E6: 0 | F6: 28145.5 | G6: AED | H6: =(F6-E6)*IFERROR(INDEX(Settings_FX!$C$16:$I$27,MATCH(TEXT(B6,"mmm-yy"),Settings_FX!$B$16:$B$27,0),MATCH(G6,Settings_FX!$C$15:$I$15,0)),1) -> 7664.0197 | I6: UAE | J6: =TEXT(B6,"mmm-yy") -> Jan-25
B7: 45662 | C7: Stripe payout ch_003 | D7: DBS SG | E7: 0 | F7: 6602.2 | G7: USD | H7: =(F7-E7)*IFERROR(INDEX(Settings_FX!$C$16:$I$27,MATCH(TEXT(B7,"mmm-yy"),Settings_FX!$B$16:$B$27,0),MATCH(G7,Settings_FX!$C$15:$I$15,0)),1) -> 6602.2 | I7: SG | J7: =TEXT(B7,"mmm-yy") -> Jan-25
B8: 45667 | C8: Bank maintenance fee | D8: Mashreq UAE | E8: 100 | F8: 0 | G8: AED | H8: =(F8-E8)*IFERROR(INDEX(Settings_FX!$C$16:$I$27,MATCH(TEXT(B8,"mmm-yy"),Settings_FX!$B$16:$B$27,0),MATCH(G8,Settings_FX!$C$15:$I$15,0)),1) -> -27.23 | I8: UAE | J8: =TEXT(B8,"mmm-yy") -> Jan-25
B9: 45669 | C9: Wire transfer fee | D9: DBS SG | E9: 35 | F9: 0 | G9: SGD | H9: =(F9-E9)*IFERROR(INDEX(Settings_FX!$C$16:$I$27,MATCH(TEXT(B9,"mmm-yy"),Settings_FX!$B$16:$B$27,0),MATCH(G9,Settings_FX!$C$15:$I$15,0)),1) -> -26.005 | I9: SG | J9: =TEXT(B9,"mmm-yy") -> Jan-25
B10: 45691 | C10: Stripe payout ch_007-010 | D10: Mashreq UAE | E10: 0 | F10: 13475 | G10: AED | H10: =(F10-E10)*IFERROR(INDEX(Settings_FX!$C$16:$I$27,MATCH(TEXT(B10,"mmm-yy"),Settings_FX!$B$16:$B$27,0),MATCH(G10,Settings_FX!$C$15:$I$15,0)),1) -> 3669.2425 | I10: UAE | J10: =TEXT(B10,"mmm-yy") -> Feb-25
B11: 45693 | C11: Stripe payout ch_009 | D11: DBS SG | E11: 0 | F11: 11651.7 | G11: USD | H11: =(F11-E11)*IFERROR(INDEX(Settings_FX!$C$16:$I$27,MATCH(TEXT(B11,"mmm-yy"),Settings_FX!$B$16:$B$27,0),MATCH(G11,Settings_FX!$C$15:$I$15,0)),1) -> 11651.7 | I11: SG | J11: =TEXT(B11,"mmm-yy") -> Feb-25
B12: 45698 | C12: Bank maintenance fee | D12: Mashreq UAE | E12: 100 | F12: 0 | G12: AED | H12: =(F12-E12)*IFERROR(INDEX(Settings_FX!$C$16:$I$27,MATCH(TEXT(B12,"mmm-yy"),Settings_FX!$B$16:$B$27,0),MATCH(G12,Settings_FX!$C$15:$I$15,0)),1) -> -27.23 | I12: UAE | J12: =TEXT(B12,"mmm-yy") -> Feb-25
B13: 45719 | C13: Stripe payout ch_011-015 | D13: Mashreq UAE | E13: 0 | F13: 16833.3 | G13: AED | H13: =(F13-E13)*IFERROR(INDEX(Settings_FX!$C$16:$I$27,MATCH(TEXT(B13,"mmm-yy"),Settings_FX!$B$16:$B$27,0),MATCH(G13,Settings_FX!$C$15:$I$15,0)),1) -> 4583.7076 | I13: UAE | J13: =TEXT(B13,"mmm-yy") -> Mar-25
B14: 45721 | C14: Stripe payout ch_014 | D14: DBS SG | E14: 0 | F14: 15049.9 | G14: USD | H14: =(F14-E14)*IFERROR(INDEX(Settings_FX!$C$16:$I$27,MATCH(TEXT(B14,"mmm-yy"),Settings_FX!$B$16:$B$27,0),MATCH(G14,Settings_FX!$C$15:$I$15,0)),1) -> 15049.9 | I14: SG | J14: =TEXT(B14,"mmm-yy") -> Mar-25
B15: 45728 | C15: Bank maintenance fee | D15: Mashreq UAE | E15: 100 | F15: 0 | G15: AED | H15: =(F15-E15)*IFERROR(INDEX(Settings_FX!$C$16:$I$27,MATCH(TEXT(B15,"mmm-yy"),Settings_FX!$B$16:$B$27,0),MATCH(G15,Settings_FX!$C$15:$I$15,0)),1) -> -27.23 | I15: UAE | J15: =TEXT(B15,"mmm-yy") -> Mar-25
B16: 45750 | C16: Stripe payout ch_016-018 | D16: Mashreq UAE | E16: 0 | F16: 8143.9 | G16: AED | H16: =(F16-E16)*IFERROR(INDEX(Settings_FX!$C$16:$I$27,MATCH(TEXT(B16,"mmm-yy"),Settings_FX!$B$16:$B$27,0),MATCH(G16,Settings_FX!$C$15:$I$15,0)),1) -> 2217.584 | I16: UAE | J16: =TEXT(B16,"mmm-yy") -> Apr-25
B17: 45757 | C17: Bank maintenance fee | D17: Mashreq UAE | E17: 100 | F17: 0 | G17: AED | H17: =(F17-E17)*IFERROR(INDEX(Settings_FX!$C$16:$I$27,MATCH(TEXT(B17,"mmm-yy"),Settings_FX!$B$16:$B$27,0),MATCH(G17,Settings_FX!$C$15:$I$15,0)),1) -> -27.23 | I17: UAE | J17: =TEXT(B17,"mmm-yy") -> Apr-25
... B26: 45910 | C26: Bank maintenance fee | D26: Mashreq UAE | E26: 100 | F26: 0 | G26: AED | H26: =(F26-E26)*IFERROR(INDEX(Settings_FX!$C$16:$I$27,MATCH(TEXT(B26,"mmm-yy"),Settings_FX!$B$16:$B$27,0),MATCH(G26,Settings_FX!$C$15:$I$15,0)),1) -> -27.23 | I26: UAE | J26: =TEXT(B26,"mmm-yy") -> Sep-25
B27: TOTAL | E27: =SUM(E6:E26) -> 635 | F27: =SUM(F6:F26) -> 199295.2 | H27: =SUM(H6:H26) -> 100157.85

Sheet Raw_Meta
B2: Raw Meta Invoices (with discount add-back)
B3: Net_Paid + Discount_Given = Amount With Add-Back · allocated per customer
B4: Add-Back Logic: Amount With AddBack = Net Paid + Discount Given → shows full gross charge per customer
B5: Invoice # | C5: Invoice Date | D5: Period | E5: Customer | F5: Campaign | G5: Gross Billed | H5: Discount Given | I5: Net Paid | J5: Currency | K5: Amount With AddBack | L5: Amount USD | M5: Entity | N5: Month
B6: INV-M-001 | C6: 45662 | D6: Jan-25 | E6: Alphabet Logistics LLC | F6: WABA Jan promo | G6: 5200 | H6: 450 | I6: 4750 | J6: USD | K6: =I6+H6 -> 5200 | L6: =K6*IFERROR(INDEX(Settings_FX!$C$16:$I$27,MATCH(TEXT(C6,"mmm-yy"),Settings_FX!$B$16:$B$27,0),MATCH(J6,Settings_FX!$C$15:$I$15,0)),1) -> 5200 | M6: UAE | N6: =TEXT(C6,"mmm-yy") -> Jan-25
B7: INV-M-002 | C7: 45665 | D7: Jan-25 | E7: Emirates Retail Group | F7: Retargeting Jan | G7: 3800 | H7: 300 | I7: 3500 | J7: USD | K7: =I7+H7 -> 3800 | L7: =K7*IFERROR(INDEX(Settings_FX!$C$16:$I$27,MATCH(TEXT(C7,"mmm-yy"),Settings_FX!$B$16:$B$27,0),MATCH(J7,Settings_FX!$C$15:$I$15,0)),1) -> 3800 | M7: UAE | N7: =TEXT(C7,"mmm-yy") -> Jan-25
B8: INV-M-003 | C8: 45669 | D8: Jan-25 | E8: Gulf Tech Distribution | F8: Lead Gen Jan | G8: 6500 | H8: 500 | I8: 6000 | J8: USD | K8: =I8+H8 -> 6500 | L8: =K8*IFERROR(INDEX(Settings_FX!$C$16:$I$27,MATCH(TEXT(C8,"mmm-yy"),Settings_FX!$B$16:$B$27,0),MATCH(J8,Settings_FX!$C$15:$I$15,0)),1) -> 6500 | M8: UAE | N8: =TEXT(C8,"mmm-yy") -> Jan-25
B9: INV-M-004 | C9: 45675 | D9: Jan-25 | E9: Singapore FinTech Hub | F9: WABA Jan SG | G9: 4200 | H9: 350 | I9: 3850 | J9: USD | K9: =I9+H9 -> 4200 | L9: =K9*IFERROR(INDEX(Settings_FX!$C$16:$I$27,MATCH(TEXT(C9,"mmm-yy"),Settings_FX!$B$16:$B$27,0),MATCH(J9,Settings_FX!$C$15:$I$15,0)),1) -> 4200 | M9: SG | N9: =TEXT(C9,"mmm-yy") -> Jan-25
B10: INV-M-005 | C10: 45693 | D10: Feb-25 | E10: Alphabet Logistics LLC | F10: WABA Feb promo | G10: 5500 | H10: 500 | I10: 5000 | J10: USD | K10: =I10+H10 -> 5500 | L10: =K10*IFERROR(INDEX(Settings_FX!$C$16:$I$27,MATCH(TEXT(C10,"mmm-yy"),Settings_FX!$B$16:$B$27,0),MATCH(J10,Settings_FX!$C$15:$I$15,0)),1) -> 5500 | M10: UAE | N10: =TEXT(C10,"mmm-yy") -> Feb-25
B11: INV-M-006 | C11: 45696 | D11: Feb-25 | E11: Emirates Retail Group | F11: Retargeting Feb | G11: 4000 | H11: 300 | I11: 3700 | J11: USD | K11: =I11+H11 -> 4000 | L11: =K11*IFERROR(INDEX(Settings_FX!$C$16:$I$27,MATCH(TEXT(C11,"mmm-yy"),Settings_FX!$B$16:$B$27,0),MATCH(J11,Settings_FX!$C$15:$I$15,0)),1) -> 4000 | M11: UAE | N11: =TEXT(C11,"mmm-yy") -> Feb-25
B12: INV-M-007 | C12: 45702 | D12: Feb-25 | E12: Gulf Tech Distribution | F12: Lead Gen Feb | G12: 6800 | H12: 550 | I12: 6250 | J12: USD | K12: =I12+H12 -> 6800 | L12: =K12*IFERROR(INDEX(Settings_FX!$C$16:$I$27,MATCH(TEXT(C12,"mmm-yy"),Settings_FX!$B$16:$B$27,0),MATCH(J12,Settings_FX!$C$15:$I$15,0)),1) -> 6800 | M12: UAE | N12: =TEXT(C12,"mmm-yy") -> Feb-25
B13: INV-M-008 | C13: 45720 | D13: Mar-25 | E13: Alphabet Logistics LLC | F13: WABA Mar promo | G13: 5800 | H13: 600 | I13: 5200 | J13: USD | K13: =I13+H13 -> 5800 | L13: =K13*IFERROR(INDEX(Settings_FX!$C$16:$I$27,MATCH(TEXT(C13,"mmm-yy"),Settings_FX!$B$16:$B$27,0),MATCH(J13,Settings_FX!$C$15:$I$15,0)),1) -> 5800 | M13: UAE | N13: =TEXT(C13,"mmm-yy") -> Mar-25
B14: INV-M-009 | C14: 45724 | D14: Mar-25 | E14: Abu Dhabi Trading | F14: Conversion Mar | G14: 4500 | H14: 400 | I14: 4100 | J14: USD | K14: =I14+H14 -> 4500 | L14: =K14*IFERROR(INDEX(Settings_FX!$C$16:$I$27,MATCH(TEXT(C14,"mmm-yy"),Settings_FX!$B$16:$B$27,0),MATCH(J14,Settings_FX!$C$15:$I$15,0)),1) -> 4500 | M14: UAE | N14: =TEXT(C14,"mmm-yy") -> Mar-25
B15: INV-M-010 | C15: 45728 | D15: Mar-25 | E15: Rak Bank Digital | F15: Brand Mar | G15: 7200 | H15: 600 | I15: 6600 | J15: USD | K15: =I15+H15 -> 7200 | L15: =K15*IFERROR(INDEX(Settings_FX!$C$16:$I$27,MATCH(TEXT(C15,"mmm-yy"),Settings_FX!$B$16:$B$27,0),MATCH(J15,Settings_FX!$C$15:$I$15,0)),1) -> 7200 | M15: UAE | N15: =TEXT(C15,"mmm-yy") -> Mar-25
B16: INV-M-011 | C16: 45734 | D16: Mar-25 | E16: Asia Pacific Solutions | F16: Lead Gen Mar SG | G16: 8500 | H16: 700 | I16: 7800 | J16: USD | K16: =I16+H16 -> 8500 | L16: =K16*IFERROR(INDEX(Settings_FX!$C$16:$I$27,MATCH(TEXT(C16,"mmm-yy"),Settings_FX!$B$16:$B$27,0),MATCH(J16,Settings_FX!$C$15:$I$15,0)),1) -> 8500 | M16: SG | N16: =TEXT(C16,"mmm-yy") -> Mar-25
B17: INV-M-012 | C17: 45741 | D17: Mar-25 | E17: Lion City Media | F17: WABA Mar SG | G17: 4300 | H17: 350 | I17: 3950 | J17: USD | K17: =I17+H17 -> 4300 | L17: =K17*IFERROR(INDEX(Settings_FX!$C$16:$I$27,MATCH(TEXT(C17,"mmm-yy"),Settings_FX!$B$16:$B$27,0),MATCH(J17,Settings_FX!$C$15:$I$15,0)),1) -> 4300 | M17: SG | N17: =TEXT(C17,"mmm-yy") -> Mar-25
... B28: INV-M-023 | C28: 45914 | D28: Sep-25 | E28: Jakarta Digital Ventures | F28: Lead Gen Sep SG | G28: 9800 | H28: 800 | I28: 9000 | J28: USD | K28: =I28+H28 -> 9800 | L28: =K28*IFERROR(INDEX(Settings_FX!$C$16:$I$27,MATCH(TEXT(C28,"mmm-yy"),Settings_FX!$B$16:$B$27,0),MATCH(J28,Settings_FX!$C$15:$I$15,0)),1) -> 9800 | M28: SG | N28: =TEXT(C28,"mmm-yy") -> Sep-25
B29: TOTAL | G29: =SUM(G6:G28) -> 133600 | H29: =SUM(H6:H28) -> 11650 | I29: =SUM(I6:I28) -> 121950 | K29: =SUM(K6:K28) -> 133600 | L29: =SUM(L6:L28) -> 133600

Sheet Settings_FX
B2: Settings & FX Rates
B3: Edit blue cells only — yellow highlights = key assumptions
B5: A · COMPANY SETTINGS
B6: UAE Company Name | C6: Acme FZ-LLC | D6: AED
B7: Singapore Company Name | C7: Acme Pte Ltd | D7: SGD
B8: Reporting Base Currency | C8: USD
B9: Stripe Account Currency | C9: USD
B10: Stripe Fee % (typical) | C10: 0.029
B11: Stripe Fixed Fee | C11: 0.3
B14: B · FX RATES TO USD (editable — update monthly)
B15: Month | C15: USD | D15: AED | E15: SGD | F15: EUR | G15: GBP | H15: INR | I15: PKR
B16: Jan-25 | C16: 1 | D16: 0.2723 | E16: 0.743 | F16: 1.082 | G16: 1.265 | H16: 0.0115 | I16: 0.0036
B17: Feb-25 | C17: 1 | D17: 0.2723 | E17: 0.743 | F17: 1.054 | G17: 1.268 | H17: 0.0115 | I17: 0.0036
B18: Mar-25 | C18: 1 | D18: 0.2723 | E18: 0.743 | F18: 1.082 | G18: 1.275 | H18: 0.0116 | I18: 0.0036
B19: Apr-25 | C19: 1 | D19: 0.2723 | E19: 0.7435 | F19: 1.135 | G19: 1.298 | H19: 0.0118 | I19: 0.0036
B20: May-25 | C20: 1 | D20: 0.2723 | E20: 0.744 | F20: 1.124 | G20: 1.312 | H20: 0.0118 | I20: 0.0036
B21: Jun-25 | C21: 1 | D21: 0.2723 | E21: 0.744 | F21: 1.146 | G21: 1.332 | H21: 0.0118 | I21: 0.0036
B22: Jul-25 | C22: 1 | D22: 0.2723 | E22: 0.7445 | F22: 1.154 | G22: 1.345 | H22: 0.0119 | I22: 0.0036
B23: Aug-25 | C23: 1 | D23: 0.2723 | E23: 0.745 | F23: 1.115 | G23: 1.328 | H23: 0.0119 | I23: 0.0036
B24: Sep-25 | C24: 1 | D24: 0.2723 | E24: 0.7455 | F24: 1.118 | G24: 1.338 | H24: 0.012 | I24: 0.0036
B25: Oct-25 | C25: 1 | D25: 0.2723 | E25: 0.746 | F25: 1.089 | G25: 1.305 | H25: 0.012 | I25: 0.0036
B26: Nov-25 | C26: 1 | D26: 0.2723 | E26: 0.7465 | F26: 1.056 | G26: 1.27 | H26: 0.012 | I26: 0.0036
B27: Dec-25 | C27: 1 | D27: 0.2723 | E27: 0.747 | F27: 1.041 | G27: 1.254 | H27: 0.012 | I27: 0.0036
B30: C · CUSTOMER MASTER
B31: Customer ID | C31: Customer Name | D31: Entity | E31: Default Currency | F31: Primary Category | G31: Country | H31: Active?
B32: C001 | C32: Alphabet Logistics LLC | D32: UAE | E32: AED | F32: WhatsApp | G32: UAE | H32: Yes
B33: C002 | C33: Emirates Retail Group | D33: UAE | E33: AED | F33: Subscription | G33: UAE | H33: Yes
B34: C003 | C34: Gulf Tech Distribution | D34: UAE | E34: USD | F34: Development | G34: UAE | H34: Yes
B35: C004 | C35: Dubai Properties Co | D35: UAE | E35: AED | F35: WhatsApp | G35: UAE | H35: Yes
B36: C005 | C36: Abu Dhabi Trading | D36: UAE | E36: AED | F36: Subscription | G36: UAE | H36: Yes
B37: C006 | C37: Rak Bank Digital | D37: UAE | E37: AED | F37: Development | G37: UAE | H37: Yes
B38: C007 | C38: Singapore FinTech Hub | D38: SG | E38: SGD | F38: WhatsApp | G38: SG | H38: Yes
B39: C008 | C39: Asia Pacific Solutions | D39: SG | E39: USD | F39: Development | G39: SG | H39: Yes
B40: C009 | C40: Marina Bay Holdings | D40: SG | E40: SGD | F40: Subscription | G40: SG | H40: Yes
B41: C010 | C41: Lion City Media | D41: SG | E41: SGD | F41: WhatsApp | G41: SG | H41: Yes
B42: C011 | C42: Sentosa E-Commerce | D42: SG | E42: USD | F42: Subscription | G42: SG | H42: Yes
... B46: C015 | C46: Jakarta Digital Ventures | D46: SG | E46: USD | F46: Development | G46: SG | H46: Yes
B49: D · REVENUE CATEGORY MAPPING (Stripe tag → Category)
B50: Stripe Tag / SKU | C50: Revenue Category | D50: P&L Line
B51: waba_msg | C51: WhatsApp | D51: WhatsApp Revenue
B52: waba_setup | C52: WhatsApp | D52: WhatsApp Revenue
B53: sub_monthly | C53: Subscription | D53: Subscription Revenue
B54: sub_annual | C54: Subscription | D54: Subscription Revenue
B55: dev_hourly | C55: Development | D55: Development Revenue
B56: dev_fixed | C56: Development | D56: Development Revenue
B57: dev_retainer | C57: Development | D57: Development Revenue
B58: oneoff_service | C58: Other Services | D58: Other Services Revenue
B59: consulting | C59: Other Services | D59: Other Services Revenue
B60: training | C60: Other Services | D60: Other Services Revenue
B61: integration | C61: Other Services | D61: Other Services Revenue
B62: premium_support | C62: Other Services | D62: Other Services Revenue
